Workbook
Name Print_Area: consolidé!$A$1:$S$83
Name Print_Area: Consultants!#REF!
Name Print_Area: 'Facturation Client'!$A$1:$M$50
Name Print_Area: 'Société A'!$A$1:$O$68
Name Print_Area: 'Société B'!$A$1:$O$69
Name Print_Area: 'Société C-1'!$A$1:$O$70
Name Print_Area: 'Société C-2'!$A$1:$O$36

Sheet Tableau de Bord
A1: TABLEAU DE BORD - SUIVI DE PROJET CONSORTIUM
A3: 1. SYNTHÈSE GLOBALE DU PROJET
A5: Budget Total Projet | B5: 6600000 | C5: (À renseigner)
A6: Total Facturé Client | B6: ='Facturation Client'!I50 -> 6249636.2
A7: Reste à Facturer (RAF) | B7: =B5-B6 -> 350363.77
A8: % Avancement Facturation | B8: =IF(B5=0,0,B6/B5) -> 0.94691458
A9: Total Heures Consommées | B9: =consolidé!D82 -> 57354.55 | C9: heures
A10: Total Dépenses | B10: =consolidé!O68 -> 68994.88
A12: 2. RÉCAPITULATIF PAR PROJET
A14: Projet | B14: Budget | C14: Facturé | D14: RAF | E14: % Avancement | F14: Heures Budget | G14: Heures Réalisées | H14: Heures RAF | I14: % Heures
A15: Projet A | B15: ='Facturation Client'!E4 -> 2510239.2 | C15: ='Facturation Client'!E50 -> 2430239.7 | D15: =B15-C15 -> 79999.507 | E15: =IF(B15=0,0,C15/B15) -> 0.96813072 | F15: 31500 | G15: ='Société A'!E69 -> 30652.15 | H15: =F15-G15 -> 847.85 | I15: =IF(F15=0,0,G15/F15) -> 0.97308413
A16: Projet B | B16: ='Facturation Client'!F4 -> 1309691.7 | C16: ='Facturation Client'!F50 -> 1265663.3 | D16: =B16-C16 -> 44028.437 | E16: =IF(B16=0,0,C16/B16) -> 0.96638259 | F16: 12450 | G16: ='Société B'!E70 -> 12146 | H16: =F16-G16 -> 304 | I16: =IF(F16=0,0,G16/F16) -> 0.97558233
A17: Projet C | B17: ='Facturation Client'!G4 -> 1303576.4 | C17: ='Facturation Client'!G50 -> 1261810.7 | D17: =B17-C17 -> 41765.657 | E17: =IF(B17=0,0,C17/B17) -> 0.96796071 | F17: 12100 | G17: ='Société B'!E70 -> 12146 | H17: =F17-G17 -> -46 | I17: =IF(F17=0,0,G17/F17) -> 1.0038017
A18: Projet D | B18: ='Facturation Client'!H4 -> 1332362.9 | C18: ='Facturation Client'!H50 -> 1291922.5 | D18: =B18-C18 -> 40440.367 | E18: =IF(B18=0,0,C18/B18) -> 0.96964763 | F18: 31250 | G18: ='Société A'!E69 -> 30652.15 | H18: =F18-G18 -> 597.85 | I18: =IF(F18=0,0,G18/F18) -> 0.9808688
A19: TOTAL | B19: =SUM(B15:B18) -> 6455870.2 | C19: =SUM(C15:C18) -> 6249636.2 | D19: =SUM(D15:D18) -> 206233.97 | E19: =IF(B19=0,0,C19/B19) -> 0.96805481 | F19: =SUM(F15:F18) -> 87300 | G19: =SUM(G15:G18) -> 85596.3 | H19: =SUM(H15:H18) -> 1703.7 | I19: =IF(F19=0,0,G19/F19) -> 0.98048454
A22: 3. RÉCAPITULATIF PAR SOCIÉTÉ
A24: Société | B24: Part Budget | C24: Honoraires Facturés | D24: Dépenses | E24: Total Coûts | F24: RAF Estimé | G24: % Avancement | H24: Heures Budget | I24: Heures Réalisées | J24: Heures RAF | K24: % Heures
A25: Société A | B25: 3250000 | C25: ='Société A'!I68 -> 2285817.9 | D25: ='Société A'!H68 -> 45519.14 | E25: =C25+D25 -> 2331337 | F25: =B25-E25 -> 918662.97 | G25: =IF(B25=0,0,E25/B25) -> 0.71733447 | H25: 43948.374 | I25: 39650 | J25: =H25-I25 -> 4298.3743 | K25: =IF(H25=0,0,I25/H25) -> 0.90219492
A26: Société B | B26: =B16 -> 1309691.7 | C26: ='Société B'!I69 -> 762524.29 | D26: ='Société B'!H69 -> 20480.56 | E26: =C26+D26 -> 783004.85 | F26: =B26-E26 -> 526686.85 | G26: =IF(B26=0,0,E26/B26) -> 0.59785433 | H26: 17710.406 | I26: 16554 | J26: =H26-I26 -> 1156.4065 | K26: =IF(H26=0,0,I26/H26) -> 0.93470469
A27: Société C-1 | B27: =B17 -> 1303576.4 | C27: ='Société C-1'!I70 -> 889034.68 | D27: ='Société C-1'!H70 -> 2631.18 | E27: =C27+D27 -> 891665.86 | F27: =B27-E27 -> 411910.54 | G27: =IF(B27=0,0,E27/B27) -> 0.68401504 | H27: 17627.712 | I27: 17023 | J27: =H27-I27 -> 604.71186 | K27: =IF(H27=0,0,I27/H27) -> 0.96569539
A28: Société C-2 | B28: 592602.1 | C28: ='Société C-2'!I36 -> 103413.73 | D28: ='Société C-2'!H36 -> 364 | E28: =C28+D28 -> 103777.73 | F28: =B28-E28 -> 488824.37 | G28: =IF(B28=0,0,E28/B28) -> 0.17512211 | H28: 8013.5074 | I28: 12369.3 | J28: =H28-I28 -> -4355.7926 | K28: =IF(H28=0,0,I28/H28) -> 1.5435563
A29: TOTAL | B29: =SUM(B25:B28) -> 6455870.2 | C29: =SUM(C25:C28) -> 4040790.6 | D29: =SUM(D25:D28) -> 68994.88 | E29: =SUM(E25:E28) -> 4109785.5 | F29: =SUM(F25:F28) -> 2346084.7 | G29: =IF(B29=0,0,E29/B29) -> 0.63659667 | H29: =SUM(H25:H28) -> 87300 | I29: =SUM(I25:I28) -> 85596.3 | J29: =SUM(J25:J28) -> 1703.7 | K29: =IF(H29=0,0,I29/H29) -> 0.98048454
A32: 4. MATRICE PROJETS x SOCIÉTÉS (Facturation)
A34: Projet \ Société | B34: Société A | C34: Société B | D34: Société C | E34: Total Projet | F34: % du Total
A35: Projet A | B35: ='Facturation Client'!E50*0.5 -> 1215119.8 | C35: ='Facturation Client'!E50*0.25 -> 607559.92 | D35: ='Facturation Client'!E50*0.25 -> 607559.92 | E35: =SUM(B35:D35) -> 2430239.7 | F35: =IF($E$39=0,0,E35/$E$39) -> 0.38886098
A36: Projet B | B36: ='Facturation Client'!F50*0.5 -> 632831.63 | C36: ='Facturation Client'!F50*0.25 -> 316415.82 | D36: ='Facturation Client'!F50*0.25 -> 316415.82 | E36: =SUM(B36:D36) -> 1265663.3 | F36: =IF($E$39=0,0,E36/$E$39) -> 0.20251791
A37: Projet C | B37: ='Facturation Client'!G50*0.5 -> 630905.37 | C37: ='Facturation Client'!G50*0.25 -> 315452.69 | D37: ='Facturation Client'!G50*0.25 -> 315452.69 | E37: =SUM(B37:D37) -> 1261810.7 | F37: =IF($E$39=0,0,E37/$E$39) -> 0.20190147
A38: Projet D | B38: ='Facturation Client'!H50*0.5 -> 645961.27 | C38: ='Facturation Client'!H50*0.25 -> 322980.63 | D38: ='Facturation Client'!H50*0.25 -> 322980.63 | E38: =SUM(B38:D38) -> 1291922.5 | F38: =IF($E$39=0,0,E38/$E$39) -> 0.20671964
A39: Total Société | B39: =SUM(B35:B38) -> 3124818.1 | C39: =SUM(C35:C38) -> 1562409.1 | D39: =SUM(D35:D38) -> 1562409.1 | E39: =SUM(E35:E38) -> 6249636.2 | F39: =SUM(F35:F38) -> 1
A40: % par Société | B40: =IF($E$39=0,0,B39/$E$39) -> 0.5 | C40: =IF($E$39=0,0,C39/$E$39) -> 0.25 | D40: =IF($E$39=0,0,D39/$E$39) -> 0.25 | E40: =SUM(B40:D40) -> 1
A43: 5. INDICATEURS CLÉS DE PERFORMANCE
A45: HEURES
A46: Heures Budget Total | B46: =F19 -> 87300 | C46: (À renseigner)
A47: Heures Réalisées Total | B47: =consolidé!D82 -> 57354.55
A48: Heures Restantes (RAF) | B48: =B46-B47 -> 29945.45
A49: % Heures Consommées | B49: =IF(B46=0,0,B47/B46) -> 0.65698225
A51: FINANCES
A52: Taux Horaire Moyen Réalisé | B52: =IF(B47=0,0,B6/B47) -> 108.96496 | C52: $/heure
A53: Ratio Honoraires/Budget | B53: =IF(B5=0,0,consolidé!N68/B5) -> 0.60178723
A54: Consultants Externes | B54: =consolidé!Q68 -> 450633.01
A55: Marge Estimée (Budget - Coûts) | B55: =B5-consolidé!N68-consolidé!O68-consolidé!Q68 -> 2108576.4
A57: LÉGENDE ET NOTES
A58: ● Cellules jaunes avec texte bleu = Données à renseigner (Budget, Heures prévues)
A59: ● RAF = Reste À Faire (Budget - Réalisé)

Sheet consolidé
B1: HONORAIRES SONT À UN TAUX DE 1.9
B2: Société C | E2: Société C | H2: Société B | K2: Société A | N2: totaux
A3: période | B3: Honoraires associés | C3: Honoraires employés | D3: DEP | E3: Honoraires associés | F3: Honoraires employés | G3: DEP | H3: Honoraires associés | I3: Honoraires employés | J3: DEP | K3: Honoraires associés | L3: Honoraires employés | M3: DEP | N3: HONOR | O3: DEP | P3: Facture au client | Q3: Consultants | R3: Ratio par période | S3: Profit
A4: 1er mai au 1 août 2020 | B4: =+'Société C-1'!F4 -> 0 | C4: =+'Société C-1'!G4 -> 25530.13 | D4: =+'Société C-1'!H4 -> 372.18 | E4: =+'Société C-2'!F4 -> 0 | F4: =+'Société C-2'!G4 -> 0 | G4: =+'Société C-2'!H4 -> 0 | H4: =+'Société B'!F4 -> 5218.75 | I4: =+'Société B'!G4 -> 22959.22 | J4: =+'Société B'!H4 -> 0 | K4: =+'Société A'!F4 -> 29893.75 | L4: =+'Société A'!G4 -> 15393.69 | M4: =+'Société A'!H4 -> 6075.25 | N4: =+B4+C4+E4+F4+H4+I4+K4+L4 -> 98995.54 | O4: =+D4+G4+M4+J4 -> 6447.43 | P4: =+'Facturation Client'!I5 -> 0 | Q4: 0 | R4: =(P4-O4-Q4)/(N4/1.9) -> -0.12374413 | S4: =+P4-N4-O4-Q4 -> -105442.97
A5: 44044 | B5: =+'Société C-1'!F5 -> 0 | C5: =+'Société C-1'!G5 -> 14942.08 | D5: =+'Société C-1'!H5 -> 131.5 | E5: =+'Société C-2'!F5 -> 1656.25 | F5: =+'Société C-2'!G5 -> 369.25 | G5: =+'Société C-2'!H5 -> 0 | H5: =+'Société B'!F5 -> 1062.5 | I5: =+'Société B'!G5 -> 18334.67 | J5: =+'Société B'!H5 -> 0 | K5: =+'Société A'!F5 -> 17850 | L5: =+'Société A'!G5 -> 15023.6 | M5: =+'Société A'!H5 -> 0 | N5: =+B5+C5+E5+F5+H5+I5+K5+L5 -> 69238.35 | O5: =+D5+G5+M5+J5 -> 131.5 | P5: =+'Facturation Client'!I6 -> 275812.61 | Q5: 0 | R5: =(P5-O5-Q5)/(N5/1.9) -> 7.5650865 | S5: =+P5-N5-O5-Q5 -> 206442.76
A6: 44075 | B6: =+'Société C-1'!F6 -> 437.5 | C6: =+'Société C-1'!G6 -> 44540.91 | D6: =+'Société C-1'!H6 -> 120.32 | E6: =+'Société C-2'!F6 -> 512.5 | F6: =+'Société C-2'!G6 -> 9144.25 | G6: =+'Société C-2'!H6 -> 200.35 | H6: =+'Société B'!F6 -> 1937.5 | I6: =+'Société B'!G6 -> 26068.52 | J6: =+'Société B'!H6 -> 3877.5 | K6: =+'Société A'!F6 -> 37762.5 | L6: =+'Société A'!G6 -> 34256.1 | M6: =+'Société A'!H6 -> 293.45 | N6: =+B6+C6+E6+F6+H6+I6+K6+L6 -> 154659.78 | O6: =+D6+G6+M6+J6 -> 4491.62 | P6: =+'Facturation Client'!I7 -> 245169.32 | Q6: 0 | R6: =(P6-O6-Q6)/(N6/1.9) -> 2.9567327 | S6: =+P6-N6-O6-Q6 -> 86017.92
A7: 44105 | B7: =+'Société C-1'!F7 -> 0 | C7: =+'Société C-1'!G7 -> 34001.71 | D7: =+'Société C-1'!H7 -> 157.65 | E7: =+'Société C-2'!F7 -> 256.25 | F7: =+'Société C-2'!G7 -> 10624.75 | G7: =+'Société C-2'!H7 -> 0 | H7: =+'Société B'!F7 -> 2031.25 | I7: =+'Société B'!G7 -> 35031.21 | J7: =+'Société B'!H7 -> 0 | K7: =+'Société A'!F7 -> 38250 | L7: =+'Société A'!G7 -> 38774.44 | M7: =+'Société A'!H7 -> 0 | N7: =+B7+C7+E7+F7+H7+I7+K7+L7 -> 158969.61 | O7: =+D7+G7+M7+J7 -> 157.65 | P7: =+'Facturation Client'!I8 -> 261771.33 | Q7: =387.5+1950 -> 2337.5 | R7: =(P7-O7-Q7)/(N7/1.9) -> 3.0988611 | S7: =+P7-N7-O7-Q7 -> 100306.57
A8: 44136 | B8: =+'Société C-1'!F8 -> 0 | C8: =+'Société C-1'!G8 -> 42751.38 | D8: =+'Société C-1'!H8 -> 0 | E8: =+'Société C-2'!F8 -> 381.25 | F8: =+'Société C-2'!G8 -> 11885.45 | G8: =+'Société C-2'!H8 -> 0 | H8: =+'Société B'!F8 -> 1531.25 | I8: =+'Société B'!G8 -> 31719.51 | J8: =+'Société B'!H8 -> 0 | K8: =+'Société A'!F8 -> 35681.25 | L8: =+'Société A'!G8 -> 34580.05 | M8: =+'Société A'!H8 -> 0 | N8: =+B8+C8+E8+F8+H8+I8+K8+L8 -> 158530.14 | O8: =+D8+G8+M8+J8 -> 0 | P8: =+'Facturation Client'!I9 -> 318143.25 | Q8: =1540+1445+1760+5100+2390 -> 12235 | R8: =(P8-O8-Q8)/(N8/1.9) -> 3.6663418 | S8: =+P8-N8-O8-Q8 -> 147378.11
A9: 44166 | B9: =+'Société C-1'!F9 -> 312.5 | C9: =+'Société C-1'!G9 -> 33356.76 | D9: =+'Société C-1'!H9 -> 268.58 | E9: =+'Société C-2'!F9 -> 256.25 | F9: =+'Société C-2'!G9 -> 12697.04 | G9: =+'Société C-2'!H9 -> 0 | H9: =+'Société B'!F9 -> 2000 | I9: =+'Société B'!G9 -> 38933.39 | J9: =+'Société B'!H9 -> 0 | K9: =+'Société A'!F9 -> 28606.25 | L9: =+'Société A'!G9 -> 31501.67 | M9: =+'Société A'!H9 -> 178.9 | N9: =+B9+C9+E9+F9+H9+I9+K9+L9 -> 147663.86 | O9: =+D9+G9+M9+J9 -> 447.48 | P9: =+'Facturation Client'!I10 -> 254673.02 | Q9: =16812.5+7855+14775+8160+8790 -> 56392.5 | R9: =(P9-O9-Q9)/(N9/1.9) -> 2.5455299 | S9: =+P9-N9-O9-Q9 -> 50169.18
A10: 44197 | B10: =+'Société C-1'!F10 -> 0 | C10: =+'Société C-1'!G10 -> 48962.88 | D10: =+'Société C-1'!H10 -> 13 | E10: =+'Société C-2'!F10 -> 250 | F10: =+'Société C-2'!G10 -> 17698.5 | G10: =+'Société C-2'!H10 -> 0 | H10: =+'Société B'!F10 -> 1500 | I10: =+'Société B'!G10 -> 42429.39 | J10: =+'Société B'!H10 -> 0 | K10: =+'Société A'!F10 -> 32043.75 | L10: =+'Société A'!G10 -> 40191.3 | M10: =+'Société A'!H10 -> 0 | N10: =+B10+C10+E10+F10+H10+I10+K10+L10 -> 183075.82 | O10: =+D10+G10+M10+J10 -> 13 | P10: =+'Facturation Client'!I11 -> 961930 | Q10: =745+19315+5400+6900+7200+3600+6650+8450+16425+6100 -> 80785 | R10: =(P10-O10-Q10)/(N10/1.9) -> 9.1445763 | S10: =+P10-N10-O10-Q10 -> 698056.18
A11: 44228 | B11: =+'Société C-1'!F11 -> 125 | C11: =+'Société C-1'!G11 -> 53139.43 | D11: =+'Société C-1'!H11 -> 0 | E11: =+'Société C-2'!F11 -> 1150 | F11: =+'Société C-2'!G11 -> 16934.05 | G11: =+'Société C-2'!H11 -> 0 | H11: =+'Société B'!F11 -> 1406.25 | I11: =+'Société B'!G11 -> 37715.2 | J11: =+'Société B'!H11 -> 0 | K11: =+'Société A'!F11 -> 30793.75 | L11: =+'Société A'!G11 -> 58682.04 | M11: =+'Société A'!H11 -> 2117.25 | N11: =+B11+C11+E11+F11+H11+I11+K11+L11 -> 199945.72 | O11: =+D11+G11+M11+J11 -> 2117.25 | P11: =+'Facturation Client'!I12 -> 0 | Q11: =323.75+4430+1333+23211.25+6480 -> 35778 | R11: =(P11-O11-Q11)/(N11/1.9) -> -0.36010261 | S11: =+P11-N11-O11-Q11 -> -237840.97
A12: 44256 | B12: =+'Société C-1'!F12 -> 0 | C12: =+'Société C-1'!G12 -> 17723.03 | D12: =+'Société C-1'!H12 -> 0 | E12: =+'Société C-2'!F12 -> 0 | F12: =+'Société C-2'!G12 -> 19233.94 | G12: =+'Société C-2'!H12 -> 163.65 | H12: =+'Société B'!F12 -> 1125 | I12: =+'Société B'!G12 -> 33288.08 | J12: =+'Société B'!H12 -> 0 | K12: =+'Société A'!F12 -> 22350 | L12: =+'Société A'!G12 -> 61740.45 | M12: =+'Société A'!H12 -> 268.25 | N12: =+B12+C12+E12+F12+H12+I12+K12+L12 -> 155460.5 | O12: =+D12+G12+M12+J12 -> 431.9 | P12: =+'Facturation Client'!I13 -> 0 | Q12: =1138.75+15100+8625+1800+1800+1800 -> 30263.75 | R12: =(P12-O12-Q12)/(N12/1.9) -> -0.37515469 | S12: =+P12-N12-O12-Q12 -> -186156.15
A13: 44287 | B13: =+'Société C-1'!F13 -> 500 | C13: =+'Société C-1'!G13 -> 29209.98 | D13: =+'Société C-1'!H13 -> 0 | E13: =+'Société C-2'!F13 -> 0 | F13: =+'Société C-2'!G13 -> 0 | G13: =+'Société C-2'!H13 -> 0 | H13: =+'Société B'!F13 -> 1187.5 | I13: =+'Société B'!G13 -> 23508.68 | J13: =+'Société B'!H13 -> 0 | K13: =+'Société A'!F13 -> 17325 | L13: =+'Société A'!G13 -> 50371.35 | M13: =+'Société A'!H13 -> 73.93 | N13: =+B13+C13+E13+F13+H13+I13+K13+L13 -> 122102.51 | O13: =+D13+G13+M13+J13 -> 73.93 | P13: =+'Facturation Client'!I14 -> 0 | Q13: =2282.5+4230+3600+2700+1725 -> 14537.5 | R13: =(P13-O13-Q13)/(N13/1.9) -> -0.22736402 | S13: =+P13-N13-O13-Q13 -> -136713.94
A14: 44317 | B14: =+'Société C-1'!F14 -> 500 | C14: =+'Société C-1'!G14 -> 11109.31 | D14: =+'Société C-1'!H14 -> 0 | E14: =+'Société C-2'!F14 -> 0 | F14: =+'Société C-2'!G14 -> 0 | G14: =+'Société C-2'!H14 -> 0 | H14: =+'Société B'!F14 -> 656.25 | I14: =+'Société B'!G14 -> 15562.81 | J14: =+'Société B'!H14 -> 0 | K14: =+'Société A'!F14 -> 12037.5 | L14: =+'Société A'!G14 -> 22791.9 | M14: =+'Société A'!H14 -> 4.3 | N14: =+B14+C14+E14+F14+H14+I14+K14+L14 -> 62657.77 | O14: =+D14+G14+M14+J14 -> 4.3 | P14: =+'Facturation Client'!I15 -> 0 | Q14: =9750+3337.5+6105+2700+1800 -> 23692.5 | R14: =(P14-O14-Q14)/(N14/1.9) -> -0.71856882 | S14: =+P14-N14-O14-Q14 -> -86354.57
A15: 44348 | B15: =+'Société C-1'!F15 -> 500 | C15: =+'Société C-1'!G15 -> 5839.36 | D15: =+'Société C-1'!H15 -> 0 | E15: =+'Société C-2'!F15 -> 0 | F15: =+'Société C-2'!G15 -> 0 | G15: =+'Société C-2'!H15 -> 0 | H15: =+'Société B'!F15 -> 531.25 | I15: =+'Société B'!G15 -> 16538.39 | J15: =+'Société B'!H15 -> 0 | K15: =+'Société A'!F15 -> 10156.25 | L15: =+'Société A'!G15 -> 13574 | M15: =+'Société A'!H15 -> 0 | N15: =+B15+C15+E15+F15+H15+I15+K15+L15 -> 47139.25 | O15: =+D15+G15+M15+J15 -> 0 | P15: =+'Facturation Client'!I16 -> 0 | Q15: =416.25+885 -> 1301.25 | R15: =(P15-O15-Q15)/(N15/1.9) -> -0.052448331 | S15: =+P15-N15-O15-Q15 -> -48440.5
A16: 44378 | B16: =+'Société C-1'!F16 -> 375 | C16: =+'Société C-1'!G16 -> 769.98 | D16: =+'Société C-1'!H16 -> 0 | E16: =+'Société C-2'!F16 -> 0 | F16: =+'Société C-2'!G16 -> 0 | G16: =+'Société C-2'!H16 -> 0 | H16: =+'Société B'!F16 -> 250 | I16: =+'Société B'!G16 -> 6258.36 | J16: =+'Société B'!H16 -> 0 | K16: =+'Société A'!F16 -> 6575 | L16: =+'Société A'!G16 -> 5254.93 | M16: =+'Société A'!H16 -> 0 | N16: =+B16+C16+E16+F16+H16+I16+K16+L16 -> 19483.27 | O16: =+D16+G16+M16+J16 -> 0 | P16: =+'Facturation Client'!I17 -> 0 | Q16: 0 | R16: =(P16-O16-Q16)/(N16/1.9) -> 0 | S16: =+P16-N16-O16-Q16 -> -19483.27
A17: 44409 | B17: =+'Société C-1'!F17 -> 625 | C17: =+'Société C-1'!G17 -> 1253.53 | D17: =+'Société C-1'!H17 -> 0 | E17: =+'Société C-2'!F17 -> 0 | F17: =+'Société C-2'!G17 -> 0 | G17: =+'Société C-2'!H17 -> 0 | H17: =+'Société B'!F17 -> 656.25 | I17: =+'Société B'!G17 -> 9237.13 | J17: =+'Société B'!H17 -> 0 | K17: =+'Société A'!F17 -> 8306.25 | L17: =+'Société A'!G17 -> 6048.44 | M17: =+'Société A'!H17 -> 12.78 | N17: =+B17+C17+E17+F17+H17+I17+K17+L17 -> 26126.6 | O17: =+D17+G17+M17+J17 -> 12.78 | P17: =+'Facturation Client'!I18 -> 1357024.2 | Q17: 0 | R17: =(P17-O17-Q17)/(N17/1.9) -> 98.685699 | S17: =+P17-N17-O17-Q17 -> 1330884.9
A18: 44440 | B18: =+'Société C-1'!F18 -> 1050 | C18: =+'Société C-1'!G18 -> 2684.23 | D18: =+'Société C-1'!H18 -> 0 | E18: =+'Société C-2'!F18 -> 0 | F18: =+'Société C-2'!G18 -> 0 | G18: =+'Société C-2'!H18 -> 0 | H18: =+'Société B'!F18 -> 843.75 | I18: =+'Société B'!G18 -> 21648.31 | J18: =+'Société B'!H18 -> 0 | K18: =+'Société A'!F18 -> 7581.25 | L18: =+'Société A'!G18 -> 2957.12 | M18: =+'Société A'!H18 -> 8951.52 | N18: =+B18+C18+E18+F18+H18+I18+K18+L18 -> 36764.66 | O18: =+D18+G18+M18+J18 -> 8951.52 | P18: =+'Facturation Client'!I19 -> 0 | Q18: =1800+4506.25+1800 -> 8106.25 | R18: =(P18-O18-Q18)/(N18/1.9) -> -0.88154665 | S18: =+P18-N18-O18-Q18 -> -53822.43
A19: 44470 | B19: =+'Société C-1'!F19 -> 125 | C19: =+'Société C-1'!G19 -> 2210.25 | D19: =+'Société C-1'!H19 -> 0 | E19: =+'Société C-2'!F19 -> 0 | F19: =+'Société C-2'!G19 -> 0 | G19: =+'Société C-2'!H19 -> 0 | H19: =+'Société B'!F19 -> 375 | I19: =+'Société B'!G19 -> 15127.17 | J19: =+'Société B'!H19 -> 2200 | K19: =+'Société A'!F19 -> 9312.5 | L19: =+'Société A'!G19 -> 7748.85 | M19: =+'Société A'!H19 -> 0 | N19: =+B19+C19+E19+F19+H19+I19+K19+L19 -> 34898.77 | O19: =+D19+G19+M19+J19 -> 2200 | P19: =+'Facturation Client'!I20 -> 0 | Q19: 2112.5 | R19: =(P19-O19-Q19)/(N19/1.9) -> -0.23478621 | S19: =+P19-N19-O19-Q19 -> -39211.27
A20: 44501 | B20: =+'Société C-1'!F20 -> 406.25 | C20: =+'Société C-1'!G20 -> 6131.78 | D20: =+'Société C-1'!H20 -> 0 | E20: =+'Société C-2'!F20 -> 0 | F20: =+'Société C-2'!G20 -> 0 | G20: =+'Société C-2'!H20 -> 0 | H20: =+'Société B'!F20 -> 250 | I20: =+'Société B'!G20 -> 19539.79 | J20: =+'Société B'!H20 -> 796.33 | K20: =+'Société A'!F20 -> 6275 | L20: =+'Société A'!G20 -> 9770.41 | M20: =+'Société A'!H20 -> 217.02 | N20: =+B20+C20+E20+F20+H20+I20+K20+L20 -> 42373.23 | O20: =+D20+G20+M20+J20 -> 1013.35 | P20: =+'Facturation Client'!I21 -> 0 | Q20: =811.25+5850+2380+1380 -> 10421.25 | R20: =(P20-O20-Q20)/(N20/1.9) -> -0.51272325 | S20: =+P20-N20-O20-Q20 -> -53807.83
A21: 44531 | B21: =+'Société C-1'!F21 -> 650 | C21: =+'Société C-1'!G21 -> 2476.18 | D21: =+'Société C-1'!H21 -> 0 | E21: =+'Société C-2'!F21 -> 0 | F21: =+'Société C-2'!G21 -> 0 | G21: =+'Société C-2'!H21 -> 0 | H21: =+'Société B'!F21 -> 312.5 | I21: =+'Société B'!G21 -> 11737.82 | J21: =+'Société B'!H21 -> 102.02 | K21: =+'Société A'!F21 -> 8375 | L21: =+'Société A'!G21 -> 8953.71 | M21: =+'Société A'!H21 -> 544.5 | N21: =+B21+C21+E21+F21+H21+I21+K21+L21 -> 32505.21 | O21: =+D21+G21+M21+J21 -> 646.52 | P21: =+'Facturation Client'!I22 -> 0 | Q21: =33.75+1380+2112.5+690 -> 4216.25 | R21: =(P21-O21-Q21)/(N21/1.9) -> -0.28423945 | S21: =+P21-N21-O21-Q21 -> -37367.98
A22: 44562 | B22: =+'Société C-1'!F22 -> 562.5 | C22: =+'Société C-1'!G22 -> 6365.71 | D22: =+'Société C-1'!H22 -> 0 | E22: =+'Société C-2'!F22 -> 0 | F22: =+'Société C-2'!G22 -> 0 | G22: =+'Société C-2'!H22 -> 0 | H22: =+'Société B'!F22 -> 5562.5 | I22: =+'Société B'!G22 -> 19426.59 | J22: =+'Société B'!H22 -> 0 | K22: =+'Société A'!F22 -> 9868.75 | L22: =+'Société A'!G22 -> 20838.4 | M22: =+'Société A'!H22 -> 0 | N22: =+B22+C22+E22+F22+H22+I22+K22+L22 -> 62624.45 | O22: =+D22+G22+M22+J22 -> 0 | P22: =+'Facturation Client'!I23 -> 0 | Q22: 0 | R22: =(P22-O22-Q22)/(N22/1.9) -> 0 | S22: =+P22-N22-O22-Q22 -> -62624.45
A23: 44593 | B23: =+'Société C-1'!F23 -> 375 | C23: =+'Société C-1'!G23 -> 3627.81 | D23: =+'Société C-1'!H23 -> 0 | E23: =+'Société C-2'!F23 -> 0 | F23: =+'Société C-2'!G23 -> 0 | G23: =+'Société C-2'!H23 -> 0 | H23: =+'Société B'!F23 -> 6906.25 | I23: =+'Société B'!G23 -> 16083.96 | J23: =+'Société B'!H23 -> 575.59 | K23: =+'Société A'!F23 -> 11168.75 | L23: =+'Société A'!G23 -> 18785.17 | M23: =+'Société A'!H23 -> 72.68 | N23: =+B23+C23+E23+F23+H23+I23+K23+L23 -> 56946.94 | O23: =+D23+G23+M23+J23 -> 648.27 | P23: =+'Facturation Client'!I24 -> 0 | Q23: =370+165 -> 535 | R23: =(P23-O23-Q23)/(N23/1.9) -> -0.039479084 | S23: =+P23-N23-O23-Q23 -> -58130.21
A24: 44621 | B24: =+'Société C-1'!F24 -> 625 | C24: =+'Société C-1'!G24 -> 11736.55 | D24: =+'Société C-1'!H24 -> 0 | E24: =+'Société C-2'!F24 -> 0 | F24: =+'Société C-2'!G24 -> 0 | G24: =+'Société C-2'!H24 -> 0 | H24: =+'Société B'!F24 -> 6781.25 | I24: =+'Société B'!G24 -> 15492.15 | J24: =+'Société B'!H24 -> 961.73 | K24: =+'Société A'!F24 -> 15418.75 | L24: =+'Société A'!G24 -> 21282.25 | M24: =+'Société A'!H24 -> 951.98 | N24: =+B24+C24+E24+F24+H24+I24+K24+L24 -> 71335.95 | O24: =+D24+G24+M24+J24 -> 1913.71 | P24: 0 | Q24: =1380+2800+2800+3963.75 -> 10943.75 | R24: =(P24-O24-Q24)/(N24/1.9) -> -0.34245249 | S24: =+P24-N24-O24-Q24 -> -84193.41
A25: 44652 | B25: =+'Société C-1'!F25 -> 500 | C25: =+'Société C-1'!G25 -> 5064.21 | D25: =+'Société C-1'!H25 -> 0 | E25: =+'Société C-2'!F25 -> 0 | F25: =+'Société C-2'!G25 -> 0 | G25: =+'Société C-2'!H25 -> 0 | H25: =+'Société B'!F25 -> 8656.25 | I25: =+'Société B'!G25 -> 16137.52 | J25: =+'Société B'!H25 -> 0 | K25: =+'Société A'!F25 -> 6006.25 | L25: =+'Société A'!G25 -> 13686.47 | M25: =+'Société A'!H25 -> 99.76 | N25: =+B25+C25+E25+F25+H25+I25+K25+L25 -> 50050.7 | O25: =+D25+G25+M25+J25 -> 99.76 | P25: ='Facturation Client'!I25 -> 266654.75 | Q25: =165+1380 -> 1545 | R25: =(P25-O25-Q25)/(N25/1.9) -> 10.060179 | S25: =+P25-N25-O25-Q25 -> 214959.29
A26: 44682 | B26: =+'Société C-1'!F26 -> 1843.75 | C26: =+'Société C-1'!G26 -> 9453.23 | D26: =+'Société C-1'!H26 -> 0 | E26: =+'Société C-2'!F26 -> 0 | F26: =+'Société C-2'!G26 -> 0 | G26: =+'Société C-2'!H26 -> 0 | H26: =+'Société B'!F26 -> 7250 | I26: =+'Société B'!G26 -> 11534.19 | J26: =+'Société B'!H26 -> 0 | K26: =+'Société A'!F26 -> 9850 | L26: =+'Société A'!G26 -> 17671.24 | M26: =+'Société A'!H26 -> 165 | N26: =+B26+C26+E26+F26+H26+I26+K26+L26 -> 57602.41 | O26: =+D26+G26+M26+J26 -> 165 | P26: 0 | Q26: =185+3168.75+1800+1056.25 -> 6210 | R26: =(P26-O26-Q26)/(N26/1.9) -> -0.21027766 | S26: =+P26-N26-O26-Q26 -> -63977.41
A27: 44713 | B27: =+'Société C-1'!F27 -> 2937.5 | C27: =+'Société C-1'!G27 -> 11283.64 | D27: =+'Société C-1'!H27 -> 289.05 | E27: =+'Société C-2'!F27 -> 0 | F27: =+'Société C-2'!G27 -> 0 | G27: =+'Société C-2'!H27 -> 0 | H27: =+'Société B'!F27 -> 7625 | I27: =+'Société B'!G27 -> 9188.16 | J27: =+'Société B'!H27 -> 1670.16 | K27: =+'Société A'!F27 -> 7800 | L27: =+'Société A'!G27 -> 23076.1 | M27: =+'Société A'!H27 -> 2216.32 | N27: =+B27+C27+E27+F27+H27+I27+K27+L27 -> 61910.4 | O27: =+D27+G27+M27+J27 -> 4175.53 | P27: 0 | Q27: =Consultants!E125 -> 2907.5 | R27: =(P27-O27-Q27)/(N27/1.9) -> -0.21737474 | S27: =+P27-N27-O27-Q27 -> -68993.43
A28: 44743 | B28: =+'Société C-1'!F28 -> 375 | C28: =+'Société C-1'!G28 -> 5257.89 | D28: =+'Société C-1'!H28 -> 0 | E28: =+'Société C-2'!F28 -> 0 | F28: =+'Société C-2'!G28 -> 0 | G28: =+'Société C-2'!H28 -> 0 | H28: =+'Société B'!F28 -> 3906.25 | I28: =+'Société B'!G28 -> 5253.93 | J28: =+'Société B'!H28 -> 0 | K28: =+'Société A'!F28 -> 5550 | L28: =+'Société A'!G28 -> 16860.14 | M28: =+'Société A'!H28 -> 213.5 | N28: =+B28+C28+E28+F28+H28+I28+K28+L28 -> 37203.21 | O28: =+D28+G28+M28+J28 -> 213.5 | P28: 0 | Q28: =Consultants!E126 -> 1380 | R28: =(P28-O28-Q28)/(N28/1.9) -> -0.081381418 | S28: =+P28-N28-O28-Q28 -> -38796.71
A29: 44774 | B29: =+'Société C-1'!F29 -> 375 | C29: =+'Société C-1'!G29 -> 12629.26 | D29: =+'Société C-1'!H29 -> 88.92 | E29: 0 | F29: 0 | G29: 0 | H29: =+'Société B'!F29 -> 3250 | I29: =+'Société B'!G29 -> 5174.43 | J29: =+'Société B'!H29 -> 1149.81 | K29: =+'Société A'!F29 -> 8237.5 | L29: =+'Société A'!G29 -> 23749.06 | M29: =+'Société A'!H29 -> 1269.4 | N29: =+B29+C29+E29+F29+H29+I29+K29+L29 -> 53415.25 | O29: =+D29+G29+M29+J29 -> 2508.13 | P29: 0 | Q29: =+Consultants!E127+Consultants!E128+Consultants!E129 -> 4506.25 | R29: =(P29-O29-Q29)/(N29/1.9) -> -0.24950406 | S29: =+P29-N29-O29-Q29 -> -60429.63
A30: 44805 | B30: =+'Société C-1'!F30 -> 687.5 | C30: =+'Société C-1'!G30 -> 10464.26 | D30: =+'Société C-1'!H30 -> 156.65 | E30: 0 | F30: 0 | G30: 0 | H30: =+'Société B'!F30 -> 4847.5 | I30: =+'Société B'!G30 -> 10878.93 | J30: =+'Société B'!H30 -> 1534.35 | K30: =+'Société A'!F30 -> 9925 | L30: =+'Société A'!G30 -> 22746.09 | M30: =+'Société A'!H30 -> 539.99 | N30: =+B30+C30+E30+F30+H30+I30+K30+L30 -> 59549.28 | O30: =+D30+G30+M30+J30 -> 2230.99 | P30: 0 | Q30: =+Consultants!E9+Consultants!E130 -> 4380 | R30: =(P30-O30-Q30)/(N30/1.9) -> -0.21093254 | S30: =+P30-N30-O30-Q30 -> -66160.27
A31: 44835 | B31: =+'Société C-1'!F31 -> 625 | C31: =+'Société C-1'!G31 -> 6067.18 | D31: =+'Société C-1'!H31 -> 0 | E31: 0 | F31: 0 | G31: 0 | H31: =+'Société B'!F31 -> 3511.25 | I31: =+'Société B'!G31 -> 6871.19 | J31: =+'Société B'!H31 -> 1797 | K31: =+'Société A'!F31 -> 13993.75 | L31: =+'Société A'!G31 -> 22905.71 | M31: =+'Société A'!H31 -> 401 | N31: =+B31+C31+E31+F31+H31+I31+K31+L31 -> 53974.08 | O31: =+D31+G31+M31+J31 -> 2198 | P31: ='Facturation Client'!I26 -> 481430.18 | Q31: =+Consultants!E10+Consultants!E131 -> 1026.25 | R31: =(P31-O31-Q31)/(N31/1.9) -> 16.833844 | S31: =+P31-N31-O31-Q31 -> 424231.85
A32: 44866 | B32: =+'Société C-1'!F32 -> 525 | C32: =+'Société C-1'!G32 -> 4507.28 | D32: =+'Société C-1'!H32 -> 0 | E32: 0 | F32: 0 | G32: 0 | H32: =+'Société B'!F32+'Société B'!F33 -> 8891.25 | I32: =+'Société B'!G32+'Société B'!G33 -> 8163.8 | J32: =+'Société B'!H32+'Société B'!H33 -> 2106.14 | K32: =+'Société A'!F32 -> 16493.75 | L32: =+'Société A'!G32 -> 23602.75 | M32: =+'Société A'!H32 -> 433 | N32: =+B32+C32+E32+F32+H32+I32+K32+L32 -> 62183.83 | O32: =+D32+G32+M32+J32 -> 2539.14 | P32: 0 | Q32: =+Consultants!E11+Consultants!E12+Consultants!E132+Consultants!E133+Consultants!E134 -> 13417.5 | R32: =(P32-O32-Q32)/(N32/1.9) -> -0.48754823 | S32: =+P32-N32-O32-Q32 -> -78140.47
A33: 44896 | B33: =+'Société C-1'!F33+'Société C-1'!F39 -> 687.5 | C33: =+'Société C-1'!G33+'Société C-1'!G39 -> 102561.73 | D33: =+'Société C-1'!H33+'Société C-1'!H39 -> 0 | E33: 0 | F33: 0 | G33: 0 | H33: ='Société B'!F34 -> 3125 | I33: ='Société B'!G34 -> 3752.73 | J33: ='Société B'!H34 -> 106.39 | K33: =+'Société A'!F33 -> 17868.75 | L33: =+'Société A'!G33 -> 23507.04 | M33: =+'Société A'!H33 -> 275 | N33: =+B33+C33+E33+F33+H33+I33+K33+L33 -> 151502.75 | O33: =+D33+G33+M33+J33 -> 381.39 | P33: =+'Facturation Client'!I27 -> 116846.91 | Q33: =Consultants!E135+Consultants!E136+Consultants!E13 -> 3041.25 | R33: =(P33-O33-Q33)/(N33/1.9) -> 1.4224568 | S33: =+P33-N33-O33-Q33 -> -38078.48
A34: 44927 | B34: =+'Société C-1'!F34 -> 500 | C34: =+'Société C-1'!G34 -> 2971.13 | D34: =+'Société C-1'!H34 -> 0 | E34: 0 | F34: 0 | G34: 0 | H34: ='Société B'!F35 -> 2906.25 | I34: ='Société B'!G35 -> 4801.78 | J34: ='Société B'!H35 -> 510.86 | K34: =+'Société A'!F34 -> 12825 | L34: =+'Société A'!G34 -> 20976.49 | M34: =+'Société A'!H34 -> 275 | N34: =+B34+C34+E34+F34+H34+I34+K34+L34 -> 44980.65 | O34: =+D34+G34+M34+J34 -> 785.86 | P34: 0 | Q34: =+Consultants!E14+Consultants!E54+Consultants!E137+Consultants!E138 -> 17260 | R34: =(P34-O34-Q34)/(N34/1.9) -> -0.76226408 | S34: =+P34-N34-O34-Q34 -> -63026.51
A35: 44958 | B35: =+'Société C-1'!F35 -> 625 | C35: =+'Société C-1'!G35 -> 6775.78 | D35: =+'Société C-1'!H35 -> 0 | E35: 0 | F35: 0 | G35: 0 | H35: ='Société B'!F36 -> 4281.25 | I35: ='Société B'!G36 -> 5131.9 | J35: ='Société B'!H36 -> 212.78 | K35: =+'Société A'!F35 -> 15775 | L35: =+'Société A'!G35 -> 31779.42 | M35: =+'Société A'!H35 -> 395.5 | N35: =+B35+C35+E35+F35+H35+I35+K35+L35 -> 64368.35 | O35: =+D35+G35+M35+J35 -> 608.28 | P35: 0 | Q35: =+Consultants!E15 -> 370 | R35: =(P35-O35-Q35)/(N35/1.9) -> -0.02887649 | S35: =+P35-N35-O35-Q35 -> -65346.63
A36: 44986 | B36: =+'Société C-1'!F36 -> 812.5 | C36: =+'Société C-1'!G36 -> 14089.35 | D36: =+'Société C-1'!H36 -> 0 | E36: 0 | F36: 0 | G36: 0 | H36: ='Société B'!F37 -> 5406.25 | I36: ='Société B'!G37 -> 6601.08 | J36: ='Société B'!H37 -> 1317.1 | K36: =+'Société A'!F36 -> 28337.5 | L36: =+'Société A'!G36 -> 48812.44 | M36: =+'Société A'!H36 -> 2139.02 | N36: =+B36+C36+E36+F36+H36+I36+K36+L36 -> 104059.12 | O36: =+D36+G36+M36+J36 -> 3456.12 | P36: 0 | Q36: =+Consultants!E16 -> 416.25 | R36: =(P36-O36-Q36)/(N36/1.9) -> -0.070705028 | S36: =+P36-N36-O36-Q36 -> -107931.49
A37: 45017 | B37: =+'Société C-1'!F37 -> 500 | C37: =+'Société C-1'!G37 -> 6120.73 | D37: =+'Société C-1'!H37 -> 277.71 | E37: 0 | F37: 0 | G37: 0 | H37: ='Société B'!F38 -> 2937.5 | I37: ='Société B'!G38 -> 4256 | J37: ='Société B'!H38 -> 212.78 | K37: =+'Société A'!F37 -> 23762.5 | L37: =+'Société A'!G37 -> 31759.47 | M37: =+'Société A'!H37 -> 423.42 | N37: =+B37+C37+E37+F37+H37+I37+K37+L37 -> 69336.2 | O37: =+D37+G37+M37+J37 -> 913.91 | P37: 0 | Q37: =+Consultants!E162+Consultants!E163+Consultants!E17 -> 12727.5 | R37: =(P37-O37-Q37)/(N37/1.9) -> -0.37381165 | S37: =+P37-N37-O37-Q37 -> -82977.61
A38: 45047 | B38: =+'Société C-1'!F38+'Société C-1'!F40 -> 562.5 | C38: =+'Société C-1'!G38+'Société C-1'!G40 -> 149658.96 | D38: =+'Société C-1'!H38+'Société C-1'!H40 -> 88.4 | E38: 0 | F38: 0 | G38: 0 | H38: ='Société B'!F39 -> 3937.5 | I38: ='Société B'!G39 -> 3957.7 | J38: ='Société B'!H39 -> 809.85 | K38: =+'Société A'!F38 -> 24943.75 | L38: =+'Société A'!G38 -> 44593.97 | M38: =+'Société A'!H38 -> 1619.86 | N38: =+B38+C38+E38+F38+H38+I38+K38+L38 -> 227654.38 | O38: =+D38+G38+M38+J38 -> 2518.11 | P38: 0 | Q38: =+Consultants!E18+Consultants!E19 -> 4076.25 | R38: =(P38-O38-Q38)/(N38/1.9) -> -0.055036428 | S38: =+P38-N38-O38-Q38 -> -234248.74
A39: 45078 | B39: =+'Société C-1'!F41 -> 500 | C39: =+'Société C-1'!G41 -> 38035.31 | D39: =+'Société C-1'!H41 -> 339.5 | E39: 0 | F39: 0 | G39: 0 | H39: ='Société B'!F40 -> 1281.25 | I39: ='Société B'!G40 -> 1580.09 | J39: ='Société B'!H40 -> 116.29 | K39: =+'Société A'!F39 -> 21437.5 | L39: =+'Société A'!G39 -> 33114.64 | M39: =+'Société A'!H39 -> 705.42 | N39: =+B39+C39+E39+F39+H39+I39+K39+L39 -> 95948.79 | O39: =+D39+G39+M39+J39 -> 1161.21 | P39: 0 | Q39: =+Consultants!E20+Consultants!E139+Consultants!E140+Consultants!E141 -> 5212.5 | R39: =(P39-O39-Q39)/(N39/1.9) -> -0.12621367 | S39: =+P39-N39-O39-Q39 -> -102322.5
A40: 45108 | B40: =+'Société C-1'!F42 -> 562.5 | C40: =+'Société C-1'!G42 -> 5690.67 | D40: =+'Société C-1'!H42 -> 83.2 | E40: 0 | F40: 0 | G40: 0 | H40: ='Société B'!F41 -> 2062.5 | I40: ='Société B'!G41 -> 1415.5 | J40: ='Société B'!H41 -> 0 | K40: =+'Société A'!F40 -> 16943.75 | L40: =+'Société A'!G40 -> 30144.71 | M40: =+'Société A'!H40 -> 589.3 | N40: =+B40+C40+E40+F40+H40+I40+K40+L40 -> 56819.63 | O40: =+D40+G40+M40+J40 -> 672.5 | P40: =+'Facturation Client'!I28 -> 294994.74 | Q40: 0 | R40: =(P40-O40-Q40)/(N40/1.9) -> 9.8418849 | S40: =+P40-N40-O40-Q40 -> 237502.61
A41: 45139 | B41: =+'Société C-1'!F43 -> 875 | C41: =+'Société C-1'!G43 -> 7859.44 | D41: =+'Société C-1'!H43 -> 0 | E41: 0 | F41: 0 | G41: 0 | H41: ='Société B'!F42 -> 7156.25 | I41: ='Société B'!G42 -> 6086.98 | J41: ='Société B'!H42 -> 0 | K41: =+'Société A'!F41 -> 24062.5 | L41: =+'Société A'!G41 -> 39589.38 | M41: =+'Société A'!H41 -> 859.99 | N41: =+B41+C41+E41+F41+H41+I41+K41+L41 -> 85629.55 | O41: =+D41+G41+M41+J41 -> 859.99 | P41: 0 | Q41: =+Consultants!E142+Consultants!E143+Consultants!E144+Consultants!E145+Consultants!E146+Consultants!E21 -> 6486.26 | R41: =(P41-O41-Q41)/(N41/1.9) -> -0.16300302 | S41: =+P41-N41-O41-Q41 -> -92975.8
A42: 45170 | B42: =+'Société C-1'!F44 -> 437.5 | C42: =+'Société C-1'!G44 -> 3256.35 | D42: =+'Société C-1'!H44 -> 182.52 | E42: 0 | F42: 0 | G42: 0 | H42: ='Société B'!F43 -> 5156.25 | I42: ='Société B'!G43 -> 1655.38 | J42: ='Société B'!H43 -> 423.88 | K42: =+'Société A'!F42 -> 20462.5 | L42: =+'Société A'!G42 -> 36795.41 | M42: =+'Société A'!H42 -> 686.4 | N42: =+B42+C42+E42+F42+H42+I42+K42+L42 -> 67763.39 | O42: =+D42+G42+M42+J42 -> 1292.8 | P42: =+'Facturation Client'!I29 -> 137825.39 | Q42: =+Consultants!E22+Consultants!E55 -> 1188.75 | R42: =(P42-O42-Q42)/(N42/1.9) -> 3.7948706 | S42: =+P42-N42-O42-Q42 -> 67580.45
A43: 45200 | B43: =+'Société C-1'!F45 -> 625 | C43: =+'Société C-1'!G45 -> 4397.49 | D43: =+'Société C-1'!H45 -> 0 | E43: 0 | F43: 0 | G43: 0 | H43: ='Société B'!F44 -> 1812.5 | I43: ='Société B'!G44 -> 409.45 | J43: ='Société B'!H44 -> 0 | K43: =+'Société A'!F43 -> 15837.5 | L43: =+'Société A'!G43 -> 34187.2 | M43: =+'Société A'!H43 -> 1584.18 | N43: =+B43+C43+E43+F43+H43+I43+K43+L43 -> 57269.14 | O43: =+D43+G43+M43+J43 -> 1584.18 | P43: 0 | Q43: =+Consultants!E147+Consultants!E148+Consultants!E149 -> 4360 | R43: =(P43-O43-Q43)/(N43/1.9) -> -0.19720816 | S43: =+P43-N43-O43-Q43 -> -63213.32
A44: 45231 | B44: =+'Société C-1'!F46 -> 687.5 | C44: =+'Société C-1'!G46 -> 7185.25 | D44: =+'Société C-1'!H46 -> 0 | E44: 0 | F44: 0 | G44: 0 | H44: ='Société B'!F45 -> 3468.75 | I44: ='Société B'!G45 -> 1169.69 | J44: ='Société B'!H45 -> 0 | K44: =+'Société A'!F44 -> 26662.5 | L44: =+'Société A'!G44 -> 40468.07 | M44: =+'Société A'!H44 -> 1447.48 | N44: =+B44+C44+E44+F44+H44+I44+K44+L44 -> 79641.76 | O44: =+D44+G44+M44+J44 -> 1447.48 | P44: 0 | Q44: =Consultants!E23+Consultants!E171 -> 7095 | R44: =(P44-O44-Q44)/(N44/1.9) -> -0.2037965 | S44: =+P44-N44-O44-Q44 -> -88184.24
A45: 45261 | B45: =+'Société C-1'!F47 -> 375 | C45: =+'Société C-1'!G47 -> 3248.25 | D45: =+'Société C-1'!H47 -> 0 | E45: 0 | F45: 0 | G45: 0 | H45: ='Société B'!F46 -> 1562.5 | I45: ='Société B'!G46 -> 1675.33 | J45: ='Société B'!H46 -> 0 | K45: =+'Société A'!F45 -> 12831.25 | L45: =+'Société A'!G45 -> 22892.16 | M45: =+'Société A'!H45 -> 545.46 | N45: =+B45+C45+E45+F45+H45+I45+K45+L45 -> 42584.49 | O45: =+D45+G45+M45+J45 -> 545.46 | P45: =+'Facturation Client'!I30 -> 197699.95 | Q45: =+Consultants!E150 -> 1380 | R45: =(P45-O45-Q45)/(N45/1.9) -> 8.7349063 | S45: =+P45-N45-O45-Q45 -> 153190
A46: 45292 | B46: =+'Société C-1'!F48 -> 625 | C46: =+'Société C-1'!G48 -> 1336.89 | D46: =+'Société C-1'!H48 -> 0 | E46: 0 | F46: 0 | G46: 0 | H46: ='Société B'!F47 -> 1062.5 | I46: ='Société B'!G47 -> 131.1 | J46: ='Société B'!H47 -> 0 | K46: =+'Société A'!F46 -> 15912.5 | L46: =+'Société A'!G46 -> 27012.55 | M46: =+'Société A'!H46 -> 1602.14 | N46: =+B46+C46+E46+F46+H46+I46+K46+L46 -> 46080.54 | O46: =+D46+G46+M46+J46 -> 1602.14 | P46: 0 | Q46: 0 | R46: =(P46-O46-Q46)/(N46/1.9) -> -0.066059686 | S46: =+P46-N46-O46-Q46 -> -47682.68
A47: 45323 | B47: =+'Société C-1'!F49 -> 812.5 | C47: =+'Société C-1'!G49 -> 2085.49 | D47: =+'Société C-1'!H49 -> 0 | E47: 0 | F47: 0 | G47: 0 | H47: ='Société B'!F48 -> 1718.75 | I47: ='Société B'!G48 -> 1883.85 | J47: ='Société B'!H48 -> 0 | K47: =+'Société A'!F47 -> 19418.75 | L47: =+'Société A'!G47 -> 28120.88 | M47: =+'Société A'!H47 -> 742.78 | N47: =+B47+C47+E47+F47+H47+I47+K47+L47 -> 54040.22 | O47: =+D47+G47+M47+J47 -> 742.78 | P47: 0 | Q47: =+Consultants!E151+Consultants!E152 -> 3055 | R47: =(P47-O47-Q47)/(N47/1.9) -> -0.13352614 | S47: =+P47-N47-O47-Q47 -> -57838
A48: 45352 | B48: =+'Société C-1'!F50 -> 375 | C48: =+'Société C-1'!G50 -> 2126.34 | D48: =+'Société C-1'!H50 -> 0 | E48: 0 | F48: 0 | G48: 0 | H48: ='Société B'!F49 -> 1281.25 | I48: ='Société B'!G49 -> 171 | J48: ='Société B'!H49 -> 0 | K48: =+'Société A'!F48 -> 14087.5 | L48: =+'Société A'!G48 -> 20716.74 | M48: =+'Société A'!H48 -> 635.19 | N48: =+B48+C48+E48+F48+H48+I48+K48+L48 -> 38757.83 | O48: =+D48+G48+M48+J48 -> 635.19 | P48: 0 | Q48: =+Consultants!E24+Consultants!E56+Consultants!E153 -> 8737.5 | R48: =(P48-O48-Q48)/(N48/1.9) -> -0.45947131 | S48: =+P48-N48-O48-Q48 -> -48130.52
A49: 45383 | B49: =+'Société C-1'!F51 -> 750 | C49: =+'Société C-1'!G51 -> 1675.8 | D49: =+'Société C-1'!H51 -> 0 | E49: 0 | F49: 0 | G49: 0 | H49: ='Société B'!F50 -> 1187.5 | I49: ='Société B'!G50 -> 226.6 | J49: ='Société B'!H50 -> 0 | K49: =+'Société A'!F49 -> 18106.25 | L49: =+'Société A'!G49 -> 17224.22 | M49: =+'Société A'!H49 -> 482.96 | N49: =+B49+C49+E49+F49+H49+I49+K49+L49 -> 39170.37 | O49: =+D49+G49+M49+J49 -> 482.96 | P49: =+'Facturation Client'!I31 -> 114880.64 | Q49: =+Consultants!E25 -> 138.75 | R49: =(P49-O49-Q49)/(N49/1.9) -> 5.5422496 | S49: =+P49-N49-O49-Q49 -> 75088.56
A50: 45413 | B50: =+'Société C-1'!F52 -> 1375 | C50: =+'Société C-1'!G52 -> 2622.48 | D50: =+'Société C-1'!H52 -> 0 | E50: 0 | F50: 0 | G50: 0 | H50: ='Société B'!F51 -> 1062.5 | I50: ='Société B'!G51 -> 101.97 | J50: ='Société B'!H51 -> 0 | K50: =+'Société A'!F50 -> 16137.5 | L50: =+'Société A'!G50 -> 21649.81 | M50: =+'Société A'!H50 -> 820.57 | N50: =+B50+C50+E50+F50+H50+I50+K50+L50 -> 42949.26 | O50: =+D50+G50+M50+J50 -> 820.57 | P50: 0 | Q50: =+Consultants!E154+Consultants!E26 -> 5732.5 | R50: =(P50-O50-Q50)/(N50/1.9) -> -0.28989633 | S50: =+P50-N50-O50-Q50 -> -49502.33
A51: 45444 | B51: =+'Société C-1'!F53 -> 1000 | C51: =+'Société C-1'!G53 -> 1657.04 | D51: =+'Société C-1'!H53 -> 0 | E51: 0 | F51: 0 | G51: 0 | H51: ='Société B'!F52 -> 812.5 | I51: ='Société B'!G52 -> 72.63 | J51: ='Société B'!H52 -> 0 | K51: =+'Société A'!F51 -> 13450 | L51: =+'Société A'!G51 -> 18035.29 | M51: =+'Société A'!H51 -> 967.07 | N51: =+B51+C51+E51+F51+H51+I51+K51+L51 -> 35027.46 | O51: =+D51+G51+M51+J51 -> 967.07 | P51: 0 | Q51: =+Consultants!E57+Consultants!E155 -> 10215 | R51: =(P51-O51-Q51)/(N51/1.9) -> -0.60655077 | S51: =+P51-N51-O51-Q51 -> -46209.53
A52: 45474 | B52: =+'Société C-1'!F54 -> 500 | C52: =+'Société C-1'!G54 -> 3581.75 | D52: =+'Société C-1'!H54 -> 0 | E52: 0 | F52: 0 | G52: 0 | H52: ='Société B'!F53 -> 812.5 | I52: ='Société B'!G53 -> 45.32 | J52: ='Société B'!H53 -> 0 | K52: =+'Société A'!F52 -> 15325 | L52: =+'Société A'!G52 -> 23860.93 | M52: =+'Société A'!H52 -> 1859.16 | N52: =+B52+C52+E52+F52+H52+I52+K52+L52 -> 44125.5 | O52: =+D52+G52+M52+J52 -> 1859.16 | P52: 0 | Q52: =+Consultants!E27 -> 5545 | R52: =(P52-O52-Q52)/(N52/1.9) -> -0.31881574 | S52: =+P52-N52-O52-Q52 -> -51529.66
A53: 45505 | B53: =+'Société C-1'!F55 -> 375 | C53: =+'Société C-1'!G55 -> 2057.23 | D53: =+'Société C-1'!H55 -> 0 | E53: 0 | F53: 0 | G53: 0 | H53: ='Société B'!F54 -> 781.25 | I53: ='Société B'!G54 -> 0 | J53: ='Société B'!H54 -> 0 | K53: =+'Société A'!F53 -> 10293.75 | L53: =+'Société A'!G53 -> 9006.49 | M53: =+'Société A'!H53 -> 122.63 | N53: =+B53+C53+E53+F53+H53+I53+K53+L53 -> 22513.72 | O53: =+D53+G53+M53+J53 -> 122.63 | P53: =+'Facturation Client'!I32+'Facturation Client'!I33 -> 915820.16 | Q53: =+Consultants!E28 -> 323.75 | R53: =(P53-O53-Q53)/(N53/1.9) -> 77.251124 | S53: =+P53-N53-O53-Q53 -> 892860.06
A54: 45536 | B54: =+'Société C-1'!F56 -> 875 | C54: =+'Société C-1'!G56 -> 1831.61 | D54: =+'Société C-1'!H56 -> 0 | E54: 0 | F54: 0 | G54: 0 | H54: ='Société B'!F55 -> 125 | I54: ='Société B'!G55 -> 19.38 | J54: ='Société B'!H55 -> 0 | K54: =+'Société A'!F54 -> 5993.75 | L54: =+'Société A'!G54 -> 12980.81 | M54: =+'Société A'!H54 -> 486.97 | N54: =+B54+C54+E54+F54+H54+I54+K54+L54 -> 21825.55 | O54: =+D54+G54+M54+J54 -> 486.97 | P54: 0 | Q54: =+Consultants!E58+Consultants!E29+Consultants!E156 -> 5050 | R54: =(P54-O54-Q54)/(N54/1.9) -> -0.48201502 | S54: =+P54-N54-O54-Q54 -> -27362.52
A55: 45566 | B55: =+'Société C-1'!F57 -> 437.5 | C55: =+'Société C-1'!G57 -> 2063.4 | D55: =+'Société C-1'!H57 -> 0 | E55: 0 | F55: 0 | G55: 0 | H55: ='Société B'!F56 -> 218.75 | I55: ='Société B'!G56 -> 0 | J55: ='Société B'!H56 -> 0 | K55: =+'Société A'!F55 -> 6668.75 | L55: =+'Société A'!G55 -> 14009.19 | M55: =+'Société A'!H55 -> 1075.46 | N55: =+B55+C55+E55+F55+H55+I55+K55+L55 -> 23397.59 | O55: =+D55+G55+M55+J55 -> 1075.46 | P55: 0 | Q55: =+Consultants!E172+Consultants!E173+Consultants!E174 -> 5557.5 | R55: =(P55-O55-Q55)/(N55/1.9) -> -0.53862915 | S55: =+P55-N55-O55-Q55 -> -30030.55
A56: 45597 | B56: =+'Société C-1'!F58 -> 500 | C56: =+'Société C-1'!G58 -> 1746.58 | D56: =+'Société C-1'!H58 -> 0 | E56: 0 | F56: 0 | G56: 0 | H56: ='Société B'!F57 -> 156.25 | I56: ='Société B'!G57 -> 95 | J56: ='Société B'!H57 -> 0 | K56: =+'Société A'!F56 -> 4243.75 | L56: =+'Société A'!G56 -> 5746.56 | M56: =+'Société A'!H56 -> 0 | N56: =+B56+C56+E56+F56+H56+I56+K56+L56 -> 12488.14 | O56: =+D56+G56+M56+J56 -> 0 | P56: =+'Facturation Client'!I34 -> 19175.44 | Q56: =+Consultants!E164 -> 4250 | R56: =(P56-O56-Q56)/(N56/1.9) -> 2.2708214 | S56: =+P56-N56-O56-Q56 -> 2437.3
A57: 45627 | B57: =+'Société C-1'!F59 -> 437.5 | C57: =+'Société C-1'!G59 -> 1445.43 | D57: =+'Société C-1'!H59 -> 0 | E57: 0 | F57: 0 | G57: 0 | H57: ='Société B'!F58 -> 468.75 | I57: ='Société B'!G58 -> 0 | J57: ='Société B'!H58 -> 0 | K57: =+'Société A'!F57 -> 875 | L57: =+'Société A'!G57 -> 2340.1 | M57: =+'Société A'!H57 -> 0 | N57: =+B57+C57+E57+F57+H57+I57+K57+L57 -> 5566.78 | O57: =+D57+G57+M57+J57 -> 0 | P57: 0 | Q57: 0 | R57: =(P57-O57-Q57)/(N57/1.9) -> 0 | S57: =+P57-N57-O57-Q57 -> -5566.78
A58: 45658 | B58: =+'Société C-1'!F60 -> 500 | C58: =+'Société C-1'!G60 -> 1787.56 | D58: =+'Société C-1'!H60 -> 0 | E58: 0 | F58: 0 | G58: 0 | H58: ='Société B'!F59 -> 31.25 | I58: ='Société B'!G59 -> 0 | J58: ='Société B'!H59 -> 0 | K58: =+'Société A'!F58 -> 1812.5 | L58: =+'Société A'!G58 -> 3929.68 | M58: =+'Société A'!H58 -> 78.4 | N58: =+B58+C58+E58+F58+H58+I58+K58+L58 -> 8060.99 | O58: =+D58+G58+M58+J58 -> 78.4 | P58: 0 | Q58: =+Consultants!E165 -> 4250 | R58: =(P58-O58-Q58)/(N58/1.9) -> -1.0202171 | S58: =+P58-N58-O58-Q58 -> -12389.39
A59: 45689 | B59: =+'Société C-1'!F61 -> 250 | C59: =+'Société C-1'!G61 -> 1763.34 | D59: =+'Société C-1'!H61 -> 0 | E59: 0 | F59: 0 | G59: 0 | H59: ='Société B'!F60 -> 343.75 | I59: ='Société B'!G60 -> 31 | J59: ='Société B'!H60 -> 0 | K59: =+'Société A'!F59 -> 2562.5 | L59: =+'Société A'!G59 -> 3294.76 | M59: =+'Société A'!H59 -> 0 | N59: =+B59+C59+E59+F59+H59+I59+K59+L59 -> 8245.35 | O59: =+D59+G59+M59+J59 -> 0 | P59: 0 | Q59: =+Consultants!E30 -> 138.75 | R59: =(P59-O59-Q59)/(N59/1.9) -> -0.031972566 | S59: =+P59-N59-O59-Q59 -> -8384.1
A60: 45717 | B60: =+'Société C-1'!F62 -> 312.5 | C60: =+'Société C-1'!G62 -> 861.44 | D60: =+'Société C-1'!H62 -> 0 | E60: 0 | F60: 0 | G60: 0 | H60: ='Société B'!F61 -> 0 | I60: ='Société B'!G61 -> 0 | J60: ='Société B'!H61 -> 0 | K60: =+'Société A'!F60 -> 3031.25 | L60: =+'Société A'!G60 -> 2641.48 | M60: =+'Société A'!H60 -> 0 | N60: =+B60+C60+E60+F60+H60+I60+K60+L60 -> 6846.67 | O60: =+D60+G60+M60+J60 -> 0 | P60: 0 | Q60: =+Consultants!E59 -> 2986.25 | R60: =(P60-O60-Q60)/(N60/1.9) -> -0.82870578 | S60: =+P60-N60-O60-Q60 -> -9832.92
A61: 45748 | B61: =+'Société C-1'!F63 -> 437.5 | C61: =+'Société C-1'!G63 -> 2058.55 | D61: =+'Société C-1'!H63 -> 0 | E61: 0 | F61: 0 | G61: 0 | H61: ='Société B'!F62 -> 125 | I61: ='Société B'!G62 -> 29.45 | J61: ='Société B'!H62 -> 0 | K61: =+'Société A'!F61 -> 3750 | L61: =+'Société A'!G61 -> 2460.51 | M61: =+'Société A'!H61 -> 0 | N61: =+B61+C61+E61+F61+H61+I61+K61+L61 -> 8861.01 | O61: =+D61+G61+M61+J61 -> 0 | P61: 0 | Q61: 0 | R61: =(P61-O61-Q61)/(N61/1.9) -> 0 | S61: =+P61-N61-O61-Q61 -> -8861.01
A62: 45778 | B62: =+'Société C-1'!F64 -> 375 | C62: =+'Société C-1'!G64 -> 1796.72 | D62: =+'Société C-1'!H64 -> 62 | E62: 0 | F62: 0 | G62: 0 | H62: ='Société B'!F63 -> 625 | I62: ='Société B'!G63 -> 29.45 | J62: ='Société B'!H63 -> 0 | K62: =+'Société A'!F62 -> 3025 | L62: =+'Société A'!G62 -> 2810.82 | M62: =+'Société A'!H62 -> 0 | N62: =+B62+C62+E62+F62+H62+I62+K62+L62 -> 8661.99 | O62: =+D62+G62+M62+J62 -> 62 | P62: 0 | Q62: 0 | R62: =(P62-O62-Q62)/(N62/1.9) -> -0.013599646 | S62: =+P62-N62-O62-Q62 -> -8723.99
A63: 45809 | B63: =+'Société C-1'!F65 -> 0 | C63: =+'Société C-1'!G65 -> 715.43 | D63: =+'Société C-1'!H65 -> 0 | E63: 0 | F63: 0 | G63: 0 | H63: ='Société B'!F64 -> 406.25 | I63: ='Société B'!G64 -> 14.73 | J63: ='Société B'!H64 -> 0 | K63: =+'Société A'!F63 -> 2406.25 | L63: =+'Société A'!G63 -> 3513.34 | M63: =+'Société A'!H63 -> 0 | N63: =+B63+C63+E63+F63+H63+I63+K63+L63 -> 7056 | O63: =+D63+G63+M63+J63 -> 0 | P63: 0 | Q63: =+Consultants!E31 -> 2008.75 | R63: =(P63-O63-Q63)/(N63/1.9) -> -0.5409049 | S63: =+P63-N63-O63-Q63 -> -9064.75
A64: 45839 | B64: =+'Société C-1'!F66 -> 125 | C64: =+'Société C-1'!G66 -> 1393.55 | D64: =+'Société C-1'!H66 -> 0 | E64: 0 | F64: 0 | G64: 0 | H64: ='Société B'!F65 -> 125 | I64: ='Société B'!G65 -> 64.61 | J64: ='Société B'!H65 -> 0 | K64: =+'Société A'!F64 -> 593.75 | L64: =+'Société A'!G64 -> 2406.35 | M64: =+'Société A'!H64 -> 0 | N64: =+B64+C64+E64+F64+H64+I64+K64+L64 -> 4708.26 | O64: =+D64+G64+M64+J64 -> 0 | P64: 0 | Q64: 0 | R64: =(P64-O64-Q64)/(N64/1.9) -> 0 | S64: =+P64-N64-O64-Q64 -> -4708.26
A65: 45870 | B65: =+'Société C-1'!F67 -> 0 | C65: =+'Société C-1'!G67 -> 2886.25 | D65: =+'Société C-1'!H67 -> 0 | E65: 0 | F65: 0 | G65: 0 | H65: ='Société B'!F66 -> 0 | I65: ='Société B'!G66 -> 87.4 | J65: ='Société B'!H66 -> 0 | K65: =+'Société A'!F65 -> 968.75 | L65: =+'Société A'!G65 -> 1131.93 | M65: =+'Société A'!H65 -> 0 | N65: =+B65+C65+E65+F65+H65+I65+K65+L65 -> 5074.33 | O65: =+D65+G65+M65+J65 -> 0 | P65: =+'Facturation Client'!I35 -> 29784.3 | Q65: 0 | R65: =(P65-O65-Q65)/(N65/1.9) -> 11.152245 | S65: =+P65-N65-O65-Q65 -> 24709.97
A66: 45901 | B66: =+'Société C-1'!F68 -> 0 | C66: =+'Société C-1'!G68 -> 1120.25 | D66: =+'Société C-1'!H68 -> 0 | E66: 0 | F66: 0 | G66: 0 | H66: ='Société B'!F67 -> 187.5 | I66: ='Société B'!G67 -> 16.63 | J66: ='Société B'!H67 -> 0 | K66: =+'Société A'!F66 -> 937.5 | L66: =+'Société A'!G66 -> 1130.98 | M66: =+'Société A'!H66 -> 0 | N66: =+B66+C66+E66+F66+H66+I66+K66+L66 -> 3392.86 | O66: =+D66+G66+M66+J66 -> 0 | P66: 0 | Q66: 0 | R66: =(P66-O66-Q66)/(N66/1.9) -> 0 | S66: =+P66-N66-O66-Q66 -> -3392.86
B68: =SUM(B4:B67) -> 32850 | C68: =SUM(C4:C67) -> 853553.5 | D68: =SUM(D4:D67) -> 2631.18 | E68: =SUM(E4:E67) -> 4462.5 | F68: =SUM(F4:F67) -> 98587.23 | G68: =SUM(G4:G67) -> 364 | H68: =SUM(H4:H67) -> 146687.5 | I68: =SUM(I4:I67) -> 595356.23 | ... Q68: =SUM(Q4:Q67) -> 450633.01 | R68: =(P68-O68-Q68)/(N68/1.9) -> 2.7410815 | S68: =SUM(S4:S67) -> 1758212.6
B69: =+B68/(B68+E68+H68+K68) -> 0.030449442 | C69: =+C68/(C68+F68+I68+L68) -> 0.29504522 | D69: =+D68/O68 -> 0.038135873 | E69: =+E68/(E68+H68+K68+B68) -> 0.0041363968 | F69: =F68/(F68+C68+I68+L68) -> 0.034078346 | G69: =+G68/O68 -> 0.0052757538 | H69: =+H68/(H68+K68+E68+B68) -> 0.13596811 | I69: =+I68/(I68+L68+F68+C68) -> 0.20579496 | J69: =+J68/O68 -> 0.29684174 | K69: =+K68/(K68+B68+H68+E68) -> 0.82944605 | L69: =+L68/(L68++I68+F68+C68) -> 0.46508147 | M69: =+M68/O68 -> 0.65974664 | O69: =+D69+G69+M69+J69 -> 1
B70: DES HRES ASSOCIES | C70: DES HRES EMPLOY | D70: DES DEP TOTALES | E70: DES HRES ASSOCIES | F70: DES HRES EMPLOY | G70: DES DEP TOTALES | H70: DES HRES ASSOCIES | I70: DES HRES EMPLOY | J70: DES DEP TOTALES | K70: DES HRES ASSOCIES | L70: DES HRES EMPLOY | M70: DES DEP TOTALES
B71: Total factures (associés+employés+dépenses) | C71: =+C68+B68+D68 -> 889034.68 | D71: =+D68 -> 2631.18 | E71: Total factures (associés+employés+dépenses) | F71: =+F68+E68+G68 -> 103413.73 | G71: =+G68 -> 364 | H71: Total factures (associés+employés+dépenses) | I71: =+I68+H68+J68 -> 762524.29 | J71: =+J68 -> 20480.56 | K71: Total factures (associés+employés+dépenses) | L71: =+L68+K68+M68 -> 2285817.9 | M71: =+M68 -> 45519.14
A76: HEURES | B76: Associés | C76: Employés | D76: Total | E76: % partic | F76: Retraits $ | G76: COÜTANT | H76: Associés | I76: Employés | J76: Total | K76: % partic | L76: Moyenne part
A78: Société C | B78: =+'Société C-1'!D70 -> 263 | C78: =+'Société C-1'!E70 -> 12693.4 | D78: =SUM(B78:C78) -> 12956.4 | E78: =D78/$D$82 -> 0.22590012 | F78: ='Société C-1'!O70 -> 295500 | G78: Société C | H78: ='Société C-1'!F70 -> 32850 | I78: ='Société C-1'!G70 -> 853553.5 | J78: =+I78+H78 -> 886403.5 | K78: =J78/$J$82 -> 0.22317449 | L78: =(E78+K78)/2 -> 0.22453731
A79: Société C | B79: =+'Société C-2'!D36 -> 35 | C79: =+'Société C-2'!E36 -> 1565 | D79: =SUM(B79:C79) -> 1600 | E79: =D79/$D$82 -> 0.027896653 | F79: =+'Société C-2'!O36 -> 142000 | G79: Société C | H79: ='Société C-2'!F36 -> 4462.5 | I79: ='Société C-2'!G36 -> 98587.23 | J79: =+I79+H79 -> 103049.73 | K79: =J79/$J$82 -> 0.025945375 | L79: =(E79+K79)/2 -> 0.026921014
A80: Société B | B80: ='Société B'!D69 -> 1173.5 | C80: ='Société B'!E69 -> 10972.5 | D80: =SUM(B80:C80) -> 12146 | E80: =D80/$D$82 -> 0.21177047 | F80: ='Société B'!O69 -> 437500 | G80: Société B | H80: ='Société B'!F69 -> 146687.5 | I80: ='Société B'!G69 -> 595356.23 | J80: =+I80+H80 -> 742043.73 | K80: =J80/$J$82 -> 0.18682827 | L80: =(E80+K80)/2 -> 0.19929937
A81: Société A | B81: ='Société A'!D68 -> 7116.75 | C81: ='Société A'!E68 -> 23535.4 | D81: =SUM(B81:C81) -> 30652.15 | E81: =D81/$D$82 -> 0.53443275 | F81: ='Société A'!O68 -> 875000 | G81: Société A | H81: ='Société A'!F68 -> 894837.5 | I81: ='Société A'!G68 -> 1345461.2 | J81: =+I81+H81 -> 2240298.8 | K81: =J81/$J$82 -> 0.56405186 | L81: =(E81+K81)/2 -> 0.54924231
B82: =SUM(B78:B81) -> 8588.25 | C82: =SUM(C78:C81) -> 48766.3 | D82: =SUM(D78:D81) -> 57354.55 | E82: =SUM(E78:E81) -> 1 | F82: =SUM(F78:F81) -> 1750000 | H82: =SUM(H78:H79) -> 37312.5 | I82: =SUM(I78:I79) -> 952140.73 | J82: =SUM(J78:J81) -> 3971795.7 | K82: =SUM(K78:K81) -> 1 | L82: =SUM(L78:L81) -> 1
B85: Coûtant | C85: Dépenses | D85: Dépenses+coûtant | E85: Facture client | F85: Consultants | G85: Ratio Global | H85: % prévu par bureau
A87: Société C | B87: =J78/1.9 -> 466528.16 | C87: =D68 -> 2631.18 | D87: =SUM(B87:C87) -> 469159.34 | G87: =+(C71+F78-C87)/B87 -> 2.5334023 | H87: 0.125
A88: Société C | B88: =J79/1.9 -> 54236.7 | C88: =G68 -> 364 | D88: =SUM(B88:C88) -> 54600.7 | G88: =+(F71+F79-C88)/B88 -> 4.5181534 | H88: 0.125
A89: Société B | B89: =J80/1.9 -> 390549.33 | C89: =J68 -> 20480.56 | D89: =SUM(B89:C89) -> 411029.89 | G89: =+(I71+F80-C89)/B89 -> 3.020217 | H89: 0.25
A90: Société A | B90: =J81/1.9 -> 1179104.6 | C90: =M68 -> 45519.14 | D90: =SUM(B90:C90) -> 1224623.7 | G90: =+(L71+F81-C90)/B90 -> 2.6420885 | H90: 0.5
B91: =SUM(B87:B90) -> 2090418.8 | C91: =SUM(C87:C90) -> 68994.88 | D91: =SUM(D87:D90) -> 2159413.7 | E91: =P68 -> 6249636.2 | F91: =+Q68 -> 450633.01 | G91: =(E91-C91-F91)/B91 -> 2.7410815 | H91: =SUM(H87:H90) -> 1

Sheet Facturation Client
A1: Facturation Société A | Société B | Société C
A3: Date | B3: Période | C3: Facture | D3: 001 - Conception | E3: Projet A | F3: Projet B | G3: Projet C | H3: Projet D | I3: Total avant taxes | J3: TPS 5% | K3: TVQ 9,975% | L3: Total | M3: Payé | N3: Solde dû
C4: Montant tâche | E4: 2510239.2 | F4: 1309691.7 | G4: 1303576.4 | H4: 1332362.9 | I4: =SUM(D4:H4) -> 6455870.2 | J4: =+I4*0.05 -> 322793.51 | K4: =+I4*0.09975 -> 643973.05 | L4: =+I4+J4+K4 -> 7422636.8
I5: =SUM(D5:H5) -> 0 | J5: =+I5*0.05 -> 0 | K5: =+I5*0.09975 -> 0 | L5: =+I5+J5+K5 -> 0
A6: 23-09-2020 | B6: Mai au 29 août 2020 | C6: 200117-1 | D6: 275812.61 | E6: =$D$6/4 -> 68953.152 | F6: =$D$6/4 -> 68953.152 | G6: =$D$6/4 -> 68953.152 | H6: =$D$6/4 -> 68953.152 | I6: =SUM(E6:H6) -> 275812.61 | J6: =+I6*0.05 -> 13790.63 | K6: =+I6*0.09975 -> 27512.308 | L6: =+I6+J6+K6 -> 317115.55 | M6: 317115.55 | N6: =L6-M6 -> 0
A7: 16-10-2020 | B7: 30 août au 3 octobre 2020 | C7: 200117-2 | D7: 245169.32 | E7: =$D$7/4 -> 61292.33 | F7: =$D$7/4 -> 61292.33 | G7: =$D$7/4 -> 61292.33 | H7: =$D$7/4 -> 61292.33 | I7: =SUM(E7:H7) -> 245169.32 | J7: =+I7*0.05 -> 12258.466 | K7: =+I7*0.09975 -> 24455.64 | L7: =+I7+J7+K7 -> 281883.43 | M7: 281883.43 | N7: =L7-M7 -> 0
A8: 12-11-2020 | B8: 4 au 31 octobre 2020 | C8: 200117-3 | D8: 261771.33 | E8: =$D$8/4 -> 65442.832 | F8: =$D$8/4 -> 65442.832 | G8: =$D$8/4 -> 65442.832 | H8: =$D$8/4 -> 65442.832 | I8: =SUM(E8:H8) -> 261771.33 | J8: =+I8*0.05 -> 13088.567 | K8: =+I8*0.09975 -> 26111.69 | L8: =+I8+J8+K8 -> 300971.59 | M8: 300971.59 | N8: =L8-M8 -> 0
A9: 08-12-2020 | B9: 1er au 28 novembre 2020 | C9: 200117-4 | D9: 318143.25 | E9: =$D$9/4 -> 79535.812 | F9: =$D$9/4 -> 79535.812 | G9: =$D$9/4 -> 79535.812 | H9: =$D$9/4 -> 79535.812 | I9: =SUM(E9:H9) -> 318143.25 | J9: =+I9*0.05 -> 15907.163 | K9: =+I9*0.09975 -> 31734.789 | L9: =+I9+J9+K9 -> 365785.2 | M9: 365785.2 | N9: =L9-M9 -> 0
A10: 20-01-2021 | B10: 29 nov au 2 janvier 2021 | C10: 200117-5 | D10: 254673.02 | E10: =$D$10/4 -> 63668.255 | F10: =$D$10/4 -> 63668.255 | G10: =$D$10/4 -> 63668.255 | H10: =$D$10/4 -> 63668.255 | I10: =SUM(E10:H10) -> 254673.02 | J10: =+I10*0.05 -> 12733.651 | K10: =+I10*0.09975 -> 25403.634 | L10: =+I10+J10+K10 -> 292810.3 | M10: 292810.3 | N10: =L10-M10 -> 0
A11: 16-02-2021 | B11: 3 au 30 janvier 2021 | C11: 200117-6 | D11: 961930 | E11: =$D$11/4 -> 240482.5 | F11: =$D$11/4 -> 240482.5 | G11: =$D$11/4 -> 240482.5 | H11: =$D$11/4 -> 240482.5 | I11: =SUM(E11:H11) -> 961930 | J11: =+I11*0.05 -> 48096.5 | K11: =+I11*0.09975 -> 95952.518 | L11: =+I11+J11+K11 -> 1105979 | M11: 1105979 | N11: =L11-M11 -> 0
I12: =SUM(E12:H12) -> 0 | J12: =+I12*0.05 -> 0 | K12: =+I12*0.09975 -> 0 | L12: =+I12+J12+K12 -> 0 | M12: 0 | N12: =L12-M12 -> 0
I13: =SUM(E13:H13) -> 0 | J13: =+I13*0.05 -> 0 | K13: =+I13*0.09975 -> 0 | L13: =+I13+J13+K13 -> 0 | M13: 0 | N13: =L13-M13 -> 0
I14: =SUM(E14:H14) -> 0 | J14: =+I14*0.05 -> 0 | K14: =+I14*0.09975 -> 0 | L14: =+I14+J14+K14 -> 0 | M14: 0 | N14: =L14-M14 -> 0
I15: =SUM(E15:H15) -> 0 | J15: =+I15*0.05 -> 0 | K15: =+I15*0.09975 -> 0 | L15: =+I15+J15+K15 -> 0 | M15: 0 | N15: =L15-M15 -> 0
I16: =SUM(E16:H16) -> 0 | J16: =+I16*0.05 -> 0 | K16: =+I16*0.09975 -> 0 | L16: =+I16+J16+K16 -> 0 | M16: 0 | N16: =L16-M16 -> 0
I17: =SUM(E17:H17) -> 0 | J17: =+I17*0.05 -> 0 | K17: =+I17*0.09975 -> 0 | L17: =+I17+J17+K17 -> 0 | M17: 0 | N17: =L17-M17 -> 0
A18: 01-09-2021 | B18: 1er février au 30 août 2021 | C18: 200117-7 | D18: 1357024.2 | E18: 1012723.4 | F18: 128058.62 | G18: 106302.62 | H18: 109939.62 | I18: =SUM(E18:H18) -> 1357024.2 | J18: =+I18*0.05 -> 67851.212 | K18: =+I18*0.09975 -> 135363.17 | L18: =+I18+J18+K18 -> 1560238.6 | M18: 1560238.6 | N18: =L18-M18 -> 0
I19: =SUM(E19:H19) -> 0 | J19: =+I19*0.05 -> 0 | K19: =+I19*0.09975 -> 0 | L19: =+I19+J19+K19 -> 0 | M19: 0 | N19: =L19-M19 -> 0
I20: =SUM(E20:H20) -> 0 | J20: =+I20*0.05 -> 0 | K20: =+I20*0.09975 -> 0 | L20: =+I20+J20+K20 -> 0 | M20: 0 | N20: =L20-M20 -> 0
I21: =SUM(E21:H21) -> 0 | J21: =+I21*0.05 -> 0 | K21: =+I21*0.09975 -> 0 | L21: =+I21+J21+K21 -> 0 | M21: 0 | N21: =L21-M21 -> 0
I22: =SUM(E22:H22) -> 0 | J22: =+I22*0.05 -> 0 | K22: =+I22*0.09975 -> 0 | L22: =+I22+J22+K22 -> 0 | M22: 0 | N22: =L22-M22 -> 0
I23: =SUM(E23:H23) -> 0 | J23: =+I23*0.05 -> 0 | K23: =+I23*0.09975 -> 0 | L23: =+I23+J23+K23 -> 0 | M23: 0 | N23: =L23-M23 -> 0
I24: =SUM(E24:H24) -> 0 | J24: =+I24*0.05 -> 0 | K24: =+I24*0.09975 -> 0 | L24: =+I24+J24+K24 -> 0 | M24: 0 | N24: =L24-M24 -> 0
A25: 26-05-2022 | B25: 31 août 2021 au 30 avril 2022 | C25: 200117-8 | D25: 266654.75 | E25: 90608.25 | F25: 0 | G25: 0 | H25: 176046.5 | I25: =SUM(E25:H25) -> 266654.75 | J25: =+I25*0.05 -> 13332.738 | K25: =+I25*0.09975 -> 26598.811 | L25: =+I25+J25+K25 -> 306586.3 | M25: 306586.3 | N25: =L25-M25 -> 0
A26: 14-11-2022 | B26: du 1er mai au 31 octobre 2022 | C26: 200117-9 | E26: 297922 | F26: 38169.74 | G26: 54335.78 | H26: 91002.66 | I26: =SUM(D26:H26) -> 481430.18 | J26: =+I26*0.05 -> 24071.509 | K26: =+I26*0.09975 -> 48022.66 | L26: =+I26+J26+K26 -> 553524.35 | M26: 553524.35 | N26: =L26-M26 -> 0
A27: 23-01-2023 | B27: du 1er novembre au 31 décembre 2022 | C27: 200117-10 | E27: 56206.77 | F27: 17862.62 | G27: 17732.14 | H27: 25045.38 | I27: =SUM(D27:H27) -> 116846.91 | J27: =+I27*0.05 -> 5842.3455 | K27: 11655.48 | L27: =+I27+J27+K27 -> 134344.74 | M27: 134344.74 | N27: =L27-M27 -> 0
A28: 30-09-2023 | B28: 1er janvier au 31 juillet 2023 | C28: 200117-11 | E28: 0 | F28: 93198.75 | G28: 145459.18 | H28: 56336.81 | I28: =SUM(D28:H28) -> 294994.74 | J28: =+I28*0.05 -> 14749.737 | K28: =+I28*0.09975-0.001 -> 29425.724 | L28: =+I28+J28+K28 -> 339170.2 | M28: 339170.2 | N28: =L28-M28 -> 0
A29: 26-10-2023 | B29: 1er août au 30 septembre 2023 | C29: 200117-12 | E29: 1161.88 | F29: 71870.32 | G29: 53014.9 | H29: 11778.29 | I29: =SUM(D29:H29) -> 137825.39 | J29: =+I29*0.05 -> 6891.2695 | K29: =+I29*0.09975 -> 13748.083 | L29: =+I29+J29+K29 -> 158464.74 | M29: 158464.74 | N29: =L29-M29 -> 0
A30: 31-12-2023 | B30: 1er octobre au 31 décembre 2023 | C30: 200117-13 | E30: 23181.1 | F30: 96689.75 | G30: 56400.1 | H30: 21429 | I30: =SUM(D30:H30) -> 197699.95 | J30: =+I30*0.05 -> 9884.9975 | K30: =+I30*0.09975 -> 19720.57 | L30: =+I30+J30+K30 -> 227305.52 | M30: 227305.52 | N30: =L30-M30 -> 0
A31: 10-05-2024 | B31: au 30 avril 2024 | C31: 200117-14 | E31: 5000 | F31: 38029.7 | G31: 57309.08 | H31: 14541.86 | I31: =SUM(D31:H31) -> 114880.64 | J31: =+I31*0.05 -> 5744.032 | K31: =+I31*0.09975 -> 11459.344 | L31: =+I31+J31+K31 -> 132084.02 | M31: 132084.02 | N31: =L31-M31 -> 0
A32: 18-09-2024 | B32: au 31 aout 2024 | C32: 200117-15 | E32: 359061.43 | F32: 189313.38 | G32: 179339.32 | H32: 184777.53 | I32: =SUM(D32:H32) -> 912491.66 | J32: =+I32*0.05 -> 45624.583 | K32: =+I32*0.09975 -> 91021.043 | L32: =+I32+J32+K32 -> 1049137.3 | M32: 1049137.3 | N32: =L32-M32 -> 0
A33: 18-10-2024 | B33: au 31 aout 2024 - dépenses | C33: 200117-16 | E33: 0 | F33: 2572.5 | G33: 756 | H33: 0 | I33: =SUM(D33:H33) -> 3328.5 | J33: =+I33*0.05 -> 166.425 | K33: =+I33*0.09975 -> 332.01788 | L33: =+I33+J33+K33 -> 3826.9429 | M33: 3826.9429 | N33: =L33-M33 -> 0
A34: 27-11-2024 | B34: au 30 novembre 2024 | C34: 200117-17 | E34: 5000 | F34: =6494-2500 -> 3994 | G34: =5181.44-2500 -> 2681.44 | H34: 7500 | I34: =SUM(D34:H34) -> 19175.44 | J34: =+I34*0.05 -> 958.772 | K34: =+I34*0.09975 -> 1912.7501 | L34: =+I34+J34+K34 -> 22046.962 | M34: 22046.962 | N34: =L34-M34 -> 0
B35: au 31 aout 2025 | C35: 200117-18 | E35: 0 | F35: 6529 | G35: 9105.3 | H35: 14150 | I35: =SUM(D35:H35) -> 29784.3 | J35: =+I35*0.05 -> 1489.215 | K35: =+I35*0.09975 -> 2970.9839 | L35: =+I35+J35+K35 -> 34244.499 | N35: =L35-M35 -> 34244.499
I36: =SUM(D36:H36) -> 0 | J36: =+I36*0.05 -> 0 | K36: =+I36*0.09975 -> 0 | L36: =+I36+J36+K36 -> 0 | M36: =+I36/2 -> 0 | N36: =L36-M36 -> 0
I37: =SUM(D37:H37) -> 0 | J37: =+I37*0.05 -> 0 | K37: =+I37*0.09975 -> 0 | L37: =+I37+J37+K37 -> 0 | M37: =+I37/2 -> 0 | N37: =L37-M37 -> 0
I38: =SUM(D38:H38) -> 0 | J38: =+I38*0.05 -> 0 | K38: =+I38*0.09975 -> 0 | L38: =+I38+J38+K38 -> 0 | M38: =+I38/2 -> 0 | N38: =L38-M38 -> 0
I39: =SUM(D39:H39) -> 0 | J39: =+I39*0.05 -> 0 | K39: =+I39*0.09975 -> 0 | L39: =+I39+J39+K39 -> 0 | M39: =+I39/2 -> 0 | N39: =L39-M39 -> 0
I40: =SUM(D40:H40) -> 0 | J40: =+I40*0.05 -> 0 | K40: =+I40*0.09975 -> 0 | L40: =+I40+J40+K40 -> 0 | M40: =+I40/2 -> 0 | N40: =L40-M40 -> 0
I41: =SUM(D41:H41) -> 0 | J41: =+I41*0.05 -> 0 | K41: =+I41*0.09975 -> 0 | L41: =+I41+J41+K41 -> 0 | M41: =+I41/2 -> 0 | N41: =L41-M41 -> 0
I42: =SUM(D42:H42) -> 0 | J42: =+I42*0.05 -> 0 | K42: =+I42*0.09975 -> 0 | L42: =+I42+J42+K42 -> 0 | M42: =+I42/2 -> 0 | N42: =L42-M42 -> 0
I43: =SUM(D43:H43) -> 0 | J43: =+I43*0.05 -> 0 | K43: =+I43*0.09975 -> 0 | L43: =+I43+J43+K43 -> 0 | M43: =+I43/2 -> 0 | N43: =L43-M43 -> 0
I44: =SUM(D44:H44) -> 0 | J44: =+I44*0.05 -> 0 | K44: =+I44*0.09975 -> 0 | L44: =+I44+J44+K44 -> 0 | M44: =+I44/2 -> 0 | N44: =L44-M44 -> 0
I45: =SUM(D45:H45) -> 0 | J45: =+I45*0.05 -> 0 | K45: =+I45*0.09975 -> 0 | L45: =+I45+J45+K45 -> 0 | M45: =+I45/2 -> 0 | N45: =L45-M45 -> 0
I46: =SUM(D46:H46) -> 0 | N46: =L46-M46 -> 0
I47: =SUM(D47:H47) -> 0 | N47: =L47-M47 -> 0
I48: =SUM(D48:H48) -> 0 | N48: =L48-M48 -> 0
I49: =SUM(D49:H49) -> 0 | N49: =L49-M49 -> 0
D50: =SUM(D5:D40) -> 3941178.5 | E50: =SUM(E5:E40) -> 2430239.7 | F50: =SUM(F5:F40) -> 1265663.3 | G50: =SUM(G5:G40) -> 1261810.7 | H50: =SUM(H5:H49) -> 1291922.5 | I50: =SUM(I5:I49) -> 6249636.2 | J50: =+I50*0.05 -> 312481.81 | K50: =+I50*0.09975 -> 623401.21 | L50: =+I50+J50+K50 -> 7185519.3 | M50: =SUM(M6:M49) -> 7151274.8 | N50: =SUM(N6:N49) -> 34244.499
C51: % d'avancement | E51: =+E50/E4 -> 0.96813072 | F51: =+F50/F4 -> 0.96638259 | G51: =+G50/G4 -> 0.96796071 | H51: =+H50/H4 -> 0.96964763 | I51: =+I50/I4 -> 0.96805481 | J51: =+J50/J4 -> 0.96805481 | K51: =+K50/K4 -> 0.96805481 | L51: =+L50/L4 -> 0.96805481

Sheet Société C-1
A1: Société C
A3: Date | B3: période | C3: facture | D3: Heures Associés | E3: Heures Employés | F3: Honoraires associés | G3: Honoraires employés | H3: Frais refacturables | I3: Sous-TOTAL | J3: TPS | K3: TVQ | L3: TOTAL | M3: payé | N3: dû | O3: Partage | P3: Coûtant Société C | Q3: Coûtant PRDI
A4: 44056 | B4: Mai à Juillet | C4: 36379 | D4: 0 | E4: 376.25 | F4: =D4*125 -> 0 | G4: 25530.13 | H4: 372.18 | I4: =SUM(F4:H4) -> 25902.31 | J4: =+I4*0.05 -> 1295.1155 | K4: =+I4*0.09975 -> 2583.7554 | L4: =SUM(I4:K4) -> 29781.181 | M4: 29781.181 | N4: =+L4-M4 -> 0
A5: 44075 | B5: Août | C5: 36511 | D5: 0 | E5: 244.5 | F5: =D5*125 -> 0 | G5: 14942.08 | H5: 131.5 | I5: =SUM(F5:H5) -> 15073.58 | J5: =+I5*0.05 -> 753.679 | K5: =+I5*0.09975 -> 1503.5896 | L5: =SUM(I5:K5) -> 17330.849 | M5: 17330.849 | N5: =+L5-M5 -> 0 | P5: 7864.25 | Q5: 0
A6: 44109 | B6: Septembre | C6: 36753 | D6: 3.5 | E6: 635.25 | F6: =D6*125 -> 437.5 | G6: =44978.41-F6 -> 44540.91 | H6: =120.32 -> 120.32 | I6: =SUM(F6:H6) -> 45098.73 | J6: =+I6*0.05 -> 2254.9365 | K6: =+I6*0.09975 -> 4498.5983 | L6: =SUM(I6:K6) -> 51852.265 | M6: 51852.265 | N6: =+L6-M6 -> 0 | O6: 18750 | P6: 22491.28 | Q6: 1287.81
A7: 44137 | B7: Octobre | C7: 37027 | D7: 0 | E7: 489.25 | F7: 0 | G7: 34001.71 | H7: =157.65 -> 157.65 | I7: =SUM(F7:H7) -> 34159.36 | J7: =+I7*0.05 -> 1707.968 | K7: =+I7*0.09975 -> 3407.3962 | L7: =SUM(I7:K7) -> 39274.724 | M7: 39274.724 | N7: =+L7-M7 -> 0 | P7: 17184.75 | Q7: 710.87
A8: 44166 | B8: Novembre | C8: 37288 | D8: 0 | E8: 611.75 | F8: 0 | G8: 42751.38 | I8: =SUM(F8:H8) -> 42751.38 | J8: =+I8*0.05 -> 2137.569 | K8: =+I8*0.09975 -> 4264.4502 | L8: =SUM(I8:K8) -> 49153.399 | M8: 49153.399 | N8: =+L8-M8 -> 0 | P8: 20202.75 | Q8: 2297.95
A9: 44202 | B9: décembre | C9: 37610 | D9: 2.5 | E9: =639.25-D9 -> 636.75 | F9: =2.5*125 -> 312.5 | G9: =33669.26-F9 -> 33356.76 | H9: =268.58 -> 268.58 | I9: =SUM(F9:H9) -> 33937.84 | J9: =+I9*0.05 -> 1696.892 | K9: =+I9*0.09975 -> 3385.2995 | L9: =SUM(I9:K9) -> 39020.032 | M9: 39020.032 | N9: =+L9-M9 -> 0 | P9: 16765.88 | Q9: =257.13+2112.01 -> 2369.14
A10: 44231 | B10: janvier | C10: 37894 | D10: 0 | E10: 613.75 | F10: 0 | G10: 48962.88 | H10: =9+4 -> 13 | I10: =SUM(F10:H10) -> 48975.88 | J10: =+I10*0.05 -> 2448.794 | K10: =+I10*0.09975 -> 4885.344 | L10: =SUM(I10:K10) -> 56310.018 | M10: 56310.018 | N10: =+L10-M10 -> 0 | P10: 25360.13 | Q10: 408.36
A11: 44257 | B11: février | C11: 38109 | D11: 1 | E11: =703-D11 -> 702 | F11: 125 | G11: =53264.43-F11 -> 53139.43 | I11: =SUM(F11:H11) -> 53264.43 | J11: =+I11*0.05 -> 2663.2215 | K11: =+I11*0.09975 -> 5313.1269 | L11: =SUM(I11:K11) -> 61240.778 | M11: 61240.778 | N11: =+L11-M11 -> 0 | O11: 81250 | P11: 24586.15 | Q11: 3477.98
A12: 44293 | B12: mars | C12: 38486 | D12: 0 | E12: 299.75 | F12: 0 | G12: 17723.03 | I12: =SUM(F12:H12) -> 17723.03 | J12: =+I12*0.05 -> 886.1515 | K12: =+I12*0.09975 -> 1767.8722 | L12: =SUM(I12:K12) -> 20377.054 | M12: 20377.054 | N12: =+L12-M12 -> 0 | P12: 9285.88 | Q12: 42.03
A13: 44319 | B13: avril | C13: 38647 | D13: 4 | E13: 492.25 | F13: 500 | G13: =29709.98-F13 -> 29209.98 | I13: =SUM(F13:H13) -> 29709.98 | J13: =+I13*0.05 -> 1485.499 | K13: =+I13*0.09975 -> 2963.5705 | L13: =SUM(I13:K13) -> 34159.05 | M13: 34159.05 | N13: =+L13-M13 -> 0 | P13: 11343.28 | Q13: 210.15
A14: 44349 | B14: mai | C14: 39182 | D14: 4 | E14: 179.5 | F14: 500 | G14: =11609.31-500 -> 11109.31 | I14: =SUM(F14:H14) -> 11609.31 | J14: =+I14*0.05 -> 580.4655 | K14: =+I14*0.09975 -> 1158.0287 | L14: =SUM(I14:K14)+0.01 -> 13347.814 | M14: 13347.814 | N14: =+L14-M14 -> 0 | P14: 6322.35 | Q14: 375.25
A15: 44378 | B15: juin | C15: PRAA-2021-0290 | D15: 4 | E15: =93.25+4 -> 97.25 | F15: 500 | G15: =6045.63-F15+293.73 -> 5839.36 | I15: =SUM(F15:H15) -> 6339.36 | J15: =+I15*0.05 -> 316.968 | K15: =+I15*0.09975 -> 632.35116 | L15: =SUM(I15:K15) -> 7288.6792 | M15: 7288.6792 | N15: =+L15-M15 -> 0 | P15: 3390.35 | Q15: 154.59
A16: 44414 | B16: juillet | C16: PRAA-2021-0560 | D16: 3 | E16: 12 | F16: 375 | G16: =1144.98-F16 -> 769.98 | I16: =SUM(F16:H16) -> 1144.98 | J16: =+I16*0.05 -> 57.249 | K16: =+I16*0.09975 -> 114.21176 | L16: =SUM(I16:K16) -> 1316.4408 | M16: 1316.4408 | N16: =+L16-M16 -> 0 | P16: 732.45 | Q16: 10.75
A17: 44448 | B17: Août | C17: PRAA-2021-0760 | D17: 5 | E17: =5.75+1+12.5 -> 19.25 | F17: 625 | G17: =1878.53-F17 -> 1253.53 | I17: =SUM(F17:H17) -> 1878.53 | J17: =+I17*0.05 -> 93.9265 | K17: =+I17*0.09975 -> 187.38337 | L17: =SUM(I17:K17) -> 2159.8399 | M17: 2159.8399 | N17: =+L17-M17 -> 0 | O17: 145500 | P17: 1756.75 | Q17: 10.75
A18: 44482 | B18: septembre | C18: PRAA-2021-0894 | D18: =6+2 -> 8 | E18: =1+0.5+7.5+9.75+20 -> 38.75 | F18: =750+300 -> 1050 | G18: =3734.23-F18 -> 2684.23 | I18: =SUM(F18:H18) -> 3734.23 | J18: =+I18*0.05 -> 186.7115 | K18: =+I18*0.09975 -> 372.48944 | L18: =SUM(I18:K18) -> 4293.4309 | M18: 4293.4309 | N18: =+L18-M18 -> 0 | P18: 2175.73 | Q18: 0
A19: 44503 | B19: Octobre | C19: PRAA-2021-1050 | D19: 2 | E19: =1+9+22 -> 32 | F19: 125 | G19: =2335.25-F19 -> 2210.25 | I19: =SUM(F19:H19) -> 2335.25 | J19: =+I19*0.05 -> 116.7625 | K19: =+I19*0.09975 -> 232.94119 | L19: =SUM(I19:K19) -> 2684.9537 | M19: 2684.9537 | N19: =+L19-M19 -> 0 | P19: 1317.28 | Q19: 0
A20: 44536 | B20: novembre | C20: PRAA-2021-1209 | D20: 3.25 | E20: =5.25+1+11 -> 17.25 | F20: 406.25 | G20: =6538.03-F20 -> 6131.78 | I20: =SUM(F20:H20) -> 6538.03 | J20: =+I20*0.05 -> 326.9015 | K20: =+I20*0.09975 -> 652.16849 | L20: =SUM(I20:K20) -> 7517.1 | M20: 7517.1 | N20: =+L20-M20 -> 0 | P20: 1994.64 | Q20: 0
A21: 44568 | B21: décembre | C21: PRAA-2022-0070 | D21: =4+1 -> 5 | E21: =11+4.5+4.25+1+11 -> 31.75 | F21: =500+150 -> 650 | G21: =3126.18-F21 -> 2476.18 | I21: =SUM(F21:H21) -> 3126.18 | J21: =+I21*0.05 -> 156.309 | K21: =+I21*0.09975-0.01 -> 311.82646 | L21: =SUM(I21:K21) -> 3594.3155 | M21: 3594.3155 | N21: =+L21-M21 -> 0
A22: 44610 | B22: 2 au 29 janvier 2022 | C22: PRAA-2022-0301 | D22: =4+0.5 -> 4.5 | E22: =62.5+9.75+17 -> 89.25 | F22: =500+62.5 -> 562.5 | G22: =6928.21-F22 -> 6365.71 | I22: =SUM(F22:H22) -> 6928.21 | J22: =+I22*0.05 -> 346.4105 | K22: =+I22*0.09975 -> 691.08895 | L22: =SUM(I22:K22) -> 7965.7094 | M22: 7965.7094 | N22: =+L22-M22 -> 0
A23: 44629 | B23: 30 janvier au 26 février 2022 | C23: PRAA-2022-0778 | D23: 3 | E23: =21+14.75+9.5+12 -> 57.25 | F23: 375 | G23: =4002.81-F23 -> 3627.81 | I23: =SUM(F23:H23) -> 4002.81 | J23: =+I23*0.05 -> 200.1405 | K23: =+I23*0.09975 -> 399.2803 | L23: =SUM(I23:K23) -> 4602.2308 | M23: 4602.2308 | N23: =+L23-M23 -> 0
A24: 44664 | B24: 27 février au 2 avril 2022 | C24: PRAA-2022-0781 | D24: 5 | E24: =68+6.25+0.5+104.75+18.5 -> 198 | F24: 625 | G24: =12361.55-F24 -> 11736.55 | I24: =SUM(F24:H24) -> 12361.55 | J24: =+I24*0.05 -> 618.0775 | K24: =+I24*0.09975 -> 1233.0646 | L24: =SUM(I24:K24) -> 14212.692 | M24: 14212.692 | N24: =+L24-M24 -> 0
A25: 44717 | B25: 3 au 30 avril 2022 | C25: PRAA-2022-0928 | D25: 4 | E25: =6.5+5.75+1+41+21 -> 75.25 | F25: 500 | G25: =5564.21-F25 -> 5064.21 | I25: =SUM(F25:H25) -> 5564.21 | J25: =+I25*0.05 -> 278.2105 | K25: =+I25*0.09975 -> 555.02995 | L25: =SUM(I25:K25) -> 6397.4504 | M25: 6397.4504 | N25: =+L25-M25 -> 0
A26: 44721 | B26: 1er au 28 mai 2022 | C26: PRAA-2022-1169 | D26: =4+10.75 -> 14.75 | E26: =7.25+33+4.5+2.5+58+0.5+28.5+4 -> 138.25 | F26: =500+1343.75 -> 1843.75 | G26: =11296.98-F26 -> 9453.23 | I26: =SUM(F26:H26) -> 11296.98 | J26: =+I26*0.05 -> 564.849 | K26: =+I26*0.09975 -> 1126.8738 | L26: =SUM(I26:K26) -> 12988.703 | M26: 12988.703 | N26: =+L26-M26 -> 0
A27: 44757 | B27: 29 mai au 2 juillet 2022 | C27: PRAA-2022-1351 | D27: =6.5+17 -> 23.5 | E27: 173.4 | F27: =812.5+2125 -> 2937.5 | G27: =14221.14-F27 -> 11283.64 | H27: 289.05 | I27: =SUM(F27:H27) -> 14510.19 | J27: 725.52 | K27: 1447.38 | L27: =SUM(I27:K27) -> 16683.09 | M27: 16683.09 | N27: =+L27-M27 -> 0
A28: 44803 | B28: 3 au 30 juillet 2022 | C28: PRAA-2022-1584 | D28: 3 | E28: =81.5-3 -> 78.5 | F28: 375 | G28: =5424.83-F28+208.06 -> 5257.89 | I28: =SUM(F28:H28) -> 5632.89 | J28: =+I28*0.05 -> 281.6445 | K28: 561.88 | L28: =SUM(I28:K28) -> 6476.4145 | M28: 6476.4145 | N28: =+L28-M28 -> 0
A29: 44826 | B29: 31 juillet au 3 septembre 2022 | C29: PRAA-2022-1717 | D29: 3 | E29: =175.25-D29+22.25 -> 194.5 | F29: 375 | G29: =12040.01-F29+964.25 -> 12629.26 | H29: 88.92 | I29: =SUM(F29:H29) -> 13093.18 | J29: =+I29*0.05 -> 654.659 | K29: =+I29*0.09975 -> 1306.0447 | L29: =SUM(I29:K29) -> 15053.884 | M29: 15053.884 | N29: =+L29-M29 -> 0
A30: 44841 | B30: 4 septembre au 1er octobre 202 | C30: PRAA-2022-1808 | D30: 5.5 | E30: =128.25-D30+28.75+11 -> 162.5 | F30: =625+62.5 -> 687.5 | G30: =9085.03-F30+2066.73 -> 10464.26 | H30: =81.16+75.49 -> 156.65 | I30: =SUM(F30:H30) -> 11308.41 | J30: =+I30*0.05 -> 565.4205 | K30: 1128.02 | L30: =SUM(I30:K30) -> 13001.851 | M30: 13001.851 | N30: =+L30-M30 -> 0
A31: 44871 | B31: 2 au 29 octobre 2022 | C31: PRAA-2022-1980 | D31: 5 | E31: =2.5+11.5+52+2.5+14+12 -> 94.5 | F31: 625 | G31: =6213.38-F31+478.8 -> 6067.18 | I31: =SUM(F31:H31) -> 6692.18 | J31: =+I31*0.05 -> 334.609 | K31: =+I31*0.09975 -> 667.54496 | L31: =SUM(I31:K31) -> 7694.334 | M31: 7694.334 | N31: =+L31-M31 -> 0
A32: 44898 | B32: 30 octobre au 26 novembre 2022 | C32: PRAA-2022-2205 | D32: 4 | E32: =12+1.5+43.5+6.75+4+3.5 -> 71.25 | F32: =375+150 -> 525 | G32: =4830.4-F32-14.25+216.13 -> 4507.28 | I32: =SUM(F32:H32) -> 5032.28 | J32: 251.62 | K32: =+I32*0.09975 -> 501.96993 | L32: =SUM(I32:K32) -> 5785.8699 | M32: 5785.8699 | N32: =+L32-M32 -> 0
A33: 44939 | B33: 27 novembre au 31 décembre 2022 | C33: PRAA-2023-0043 | D33: 5 | E33: =83.75-D33+8.25 -> 87 | F33: 625 | G33: =5599.2-F33+329.18 -> 5303.38 | I33: =SUM(F33:H33) -> 5928.38 | J33: 296.42 | K33: =+I33*0.09975 -> 591.35591 | L33: =SUM(I33:K33) -> 6816.1559 | M33: 6816.1559 | N33: =+L33-M33 -> 0
A34: 44967 | B34: 1er au 28 janvier 2023 | C34: PRAA-2023-0250 | D34: 4 | E34: =46.5-D34 -> 42.5 | F34: 500 | G34: =3471.13-F34 -> 2971.13 | I34: =SUM(F34:H34) -> 3471.13 | J34: =+I34*0.05 -> 173.5565 | K34: 346.24 | L34: =SUM(I34:K34) -> 3990.9265 | M34: 3990.9265 | N34: =+L34-M34 -> 0
A35: 45000 | B35: 29 janvier au 25 février 2023 | C35: PRAA-2023-0381 | D35: 5 | E35: =118.75-D35 -> 113.75 | F35: =+D35*125 -> 625 | G35: =7400.78-F35 -> 6775.78 | I35: =SUM(F35:H35) -> 7400.78 | J35: =+I35*0.05 -> 370.039 | K35: =+I35*0.09975 -> 738.2278 | L35: =SUM(I35:K35) -> 8509.0468 | M35: 8509.0468 | N35: =+L35-M35 -> 0
A36: 45026 | B36: 26 février au 1er avril 2023 | C36: PRAA-2023-0489 | D36: 6.5 | E36: =249.5-D36 -> 243 | F36: =+D36*125 -> 812.5 | G36: =14901.85-F36 -> 14089.35 | I36: =SUM(F36:H36) -> 14901.85 | J36: =+I36*0.05 -> 745.0925 | K36: =+I36*0.09975 -> 1486.4595 | L36: =SUM(I36:K36) -> 17133.402 | M36: 17133.402 | N36: =+L36-M36 -> 0
A37: 45072 | B37: 2 au 29 avril 2023 | C37: PRAA-2023-0718 | D37: 4 | E37: =99-D37+3 -> 98 | F37: =+D37*125 -> 500 | G37: =6445.93-F37+174.8 -> 6120.73 | H37: =100.48+172.96+9.7-5.43 -> 277.71 | I37: =SUM(F37:H37) -> 6898.44 | J37: =+I37*0.05+0.005 -> 344.927 | K37: =+I37*0.09975 -> 688.11939 | L37: =SUM(I37:K37) -> 7931.4864 | M37: 7931.4864 | N37: =+L37-M37 -> 0
A38: 45091 | B38: 30 avril au 3 juin 2023 | C38: PRAA-2023-0851 | D38: 4 | E38: =318.5-D38 -> 314.5 | F38: =+D38*125 -> 500 | G38: =20252.33-F38 -> 19752.33 | H38: 88.4 | I38: =SUM(F38:H38) -> 20340.73 | J38: =+I38*0.05 -> 1017.0365 | K38: =+I38*0.09975-0.005 -> 2028.9828 | L38: =SUM(I38:K38) -> 23386.749 | M38: 23386.749 | N38: =+L38-M38 -> 0
A39: 45163 | B39: Granby 2022 | C39: PRAA-2023-1262 | D39: 0.5 | E39: =1384.5-D39 -> 1384 | F39: =+D39*125 -> 62.5 | G39: =97320.85-F39 -> 97258.35 | I39: =SUM(F39:H39) -> 97320.85 | J39: =+I39*0.05 -> 4866.0425 | K39: =+I39*0.09975+0.001 -> 9707.7558 | L39: =SUM(I39:K39) -> 111894.65 | M39: 111894.65 | N39: =+L39-M39 -> 0
A40: 45163 | B40: Granby au 3 juin 2023 | C40: PRAA-2023-1259 | D40: 0.5 | E40: =1970-D40 -> 1969.5 | F40: =+D40*125 -> 62.5 | G40: =129969.13-F40 -> 129906.63 | I40: =SUM(F40:H40) -> 129969.13 | J40: =+I40*0.05 -> 6498.4565 | K40: =+I40*0.09975 -> 12964.421 | L40: =SUM(I40:K40) -> 149432.01 | M40: 149432.01 | N40: =+L40-M40 -> 0
A41: 45163 | B41: 4 juin au 1er juillet 2023 | C41: PRAA-2023-1260 | D41: 4 | E41: =552.5-D41 -> 548.5 | F41: =+D41*125 -> 500 | G41: =38535.31-F41 -> 38035.31 | H41: 339.5 | I41: =SUM(F41:H41) -> 38874.81 | J41: =+I41*0.05+0.005 -> 1943.7455 | K41: =+I41*0.09975 -> 3877.7623 | L41: =SUM(I41:K41) -> 44696.318 | M41: 44696.318 | N41: =+L41-M41 -> 0
A42: 45163 | B42: 2 au 29 juillet 2023 | C42: PRAA-2023-1261 | D42: 4.5 | E42: =90.5-D42 -> 86 | F42: =+D42*125 -> 562.5 | G42: =6253.17-F42 -> 5690.67 | H42: 83.2 | I42: =SUM(F42:H42) -> 6336.37 | J42: =+I42*0.05 -> 316.8185 | K42: =+I42*0.09975 -> 632.05291 | L42: =SUM(I42:K42) -> 7285.2414 | M42: 7285.2414 | N42: =+L42-M42 -> 0
A43: 45182 | B43: 30 juillet au 2 septembre 2023 | C43: PRAA-2023-1442 | D43: 7 | E43: =136-D43 -> 129 | F43: =+D43*125 -> 875 | G43: =8734.44-F43 -> 7859.44 | I43: =SUM(F43:H43) -> 8734.44 | J43: =+I43*0.05 -> 436.722 | K43: =+I43*0.09975 -> 871.26039 | L43: =SUM(I43:K43) -> 10042.422 | M43: 10042.422 | N43: =+L43-M43 -> 0
A44: 45210 | B44: 3 au 30 septembre 2023 | C44: PRAA-2023-1531 | D44: 3.5 | E44: =52.5-D44 -> 49 | F44: =+D44*125 -> 437.5 | G44: =3693.85-F44 -> 3256.35 | H44: 182.52 | I44: =SUM(F44:H44) -> 3876.37 | J44: =+I44*0.05 -> 193.8185 | K44: =+I44*0.09975 -> 386.66791 | L44: =SUM(I44:K44) -> 4456.8564 | M44: 4456.8564 | N44: =+L44-M44 -> 0
A45: 45255 | B45: 1er au 28 octobre 2023 | C45: PRAA-2023-1738 | D45: 5 | E45: =69.5-D45 -> 64.5 | F45: =+D45*125 -> 625 | G45: =5022.49-F45 -> 4397.49 | I45: =SUM(F45:H45) -> 5022.49 | J45: =+I45*0.05+0.001 -> 251.1255 | K45: =+I45*0.09975 -> 500.99338 | L45: =SUM(I45:K45) -> 5774.6089 | M45: 5774.6089 | N45: =+L45-M45 -> 0
A46: 45269 | B46: 29 octobre au 2 décembre 2023 | C46: PRAA-2023-1919 | D46: 5.5 | E46: =112.5-D46 -> 107 | F46: =+D46*125 -> 687.5 | G46: =7872.75-F46 -> 7185.25 | I46: =SUM(F46:H46) -> 7872.75 | J46: =+I46*0.05+0.001 -> 393.6385 | K46: =+I46*0.09975-0.005 -> 785.30181 | L46: =SUM(I46:K46) -> 9051.6903 | M46: 9051.6903 | N46: =+L46-M46 -> 0
A47: 45291 | B47: 3 au 31 décembre 2023 | C47: PRAA-2024-0097 | D47: 3 | E47: =8.25+23+2+15 -> 48.25 | F47: =+D47*125 -> 375 | G47: =3623.25-F47 -> 3248.25 | I47: =SUM(F47:H47) -> 3623.25 | J47: =+I47*0.05 -> 181.1625 | K47: =+I47*0.09975 -> 361.41919 | L47: =SUM(I47:K47) -> 4165.8317 | M47: 4165.8317 | N47: =+L47-M47 -> 0
A48: 45322 | B48: au 31 janvier 2024 | C48: PRAA-2024-0259 | D48: 5 | E48: =24.5-D48 -> 19.5 | F48: =+D48*125 -> 625 | G48: =1961.89-F48 -> 1336.89 | I48: =SUM(F48:H48) -> 1961.89 | J48: =+I48*0.05 -> 98.0945 | K48: =+I48*0.09975 -> 195.69853 | L48: =SUM(I48:K48) -> 2255.683 | M48: 2255.683 | N48: =+L48-M48 -> 0
A49: 45351 | B49: au 29 février 2024 | C49: PRAA-2024-0367 | D49: 6.5 | E49: 30 | F49: =+D49*125 -> 812.5 | G49: =2897.99-F49 -> 2085.49 | I49: =SUM(F49:H49) -> 2897.99 | J49: =+I49*0.05 -> 144.8995 | K49: =+I49*0.09975 -> 289.0745 | L49: =SUM(I49:K49) -> 3331.964 | M49: 3331.964 | N49: =+L49-M49 -> 0
A50: 45382 | B50: au 31 mars 2024 | C50: PRAA-2024-0501 | D50: 3 | E50: 33.75 | F50: =+D50*125 -> 375 | G50: =2501.34-F50 -> 2126.34 | I50: =SUM(F50:H50) -> 2501.34 | J50: =+I50*0.05 -> 125.067 | K50: =+I50*0.09975 -> 249.50867 | L50: =SUM(I50:K50) -> 2875.9157 | M50: 2875.9157 | N50: =+L50-M50 -> 0
A51: 45412 | B51: au 30 avril 2024 | C51: PRAA-2024-0844 | D51: 6 | E51: 25.5 | F51: =+D51*125 -> 750 | G51: =2425.8-F51 -> 1675.8 | I51: =SUM(F51:H51) -> 2425.8 | J51: =+I51*0.05 -> 121.29 | K51: =+I51*0.09975 -> 241.97355 | L51: =SUM(I51:K51) -> 2789.0636 | M51: 2789.0636 | N51: =+L51-M51 -> 0
A52: 45443 | B52: au 31 mai 2024 | C52: PRAA-2024-0971 | D52: 11 | E52: 37 | F52: =+D52*125 -> 1375 | G52: =3997.48-F52 -> 2622.48 | I52: =SUM(F52:H52) -> 3997.48 | J52: =+I52*0.05 -> 199.874 | K52: =+I52*0.09975 -> 398.74863 | L52: =SUM(I52:K52) -> 4596.1026 | M52: 4596.1026 | N52: =+L52-M52 -> 0
A53: 45473 | B53: au 30 juin 2024 | C53: PRAA-2024-1104 | D53: 8 | E53: 26 | F53: =+D53*125 -> 1000 | G53: =2657.04-F53 -> 1657.04 | I53: =SUM(F53:H53) -> 2657.04 | J53: =+I53*0.05 -> 132.852 | K53: =+I53*0.09975 -> 265.03974 | L53: =SUM(I53:K53) -> 3054.9317 | M53: 3054.9317 | N53: =+L53-M53 -> 0
A54: 45504 | B54: au 31 juillet 2024 | C54: PRAA-2024-1312 | D54: 4 | E54: 60 | F54: =+D54*125 -> 500 | G54: =4081.75-F54 -> 3581.75 | I54: =SUM(F54:H54) -> 4081.75 | J54: =+I54*0.05 -> 204.0875 | K54: =+I54*0.09975 -> 407.15456 | L54: =SUM(I54:K54) -> 4692.9921 | M54: 4692.9921 | N54: =+L54-M54 -> 0
A55: 45535 | B55: au 31 aout 2024 | C55: PRAA-2024-1518 | D55: 3 | E55: 31.25 | F55: =+D55*125 -> 375 | G55: =2432.23-F55 -> 2057.23 | I55: =SUM(F55:H55) -> 2432.23 | J55: =+I55*0.05 -> 121.6115 | K55: =+I55*0.09975 -> 242.61494 | L55: =SUM(I55:K55) -> 2796.4564 | M55: 2796.4564 | N55: =+L55-M55 -> 0
A56: 45565 | B56: au 30 septembre 2024 | C56: PRAA-2024-1758 | D56: 7 | E56: 27.25 | F56: =+D56*125 -> 875 | G56: =2706.61-F56 -> 1831.61 | I56: =SUM(F56:H56) -> 2706.61 | J56: =+I56*0.05 -> 135.3305 | K56: =+I56*0.09975 -> 269.98435 | L56: =SUM(I56:K56) -> 3111.9248 | M56: 3111.9248 | N56: =+L56-M56 -> 0 | O56: 50000
A57: 45596 | B57: au 31 octobre 2024 | C57: PRAA-2024-1944 | D57: 3.5 | E57: 28 | F57: =+D57*125 -> 437.5 | G57: =2500.9-F57 -> 2063.4 | I57: =SUM(F57:H57) -> 2500.9 | J57: =+I57*0.05 -> 125.045 | K57: =+I57*0.09975 -> 249.46478 | L57: =SUM(I57:K57) -> 2875.4098 | M57: 2875.4098 | N57: =+L57-M57 -> 0
A58: 45626 | B58: au 30 novembre 2024 | C58: PRAA-2024-2143 | D58: 4 | E58: 25.75 | F58: =+D58*125 -> 500 | G58: =2246.58-F58 -> 1746.58 | I58: =SUM(F58:H58) -> 2246.58 | J58: =+I58*0.05 -> 112.329 | K58: =+I58*0.09975 -> 224.09636 | L58: =SUM(I58:K58) -> 2583.0054 | M58: 2583.0054 | N58: =+L58-M58 -> 0
A59: 45657 | B59: au 31 décembre 2024 | C59: PRAA-2025-0032 | D59: 3.5 | E59: 22.25 | F59: =+D59*125 -> 437.5 | G59: =1882.93-F59 -> 1445.43 | I59: =SUM(F59:H59) -> 1882.93 | J59: =+I59*0.05 -> 94.1465 | K59: =+I59*0.09975 -> 187.82227 | L59: =SUM(I59:K59) -> 2164.8988 | M59: 2164.8988 | N59: =+L59-M59 -> 0
A60: 45688 | B60: au 31 janvier 2025 | C60: PRAA-2025-0268 | D60: 4 | E60: =5.5+15+3.75 -> 24.25 | F60: =+D60*125 -> 500 | G60: =2287.56-F60 -> 1787.56 | I60: =SUM(F60:H60) -> 2287.56 | J60: =+I60*0.05 -> 114.378 | K60: =+I60*0.09975 -> 228.18411 | L60: =SUM(I60:K60) -> 2630.1221 | M60: 2630.1221 | N60: =+L60-M60 -> 0
A61: 45716 | B61: au 28 février 2025 | C61: PRAA-2025-0620 | D61: 2 | E61: =4+14+0.25+3 -> 21.25 | F61: =+D61*125 -> 250 | G61: =1536.09-F61+477.25 -> 1763.34 | I61: =SUM(F61:H61) -> 2013.34 | J61: =+I61*0.05 -> 100.667 | K61: =+I61*0.09975 -> 200.83067 | L61: =SUM(I61:K61) -> 2314.8377 | M61: 2314.8377 | N61: =+L61-M61 -> 0
A62: 45747 | B62: au 31 mars 2025 | C62: PRAA-2025-0856 | D62: 2.5 | E62: =3+9+0.25 -> 12.25 | F62: =+D62*125 -> 312.5 | G62: =1173.94-F62 -> 861.44 | I62: =SUM(F62:H62) -> 1173.94 | J62: =+I62*0.05 -> 58.697 | K62: =+I62*0.09975 -> 117.10052 | L62: =SUM(I62:K62) -> 1349.7375 | M62: 1349.7375 | N62: =+L62-M62 -> 0
A63: 45777 | B63: au 30 avril 2025 | C63: PRAA-2025-1000 | D63: 3.5 | E63: =31-D63 -> 27.5 | F63: =+D63*125 -> 437.5 | G63: =2496.05-F63 -> 2058.55 | I63: =SUM(F63:H63) -> 2496.05 | J63: =+I63*0.05 -> 124.8025 | K63: =+I63*0.09975 -> 248.98099 | L63: =SUM(I63:K63) -> 2869.8335 | M63: 2869.8335 | N63: =+L63-M63 -> 0
A64: 45808 | B64: au 31 mai 2025 | C64: PRAA-2025-1290 | D64: 3 | E64: =16.5-D64 -> 13.5 | F64: =+D64*125 -> 375 | G64: =2171.72-F64 -> 1796.72 | H64: 62 | I64: =SUM(F64:H64) -> 2233.72 | J64: =+I64*0.05 -> 111.686 | K64: =+I64*0.09975 -> 222.81357 | L64: =SUM(I64:K64) -> 2568.2196 | N64: =+L64-M64 -> 2568.2196
A65: 45838 | B65: au 30 juin 2025 | C65: PRAA-2025-1567 | D65: 0 | E65: 9.75 | F65: =+D65*125 -> 0 | G65: 715.43 | I65: =SUM(F65:H65) -> 715.43 | J65: =+I65*0.05 -> 35.7715 | K65: =+I65*0.09975 -> 71.364142 | L65: =SUM(I65:K65) -> 822.56564 | N65: =+L65-M65 -> 822.56564
A66: 45869 | B66: au 31 juillet 2025 | C66: PRAA-2025-1788 | D66: 1 | E66: =0.5+12.5+2.25+2.5 -> 17.75 | F66: =+D66*125 -> 125 | G66: =1518.55-F66 -> 1393.55 | I66: =SUM(F66:H66) -> 1518.55 | J66: =+I66*0.05 -> 75.9275 | K66: =+I66*0.09975 -> 151.47536 | L66: =SUM(I66:K66) -> 1745.9529 | N66: =+L66-M66 -> 1745.9529
A67: 45900 | B67: au 31 aout 2025 | C67: PRAA-2025-1973 | D67: 0 | E67: 39.5 | F67: =+D67*125 -> 0 | G67: 2886.25 | I67: =SUM(F67:H67) -> 2886.25 | J67: =+I67*0.05 -> 144.3125 | K67: =+I67*0.09975 -> 287.90344 | L67: =SUM(I67:K67) -> 3318.4659 | N67: =+L67-M67 -> 3318.4659
A68: 45930 | B68: au 30 septembre 2025 | C68: PRAA-2025-2195 | D68: 0 | E68: 15 | F68: =+D68*125 -> 0 | G68: 1120.25 | I68: =SUM(F68:H68) -> 1120.25 | J68: =+I68*0.05 -> 56.0125 | K68: =+I68*0.09975 -> 111.74494 | L68: =SUM(I68:K68) -> 1288.0074 | N68: =+L68-M68 -> 1288.0074
D70: =SUM(D4:D69) -> 263 | E70: =SUM(E4:E69) -> 12693.4 | F70: =SUM(F4:F69) -> 32850 | G70: =SUM(G4:G69) -> 853553.5 | H70: =SUM(H4:H69) -> 2631.18 | I70: =SUM(I4:I69) -> 889034.68 | J70: =SUM(J4:J69) -> 44451.763 | K70: =SUM(K4:K69) -> 88681.179 | ... N70: =SUM(N4:N69) -> 9743.2114 | O70: =SUM(O5:O69) -> 295500 | P70: =SUM(P5:P69) -> 172773.9 | Q70: =SUM(Q5:Q69) -> 11355.63
E71: =+E70+D70 -> 12956.4

Sheet Société C-2
A1: Société C
A3: Date | B3: période | C3: facture | D3: Heures Associés | E3: Heures Employés | F3: Honoraires associés | G3: Honoraires employés | H3: Frais refacturables | I3: Sous-TOTAL | J3: TPS | K3: TVQ | L3: TOTAL | M3: payé | N3: dû | O3: Partage
I4: =SUM(F4:H4) -> 0 | J4: =+I4*0.05 -> 0 | K4: =+I4*0.09975 -> 0 | L4: =SUM(I4:K4) -> 0 | M4: 0 | N4: =+L4-M4 -> 0 | O4: 0
B5: au 29 août 2020 | C5: P20-021-1 | D5: 13 | E5: 3.75 | F5: =187.5+1468.75 -> 1656.25 | G5: =2025.5-F5 -> 369.25 | I5: =SUM(F5:H5) -> 2025.5 | J5: =+I5*0.05 -> 101.275 | K5: =+I5*0.09975 -> 202.04363 | L5: =SUM(I5:K5) -> 2328.8186 | M5: 2328.8186 | N5: =+L5-M5 -> 0 | O5: 0
A6: 44109 | B6: au 3 octobre 2020 | C6: P20-021-2 | D6: 4 | E6: 136.5 | F6: 512.5 | G6: =9656.75-F6 -> 9144.25 | H6: 200.35 | I6: =SUM(F6:H6) -> 9857.1 | J6: =+I6*0.05 -> 492.855 | K6: =+I6*0.09975 -> 983.24573 | L6: =SUM(I6:K6) -> 11333.201 | M6: 11333.201 | N6: =+L6-M6 -> 0 | O6: 18750
A7: 44135 | B7: au 31 otobre 2020 | C7: P20-021-3 | D7: 2 | E7: =159-D7 -> 157 | F7: 256.25 | G7: =10881-F7 -> 10624.75 | I7: =SUM(F7:H7) -> 10881 | J7: =+I7*0.05 -> 544.05 | K7: =+I7*0.09975 -> 1085.3798 | L7: =SUM(I7:K7) -> 12510.43 | M7: 12510.43 | N7: =+L7-M7 -> 0
A8: 44167 | B8: au 28 novembre 2020 | C8: P20-021-4 | D8: 3 | E8: =185.5-D8 -> 182.5 | F8: =37.5+343.75 -> 381.25 | G8: =12266.7-F8 -> 11885.45 | I8: =SUM(F8:H8) -> 12266.7 | J8: =+I8*0.05 -> 613.335 | K8: =+I8*0.09975 -> 1223.6033 | L8: =SUM(I8:K8) -> 14103.638 | M8: 14103.638 | N8: =+L8-M8 -> 0
A9: 43841 | B9: au 2 janvier 2021 | C9: P20-021-5 | D9: 2 | E9: =220.75-D9 -> 218.75 | F9: 256.25 | G9: =12953.29-F9 -> 12697.04 | I9: =SUM(F9:H9) -> 12953.29 | J9: =+I9*0.05 -> 647.6645 | K9: =+I9*0.09975 -> 1292.0907 | L9: =SUM(I9:K9) -> 14893.045 | M9: 14893.045 | N9: =+L9-M9 -> 0
A10: 44242 | B10: au 30 janvier 2021 | C10: P20-021-6 | D10: 2 | E10: =290-D10 -> 288 | F10: 250 | G10: =17948.5-F10 -> 17698.5 | I10: =SUM(F10:H10) -> 17948.5 | J10: =+I10*0.05 -> 897.425 | K10: =+I10*0.09975 -> 1790.3629 | L10: =SUM(I10:K10) -> 20636.288 | M10: 20636.288 | N10: =+L10-M10 -> 0
A11: 44259 | B11: 31 janvier au 27 février 2021 | C11: P20-021-7 | D11: 9 | E11: =277-D11 -> 268 | F11: =150+1000 -> 1150 | G11: =18084.05-F11 -> 16934.05 | I11: =SUM(F11:H11) -> 18084.05 | J11: =+I11*0.05 -> 904.2025 | K11: =+I11*0.09975 -> 1803.884 | L11: =SUM(I11:K11)-0.01 -> 20792.126 | M11: 20792.126 | N11: =+L11-M11 -> 0 | O11: 81250
A12: 44294 | B12: 28 février au 3 avril 2021 | C12: P20-021-8 | D12: 0 | E12: 310.5 | F12: 0 | G12: 19233.94 | H12: 163.65 | I12: =SUM(F12:H12) -> 19397.59 | J12: =+I12*0.05 -> 969.8795 | K12: =+I12*0.09975 -> 1934.9096 | L12: =SUM(I12:K12) -> 22302.379 | M12: 22302.379 | N12: =+L12-M12 -> 0 | O12: 42000
I13: =SUM(F13:H13) -> 0 | J13: =+I13*0.05 -> 0 | K13: =+I13*0.09975 -> 0 | L13: =SUM(I13:K13) -> 0 | N13: =+L13-M13 -> 0
N14: =+L14-M14 -> 0
I15: =SUM(F15:H15) -> 0 | J15: =+I15*0.05 -> 0 | K15: =+I15*0.09975 -> 0 | L15: =SUM(I15:K15) -> 0 | N15: =+L15-M15 -> 0
I16: =SUM(F16:H16) -> 0 | J16: =+I16*0.05 -> 0 | K16: =+I16*0.09975 -> 0 | L16: =SUM(I16:K16) -> 0 | N16: =+L16-M16 -> 0
I17: =SUM(F17:H17) -> 0 | J17: =+I17*0.05 -> 0 | K17: =+I17*0.09975 -> 0 | L17: =SUM(I17:K17) -> 0 | N17: =+L17-M17 -> 0
I18: =SUM(F18:H18) -> 0 | J18: =+I18*0.05 -> 0 | K18: =+I18*0.09975 -> 0 | L18: =SUM(I18:K18) -> 0 | N18: =+L18-M18 -> 0
I19: =SUM(F19:H19) -> 0 | J19: =+I19*0.05 -> 0 | K19: =+I19*0.09975 -> 0 | L19: =SUM(I19:K19) -> 0 | N19: =+L19-M19 -> 0
I20: =SUM(F20:H20) -> 0 | J20: =+I20*0.05 -> 0 | K20: =+I20*0.09975 -> 0 | L20: =SUM(I20:K20) -> 0 | N20: =+L20-M20 -> 0
I21: =SUM(F21:H21) -> 0 | J21: =+I21*0.05 -> 0 | K21: =+I21*0.09975 -> 0 | L21: =SUM(I21:K21) -> 0 | N21: =+L21-M21 -> 0
I22: =SUM(F22:H22) -> 0 | J22: =+I22*0.05 -> 0 | K22: =+I22*0.09975 -> 0 | L22: =SUM(I22:K22) -> 0 | N22: =+L22-M22 -> 0
I23: =SUM(F23:H23) -> 0 | J23: =+I23*0.05 -> 0 | K23: =+I23*0.09975 -> 0 | L23: =SUM(I23:K23) -> 0 | N23: =+L23-M23 -> 0
I24: =SUM(F24:H24) -> 0 | J24: =+I24*0.05 -> 0 | K24: =+I24*0.09975 -> 0 | L24: =SUM(I24:K24) -> 0 | N24: =+L24-M24 -> 0
I25: =SUM(F25:H25) -> 0 | J25: =+I25*0.05 -> 0 | K25: =+I25*0.09975 -> 0 | L25: =SUM(I25:K25) -> 0 | N25: =+L25-M25 -> 0
I26: =SUM(F26:H26) -> 0 | J26: =+I26*0.05 -> 0 | K26: =+I26*0.09975 -> 0 | L26: =SUM(I26:K26) -> 0 | N26: =+L26-M26 -> 0
... I35: =SUM(F35:H35) -> 0 | J35: =+I35*0.05 -> 0 | K35: =+I35*0.09975 -> 0 | L35: =SUM(I35:K35) -> 0 | N35: =+L35-M35 -> 0
D36: =SUM(D4:D35) -> 35 | E36: =SUM(E4:E35) -> 1565 | F36: =SUM(F4:F35) -> 4462.5 | G36: =SUM(G4:G35) -> 98587.23 | H36: =SUM(H4:H35) -> 364 | I36: =SUM(I4:I35) -> 103413.73 | J36: =SUM(J4:J35) -> 5170.6865 | K36: =SUM(K4:K35) -> 10315.52 | ... N36: =SUM(N4:N35) -> 0 | O36: =SUM(O5:O35) -> 142000
E37: =+E36+D36 -> 1600

Sheet Société B
A1: Société B
A3: Date | B3: période | C3: facture | D3: Heures Associés | E3: Heures Employés | F3: Honoraires associés | G3: Honoraires employés | H3: Frais refacturables | I3: Sous-TOTAL | J3: TPS | K3: TVQ | L3: TOTAL | M3: payé | N3: dû | O3: Partage
A4: 44091 | B4: 1er mai au 1er août 2020 | C4: 20-2926 | D4: 41.75 | E4: =563.25-D4 -> 521.5 | F4: =125*D4 -> 5218.75 | G4: =28177.97-F4 -> 22959.22 | I4: =SUM(F4:H4) -> 28177.97 | J4: =+I4*0.05 -> 1408.8985 | K4: =+I4*0.09975 -> 2810.7525 | L4: =SUM(I4:K4) -> 32397.621 | M4: 32397.621 | N4: =+L4-M4 -> 0
A5: 44091 | B5: 2 au 29 août 2020 | C5: 20-2927 | D5: 8.5 | E5: =425-D5 -> 416.5 | F5: =125*D5 -> 1062.5 | G5: =19397.17-F5 -> 18334.67 | I5: =SUM(F5:H5) -> 19397.17 | J5: =+I5*0.05 -> 969.8585 | K5: =+I5*0.09975 -> 1934.8677 | L5: =SUM(I5:K5)-0.01 -> 22301.886 | M5: 22301.886 | N5: =+L5-M5 -> 0
A6: 44104 | B6: 30 août au 3 octbre 2020 | C6: 20-2945 | D6: 15.5 | E6: =625.5-D6 -> 610 | F6: =125*D6 -> 1937.5 | G6: =28006.02-F6 -> 26068.52 | H6: =1950+387.5+1540 -> 3877.5 | I6: =SUM(F6:H6) -> 31883.52 | J6: =+I6*0.05 -> 1594.176 | K6: =+I6*0.09975 -> 3180.3811 | L6: =SUM(I6:K6) -> 36658.077 | M6: 36658.077 | N6: =+L6-M6 -> 0 | O6: 37500
A7: 44145 | B7: 4 au 31 octobre 2020 | C7: 20-2968 | D7: 16.25 | E7: =682.75-D7 -> 666.5 | F7: =125*D7 -> 2031.25 | G7: =34562.58-F7+2499.88 -> 35031.21 | I7: =SUM(F7:H7) -> 37062.46 | J7: =+I7*0.05 -> 1853.123 | K7: =+I7*0.09975 -> 3696.9804 | L7: =SUM(I7:K7) -> 42612.563 | M7: 42612.563 | N7: =+L7-M7 -> 0
A8: 44172 | B8: 1er au 28 novembre 2020 | C8: 20-2984 | D8: 12.25 | E8: =64-D8 -> 51.75 | F8: =125*D8 -> 1531.25 | G8: =33250.76-F8 -> 31719.51 | I8: =SUM(F8:H8) -> 33250.76 | J8: =+I8*0.05 -> 1662.538 | K8: =+I8*0.09975 -> 3316.7633 | L8: =SUM(I8:K8) -> 38230.061 | M8: 38230.061 | N8: =+L8-M8 -> 0
A9: 44216 | B9: 29 novembre au 26 décembre 2020 | C9: 20-3008 | D9: 16 | E9: =744.5-D9 -> 728.5 | F9: =125*D9 -> 2000 | G9: =40933.39-F9 -> 38933.39 | I9: =SUM(F9:H9) -> 40933.39 | J9: =+I9*0.05 -> 2046.6695 | K9: =+I9*0.09975 -> 4083.1057 | L9: =SUM(I9:K9) -> 47063.165 | M9: 47063.165 | N9: =+L9-M9 -> 0
A10: 44244 | B10: 3 au 30 janvier 2021 | C10: 21-3029 | D10: 12 | E10: =823.5-D10 -> 811.5 | F10: =125*D10 -> 1500 | G10: =43929.39-F10 -> 42429.39 | I10: =SUM(F10:H10) -> 43929.39 | J10: =+I10*0.05 -> 2196.4695 | K10: =+I10*0.09975 -> 4381.9567 | L10: =SUM(I10:K10) -> 50507.816 | M10: 50507.816 | N10: =+L10-M10 -> 0
A11: 44265 | B11: 31 janvier au 27 février 2021 | C11: 21-3055 | D11: 11.25 | E11: =748.75-D11 -> 737.5 | F11: =125*D11 -> 1406.25 | G11: =39121.45-F11 -> 37715.2 | I11: =SUM(F11:H11) -> 39121.45 | J11: =+I11*0.05 -> 1956.0725 | K11: =+I11*0.09975 -> 3902.3646 | L11: =SUM(I11:K11) -> 44979.887 | M11: 44979.887 | N11: =+L11-M11 -> 0 | O11: 162500
A12: 44301 | B12: 28 février au 3 avril 2021 | C12: 21-3066 | D12: 9 | E12: =683-D12 -> 674 | F12: =125*D12 -> 1125 | G12: =34413.08-F12 -> 33288.08 | I12: =SUM(F12:H12) -> 34413.08 | J12: =+I12*0.05 -> 1720.654 | K12: =+I12*0.09975 -> 3432.7047 | L12: =SUM(I12:K12)-0.01 -> 39566.429 | M12: 39566.429 | N12: =+L12-M12 -> 0
A13: 44336 | B13: 4 avril au 1er mai 2021 | C13: 21-3116 | D13: 9.5 | E13: =476.75-D13 -> 467.25 | F13: =125*D13 -> 1187.5 | G13: =24696.18-F13 -> 23508.68 | I13: =SUM(F13:H13) -> 24696.18 | J13: =+I13*0.05 -> 1234.809 | K13: =+I13*0.09975 -> 2463.444 | L13: =SUM(I13:K13) -> 28394.433 | M13: 28394.433 | N13: =+L13-M13 -> 0
A14: 44355 | B14: 2 au 29 mai 2021 | C14: 21-3118 | D14: 5.25 | E14: =310.25-D14 -> 305 | F14: =125*D14 -> 656.25 | G14: =16219.06-F14 -> 15562.81 | I14: =SUM(F14:H14) -> 16219.06 | J14: =+I14*0.05 -> 810.953 | K14: =+I14*0.09975 -> 1617.8512 | L14: =SUM(I14:K14)+0.01 -> 18647.874 | M14: 18647.874 | N14: =+L14-M14 -> 0
A15: 44392 | B15: 30 mai au 26 juin 2021 | C15: 21-3147 | D15: 4.25 | E15: =338.75-D15 -> 334.5 | F15: =125*D15 -> 531.25 | G15: =17069.64-F15 -> 16538.39 | I15: =SUM(F15:H15) -> 17069.64 | J15: =+I15*0.05 -> 853.482 | K15: =+I15*0.09975 -> 1702.6966 | L15: =SUM(I15:K15) -> 19625.819 | M15: 19625.819 | N15: =+L15-M15 -> 0
A16: 44426 | B16: 27 juin au 31 juillet 2021 | C16: 21-3197 | D16: 2 | E16: =151.75-D16 -> 149.75 | F16: =125*D16 -> 250 | G16: =6508.36-F16 -> 6258.36 | I16: =SUM(F16:H16) -> 6508.36 | J16: =+I16*0.05 -> 325.418 | K16: =+I16*0.09975 -> 649.20891 | L16: =SUM(I16:K16) -> 7482.9869 | M16: 7482.9869 | N16: =+L16-M16 -> 0
A17: 44453 | B17: 1er au 29 août 2021 | C17: 21-3222 | D17: 5.25 | E17: =233.75-D17 -> 228.5 | F17: =125*D17 -> 656.25 | G17: =9893.38-F17 -> 9237.13 | I17: =SUM(F17:H17) -> 9893.38 | J17: =+I17*0.05 -> 494.669 | K17: =+I17*0.09975 -> 986.86465 | L17: =SUM(I17:K17) -> 11374.914 | M17: 11374.914 | N17: =+L17-M17 -> 0 | O17: 187500
A18: 44495 | B18: 30 août au 2 octobre 2021 | C18: 21-3253 | D18: 6.75 | E18: =443.5-D18 -> 436.75 | F18: =125*D18 -> 843.75 | G18: =22492.06-F18 -> 21648.31 | I18: =SUM(F18:H18) -> 22492.06 | J18: =+I18*0.05 -> 1124.603 | K18: =+I18*0.09975 -> 2243.583 | L18: =SUM(I18:K18) -> 25860.246 | M18: 25860.246 | N18: =+L18-M18 -> 0
A19: 44524 | B19: 3 au 30 octobre 2021 | C19: 21-3288 | D19: 3 | E19: =301-D19 -> 298 | F19: =125*D19 -> 375 | G19: =15502.17-F19 -> 15127.17 | H19: 2200 | I19: =SUM(F19:H19) -> 17702.17 | J19: =+I19*0.05 -> 885.1085 | K19: =+I19*0.09975 -> 1765.7915 | L19: =SUM(I19:K19) -> 20353.07 | M19: 20353.07 | N19: =+L19-M19 -> 0
A20: 44551 | B20: 31 octobre au 27 novembre 2021 | C20: 21-3332 | D20: 2 | E20: =380.75-D20 -> 378.75 | F20: =125*D20 -> 250 | G20: =19789.79-F20 -> 19539.79 | H20: 796.33 | I20: =SUM(F20:H20) -> 20586.12 | J20: =+I20*0.05 -> 1029.306 | K20: =+I20*0.09975 -> 2053.4655 | L20: =SUM(I20:K20) -> 23668.891 | M20: 23668.891 | N20: =+L20-M20 -> 0
A21: 44582 | B21: 28 nov 2021 au 25 déc 2021 | C21: 21-3384 | D21: 2.5 | E21: =237.25-D21 -> 234.75 | F21: =125*D21 -> 312.5 | G21: =12050.32-F21 -> 11737.82 | H21: 102.02 | I21: =SUM(F21:H21) -> 12152.34 | J21: =+I21*0.05 -> 607.617 | K21: =+I21*0.09975 -> 1212.1959 | L21: =SUM(I21:K21) -> 13972.153 | M21: 13972.153 | N21: =+L21-M21 -> 0
A22: 44592 | B22: 26 décembre 2021 au 29 janvier 2022 | C22: 22-3397 | D22: =2.5+42 -> 44.5 | E22: =395-D22 -> 350.5 | F22: =312.5+5250 -> 5562.5 | G22: =24989.09-F22 -> 19426.59 | I22: =SUM(F22:H22) -> 24989.09 | J22: =+I22*0.05 -> 1249.4545 | K22: =+I22*0.09975 -> 2492.6617 | L22: =SUM(I22:K22)-0.01 -> 28731.196 | M22: 28731.196 | N22: =+L22-M22 -> 0
A23: 44620 | B23: 30 janvier au 26 février 2022 | C23: 22-3435 | D23: =3.75+51.5 -> 55.25 | E23: =0.75+68.75+0.25+68+70+49.25+0.75 -> 257.75 | F23: =468.75+6437.5 -> 6906.25 | G23: =22990.21-F23 -> 16083.96 | H23: =+(82.39*4)+204.51+41.52 -> 575.59 | I23: =SUM(F23:H23) -> 23565.8 | J23: =+I23*0.05 -> 1178.29 | K23: =+I23*0.09975 -> 2350.6885 | L23: =SUM(I23:K23) -> 27094.779 | M23: 27094.779 | N23: =+L23-M23 -> 0
A24: 44651 | B24: 27 février au 2 avril 2022 | C24: 22-3461 | D24: =2.5+51.75 -> 54.25 | E24: =333.5-D24 -> 279.25 | F24: =312.5+6468.75 -> 6781.25 | G24: =22273.4-F24 -> 15492.15 | H24: =152.39+103.39+75.39+82.39+82.39+336.66+68.36+60.76 -> 961.73 | I24: =SUM(F24:H24) -> 23235.13 | J24: =+I24*0.05 -> 1161.7565 | K24: =+I24*0.09975 -> 2317.7042 | L24: =SUM(I24:K24) -> 26714.591 | M24: 26714.591 | N24: =+L24-M24 -> 0
A25: 44681 | B25: 3 au 30 avril 2022 | C25: 22-3492 | D25: =2.5+66.75 -> 69.25 | E25: =335-D25 -> 265.75 | F25: =312.5+8343.75 -> 8656.25 | G25: =24793.77-F25 -> 16137.52 | I25: =SUM(F25:H25) -> 24793.77 | J25: =+I25*0.05 -> 1239.6885 | K25: =+I25*0.09975 -> 2473.1786 | L25: =SUM(I25:K25) -> 28506.637 | M25: 28506.637 | N25: =+L25-M25 -> 0
A26: 44712 | B26: 1er au 28 mai 2022 | C26: 22-3520 | D26: =2+56 -> 58 | E26: =252-D26 -> 194 | F26: =250+7000 -> 7250 | G26: =18784.19-F26 -> 11534.19 | I26: =SUM(F26:H26) -> 18784.19 | J26: =+I26*0.05 -> 939.2095 | K26: =+I26*0.09975 -> 1873.723 | L26: =SUM(I26:K26) -> 21597.122 | M26: 21597.122 | N26: =+L26-M26 -> 0
A27: 44742 | B27: 29 mai au 2 juillet | C27: 22-3548 | D27: =2+59 -> 61 | E27: =215.25-D27 -> 154.25 | F27: =250+7375 -> 7625 | G27: =16813.16-F27 -> 9188.16 | H27: 1670.16 | I27: =SUM(F27:H27) -> 18483.32 | J27: =+I27*0.05 -> 924.166 | K27: =+I27*0.09975 -> 1843.7112 | L27: =SUM(I27:K27) -> 21251.197 | M27: 21251.197 | N27: =+L27-M27 -> 0
A28: 44773 | B28: 3 au 30 juillet 2022 | C28: 22-3596 | D28: 31.25 | E28: =113.25-D28 -> 82 | F28: =125+3781.25 -> 3906.25 | G28: =9160.18-F28 -> 5253.93 | I28: =SUM(F28:H28) -> 9160.18 | J28: =+I28*0.05 -> 458.009 | K28: =+I28*0.09975 -> 913.72796 | L28: =SUM(I28:K28) -> 10531.917 | M28: 10531.917 | N28: =+L28-M28 -> 0
A29: 44804 | B29: 31 juillet au 27 août 2022 | C29: 22-3634 | D29: =3.75+22.25 -> 26 | E29: =109.5-D29 -> 83.5 | F29: =468.75+2781.25 -> 3250 | G29: =8424.43-F29 -> 5174.43 | H29: 1149.81 | I29: =SUM(F29:H29) -> 9574.24 | J29: =+I29*0.05 -> 478.712 | K29: =+I29*0.09975 -> 955.03044 | L29: =SUM(I29:K29) -> 11007.982 | M29: 11007.982 | N29: =+L29-M29 -> 0
A30: 44834 | B30: 28 août au 1er octobre 2022 | C30: 22-3665 | D30: =3.5+49 -> 52.5 | E30: =230.25-D30 -> 177.75 | F30: =437.5+4410 -> 4847.5 | G30: =15726.43-F30 -> 10878.93 | H30: 1534.35 | I30: =SUM(F30:H30) -> 17260.78 | J30: =+I30*0.05 -> 863.039 | K30: =+I30*0.09975 -> 1721.7628 | L30: =SUM(I30:K30) -> 19845.582 | M30: 19845.582 | N30: =+L30-M30 -> 0
A31: 44865 | B31: 2 au 29 octobre 2022 | C31: 22-3734 | D31: =3.25+34.5 -> 37.75 | E31: =146.5-D31 -> 108.75 | F31: =406.25+3105 -> 3511.25 | G31: =10382.44-F31 -> 6871.19 | H31: 1797 | I31: =SUM(F31:H31) -> 12179.44 | J31: =+I31*0.05 -> 608.972 | K31: =+I31*0.09975 -> 1214.8991 | L31: =SUM(I31:K31) -> 14003.311 | M31: 14003.311 | N31: =+L31-M31 -> 0
A32: 44895 | B32: du 30 octobre au 26 novembre 2022 | C32: 22-3749 | D32: =2.25+45.5 -> 47.75 | E32: =175-D32 -> 127.25 | F32: =281.25+5687.5 -> 5968.75 | G32: =14132.55-F32 -> 8163.8 | H32: 2106.14 | I32: =SUM(F32:H32) -> 16238.69 | J32: =+I32*0.05 -> 811.9345 | K32: =+I32*0.09975 -> 1619.8093 | L32: =SUM(I32:K32) -> 18670.434 | M32: 18670.434 | N32: =+L32-M32 -> 0
A33: 44895 | B33: ajustement taux horaire | C33: 22-3795 | D33: 0 | E33: 0 | F33: 2922.5 | G33: 0 | I33: =SUM(F33:H33) -> 2922.5 | J33: =+I33*0.05 -> 146.125 | K33: 291.52 | L33: =SUM(I33:K33) -> 3360.145 | M33: 3360.145 | N33: =+L33-M33 -> 0
A34: 44926 | B34: du 27 novembre au 31 décembre 2022 | C34: 22-3799 | D34: 25 | E34: =83.25-D34 -> 58.25 | F34: =62.5+3062.5 -> 3125 | G34: =6877.73-F34 -> 3752.73 | H34: 106.39 | I34: =SUM(F34:H34) -> 6984.12 | J34: =+I34*0.05 -> 349.206 | K34: 696.67 | L34: =SUM(I34:K34) -> 8029.996 | M34: 8029.996 | N34: =+L34-M34 -> 0
A35: 44957 | B35: 1er au 28 janvier 2023 | C35: 23-3851 | D35: 23.25 | E35: =97.75-D35 -> 74.5 | F35: =2781.25+125 -> 2906.25 | G35: =7708.03-F35 -> 4801.78 | H35: 510.86 | I35: =SUM(F35:H35) -> 8218.89 | J35: =+I35*0.05 -> 410.9445 | K35: 819.83 | L35: =SUM(I35:K35) -> 9449.6645 | M35: 9449.6645 | N35: =+L35-M35 -> 0
A36: 44985 | B36: 29 janvier au 25 février 2023 | C36: 23-3875 | D36: 34.25 | E36: =112.5-D36 -> 78.25 | F36: =+D36*125 -> 4281.25 | G36: =9413.15-F36 -> 5131.9 | H36: 212.78 | I36: =SUM(F36:H36) -> 9625.93 | J36: =+I36*0.05 -> 481.2965 | K36: 960.19 | L36: =SUM(I36:K36) -> 11067.417 | M36: 11067.417 | N36: =+L36-M36 -> 0
A37: 45016 | B37: 26 février au 1er avril 2023 | C37: 23-3912 | D37: 43.25 | E37: =160.25-D37 -> 117 | F37: =+D37*125 -> 5406.25 | G37: =12007.33-F37 -> 6601.08 | H37: 1317.1 | I37: =SUM(F37:H37) -> 13324.43 | J37: =+I37*0.05 -> 666.2215 | K37: =+I37*0.09975 -> 1329.1119 | L37: =SUM(I37:K37) -> 15319.763 | M37: 15319.763 | N37: =+L37-M37 -> 0
A38: 45046 | B38: 2 au 29 avril 2023 | C38: 23-3953 | D38: 23.5 | E38: =102.25-D38 -> 78.75 | F38: =+D38*125 -> 2937.5 | G38: =7193.5-F38 -> 4256 | H38: 212.78 | I38: =SUM(F38:H38) -> 7406.28 | J38: =+I38*0.05 -> 370.314 | K38: =+I38*0.09975 -> 738.77643 | L38: =SUM(I38:K38) -> 8515.3704 | M38: 8515.3704 | N38: =+L38-M38 -> 0
A39: 45085 | B39: 30 avril au 3 juin 2023 | C39: 23-3997 | D39: 31.5 | E39: =107-D39 -> 75.5 | F39: =+D39*125 -> 3937.5 | G39: =7895.2-F39 -> 3957.7 | H39: 809.85 | I39: =SUM(F39:H39) -> 8705.05 | J39: =+I39*0.05 -> 435.2525 | K39: =+I39*0.09975 -> 868.32874 | L39: =SUM(I39:K39) -> 10008.631 | M39: 10008.631 | N39: =+L39-M39 -> 0
A40: 45107 | B40: 4 juin au 1er juillet 2023 | C40: 23-4034 | D40: 10.25 | E40: =43-D40 -> 32.75 | F40: =+D40*125 -> 1281.25 | G40: =2861.34-F40 -> 1580.09 | H40: 116.29 | I40: =SUM(F40:H40) -> 2977.63 | J40: =+I40*0.05 -> 148.8815 | K40: =+I40*0.09975 -> 297.01859 | L40: =SUM(I40:K40) -> 3423.5301 | M40: 3423.5301 | N40: =+L40-M40 -> 0
A41: 45138 | B41: 2 au 29 juillet 2023 | C41: 23-4080 | D41: 16.5 | E41: 30.5 | F41: =+D41*125 -> 2062.5 | G41: =598.5+817 -> 1415.5 | I41: =SUM(F41:H41) -> 3478 | J41: =+I41*0.05 -> 173.9 | K41: =+I41*0.09975 -> 346.9305 | L41: =SUM(I41:K41) -> 3998.8305 | M41: 3998.8305 | N41: =+L41-M41 -> 0
A42: 45171 | B42: 30 juillet au 2 septembre 2023 | C42: 23-4128 | D42: 57.25 | E42: =185.5-D42 -> 128.25 | F42: =+D42*125 -> 7156.25 | G42: =13243.23-F42 -> 6086.98 | I42: =SUM(F42:H42) -> 13243.23 | J42: =+I42*0.05 -> 662.1615 | K42: =+I42*0.09975 -> 1321.0122 | L42: =SUM(I42:K42) -> 15226.404 | M42: 15226.404 | N42: =+L42-M42 -> 0
A43: 45199 | B43: 3 au 30 septembre 2023 | C43: 23-4167 | D43: =0.5+40.75 -> 41.25 | E43: =76.25-D43 -> 35 | F43: =+D43*125 -> 5156.25 | G43: =6811.63-F43 -> 1655.38 | H43: 423.88 | I43: =SUM(F43:H43) -> 7235.51 | J43: =+I43*0.05 -> 361.7755 | K43: =+I43*0.09975 -> 721.74212 | L43: =SUM(I43:K43) -> 8319.0276 | M43: 8319.0276 | N43: =+L43-M43 -> 0
A44: 45230 | B44: 1er au 28 octobre 2023 | C44: 23-4219 | D44: 14.5 | E44: =21.25-D44 -> 6.75 | F44: =+D44*125 -> 1812.5 | G44: =2221.95-F44 -> 409.45 | I44: =SUM(F44:H44) -> 2221.95 | J44: =+I44*0.05 -> 111.0975 | K44: =+I44*0.09975 -> 221.63951 | L44: =SUM(I44:K44) -> 2554.687 | M44: 2554.687 | N44: =+L44-M44 -> 0
A45: 45262 | B45: 29 octobre au 2 décembre 2023 | C45: 23-4283 | D45: 27.75 | E45: =48.75-D45 -> 21 | F45: =+D45*125 -> 3468.75 | G45: =4638.44-F45 -> 1169.69 | I45: =SUM(F45:H45) -> 4638.44 | J45: =+I45*0.05 -> 231.922 | K45: =+I45*0.09975-0.005 -> 462.67939 | L45: =SUM(I45:K45) -> 5333.0414 | M45: 5333.0414 | N45: =+L45-M45 -> 0
A46: 45291 | B46: 3 au 31 décembre 2023 | C46: 23-4336 | D46: 12.5 | E46: 37.5 | F46: =+D46*125 -> 1562.5 | G46: =243.2+1432.13 -> 1675.33 | I46: =SUM(F46:H46) -> 3237.83 | J46: =+I46*0.05 -> 161.8915 | K46: =+I46*0.09975-0.005 -> 322.96854 | L46: =SUM(I46:K46) -> 3722.69 | M46: 3722.69 | N46: =+L46-M46 -> 0
A47: 45341 | B47: au 31 janvier 2024 | C47: 24-4394 | D47: 8.5 | E47: 2.75 | F47: =+D47*125 -> 1062.5 | G47: =1193.6-F47 -> 131.1 | I47: =SUM(F47:H47) -> 1193.6 | J47: =+I47*0.05 -> 59.68 | K47: =+I47*0.09975 -> 119.0616 | L47: =SUM(I47:K47) -> 1372.3416 | M47: 1372.3416 | N47: =+L47-M47 -> 0
A48: 45382 | B48: au 29 février 2024 | C48: 24-4439 | D48: 13.75 | E48: 43.75 | F48: =+D48*125 -> 1718.75 | G48: =1838.25+45.6 -> 1883.85 | I48: =SUM(F48:H48) -> 3602.6 | J48: =+I48*0.05 -> 180.13 | K48: =+I48*0.09975 -> 359.35935 | L48: =SUM(I48:K48) -> 4142.0894 | M48: 4142.0894 | N48: =+L48-M48 -> 0
A49: 45397 | B49: au 31 mars 2024 | C49: 24-4497 | D49: 10.25 | E49: 4 | F49: =+D49*125 -> 1281.25 | G49: 171 | I49: =SUM(F49:H49) -> 1452.25 | J49: =+I49*0.05 -> 72.6125 | K49: =+I49*0.09975 -> 144.86194 | L49: =SUM(I49:K49) -> 1669.7244 | M49: 1669.7244 | N49: =+L49-M49 -> 0
A50: 45427 | B50: au 30 avril 2024 | C50: 24-4562 | D50: 9.5 | E50: 5 | F50: =+D50*125 -> 1187.5 | G50: 226.6 | I50: =SUM(F50:H50) -> 1414.1 | J50: =+I50*0.05 -> 70.705 | K50: =+I50*0.09975 -> 141.05648 | L50: =SUM(I50:K50) -> 1625.8615 | M50: 1625.8615 | N50: =+L50-M50 -> 0
A51: 45458 | B51: au 31 mai 2024 | C51: 24-4639 | D51: 8.5 | E51: 2.25 | F51: =+D51*125 -> 1062.5 | G51: 101.97 | I51: =SUM(F51:H51) -> 1164.47 | J51: =+I51*0.05 -> 58.2235 | K51: =+I51*0.09975 -> 116.15588 | L51: =SUM(I51:K51) -> 1338.8494 | M51: 1338.8494 | N51: =+L51-M51 -> 0
A52: 45481 | B52: au 30 juin 2024 | C52: 24-4698 | D52: 6.5 | E52: 1.5 | F52: =+D52*125 -> 812.5 | G52: =45.32+27.31 -> 72.63 | I52: =SUM(F52:H52) -> 885.13 | J52: =+I52*0.05 -> 44.2565 | K52: =+I52*0.09975 -> 88.291718 | L52: =SUM(I52:K52) -> 1017.6782 | M52: 1017.6782 | N52: =+L52-M52 -> 0
A53: 45504 | B53: au 31 juillet 2024 | C53: 24-4751 | D53: 6.5 | E53: 1 | F53: =+D53*125 -> 812.5 | G53: 45.32 | I53: =SUM(F53:H53) -> 857.82 | J53: =+I53*0.05 -> 42.891 | K53: =+I53*0.09975 -> 85.567545 | L53: =SUM(I53:K53) -> 986.27855 | M53: 986.27855 | N53: =+L53-M53 -> 0
A54: 45551 | B54: au 31 aout 2024 | C54: 24-4808 | D54: 6.25 | E54: 0 | F54: =+D54*125 -> 781.25 | G54: 0 | I54: =SUM(F54:H54) -> 781.25 | J54: =+I54*0.05 -> 39.0625 | K54: =+I54*0.09975 -> 77.929688 | L54: =SUM(I54:K54) -> 898.24219 | M54: 898.24219 | N54: =+L54-M54 -> 0
A55: 45565 | B55: au 30 septembre 2024 | C55: 24-4828 | D55: 1 | E55: 0.25 | F55: =+D55*125 -> 125 | G55: 19.38 | I55: =SUM(F55:H55) -> 144.38 | J55: =+I55*0.05 -> 7.219 | K55: =+I55*0.09975 -> 14.401905 | L55: =SUM(I55:K55) -> 166.0009 | M55: 166.0009 | N55: =+L55-M55 -> 0 | O55: 50000
A56: 45607 | B56: au 31 octobre 2024 | C56: 24-4891 | D56: 1.75 | E56: 0 | F56: =+D56*125 -> 218.75 | G56: 0 | I56: =SUM(F56:H56) -> 218.75 | J56: =+I56*0.05 -> 10.9375 | K56: =+I56*0.09975 -> 21.820312 | L56: =SUM(I56:K56) -> 251.50781 | M56: 251.50781 | N56: =+L56-M56 -> 0
A57: 45635 | B57: au 30 novembre 2024 | C57: 24-4949 | D57: 1.25 | E57: 2 | F57: =+D57*125 -> 156.25 | G57: 95 | I57: =SUM(F57:H57) -> 251.25 | J57: =+I57*0.05 -> 12.5625 | K57: =+I57*0.09975 -> 25.062188 | L57: =SUM(I57:K57) -> 288.87469 | M57: 288.87469 | N57: =+L57-M57 -> 0
A58: 45657 | B58: au 31 décembre 2024 | C58: 24-5011 | D58: 3.75 | E58: 0 | F58: =+D58*125 -> 468.75 | G58: 0 | I58: =SUM(F58:H58) -> 468.75 | J58: =+I58*0.05 -> 23.4375 | K58: =+I58*0.09975 -> 46.757812 | L58: =SUM(I58:K58) -> 538.94531 | M58: 538.94531 | N58: =+L58-M58 -> 0
A59: 45688 | B59: au 31 janvier 2025 | C59: 25-5062 | D59: 0.25 | F59: =+D59*125 -> 31.25 | G59: 0 | I59: =SUM(F59:H59) -> 31.25 | J59: =+I59*0.05 -> 1.5625 | K59: =+I59*0.09975 -> 3.1171875 | L59: =SUM(I59:K59) -> 35.929688 | M59: 35.929688 | N59: =+L59-M59 -> 0
A60: 45716 | B60: au 28 février 2025 | C60: 25-5109 | D60: 2.75 | E60: 0.5 | F60: =+D60*125 -> 343.75 | G60: 31 | I60: =SUM(F60:H60) -> 374.75 | J60: =+I60*0.05 -> 18.7375 | K60: =+I60*0.09975 -> 37.381312 | L60: =SUM(I60:K60) -> 430.86881 | M60: 430.86881 | N60: =+L60-M60 -> 0
A61: 45747 | B61: au 31 mars 2025 | I61: =SUM(F61:H61) -> 0 | J61: =+I61*0.05 -> 0 | K61: =+I61*0.09975 -> 0 | L61: =SUM(I61:K61) -> 0 | M61: 0 | N61: =+L61-M61 -> 0
A62: 45777 | B62: au 30 avril 2025 | C62: 25-5259 | D62: 1 | E62: 0.5 | F62: =+D62*125 -> 125 | G62: 29.45 | I62: =SUM(F62:H62) -> 154.45 | J62: =+I62*0.05 -> 7.7225 | K62: =+I62*0.09975 -> 15.406387 | L62: =SUM(I62:K62) -> 177.57889 | M62: 177.57889 | N62: =+L62-M62 -> 0
A63: 45808 | B63: au 31 mai 2025 | C63: 25-5315 | D63: 5 | E63: 0.5 | F63: =+D63*125 -> 625 | G63: 29.45 | I63: =SUM(F63:H63) -> 654.45 | J63: =+I63*0.05 -> 32.7225 | K63: =+I63*0.09975 -> 65.281388 | L63: =SUM(I63:K63) -> 752.45389 | N63: =+L63-M63 -> 752.45389
A64: 45838 | B64: au 28 juin 2025 | C64: 25-5374 | D64: 3.25 | E64: 0.25 | F64: =+D64*125 -> 406.25 | G64: 14.73 | I64: =SUM(F64:H64) -> 420.98 | J64: =+I64*0.05 -> 21.049 | K64: =+I64*0.09975 -> 41.992755 | L64: =SUM(I64:K64) -> 484.02175 | N64: =+L64-M64 -> 484.02175
A65: 45869 | B65: au 31 juillet 2025 | C65: 25-5423 | D65: 1 | E65: 1 | F65: =+D65*125 -> 125 | G65: =189.61-F65 -> 64.61 | I65: =SUM(F65:H65) -> 189.61 | J65: =+I65*0.05 -> 9.4805 | K65: =+I65*0.09975 -> 18.913598 | L65: =SUM(I65:K65) -> 218.0041 | N65: =+L65-M65 -> 218.0041
A66: 45900 | B66: au 30 aout 2025 | C66: 25-5469 | D66: 0 | E66: 1.25 | F66: =+D66*125 -> 0 | G66: 87.4 | I66: =SUM(F66:H66) -> 87.4 | J66: =+I66*0.05 -> 4.37 | K66: =+I66*0.09975 -> 8.71815 | L66: =SUM(I66:K66) -> 100.48815 | N66: =+L66-M66 -> 100.48815
A67: 45930 | B67: au 27 septembre 2025 | C67: 25-5529 | D67: 1.5 | E67: 0.25 | F67: =+D67*125 -> 187.5 | G67: 16.63 | I67: =SUM(F67:H67) -> 204.13 | J67: =+I67*0.05 -> 10.2065 | K67: =+I67*0.09975 -> 20.361968 | L67: =SUM(I67:K67) -> 234.69847 | N67: =+L67-M67 -> 234.69847
D69: =SUM(D4:D68) -> 1173.5 | E69: =SUM(E4:E68) -> 10972.5 | F69: =SUM(F4:F68) -> 146687.5 | G69: =SUM(G4:G68) -> 595356.23 | H69: =SUM(H4:H68) -> 20480.56 | I69: =SUM(I4:I68) -> 762524.29 | J69: =SUM(J4:J68) -> 38126.215 | K69: =SUM(K4:K68) -> 76061.792 | ... N69: =SUM(N4:N68) -> 1789.6664 | O69: =SUM(O5:O68) -> 437500
E70: =+E69+D69 -> 12146

Sheet Société A
A1: Société A
A3: Date | B3: période | C3: facture | D3: Heures Associés | E3: Heures Employés | F3: Honoraires associés | G3: Honoraires employés | H3: Frais refacturables | I3: Sous-TOTAL | J3: TPS | K3: TVQ | L3: TOTAL | M3: payé | N3: dû | O3: Partage
A4: 17-09-2020 | B4: 1er mai au 1er août 2020 | C4: F3769 | D4: 237 | E4: 251 | F4: =7406.25+1612.5+12343.75+8531.25 -> 29893.75 | G4: =4598.95+6304.2+3703.92+654.08+132.54 -> 15393.69 | H4: 6075.25 | I4: =SUM(F4:H4) -> 51362.69 | J4: =+I4*0.05 -> 2568.1345 | K4: =+I4*0.09975 -> 5123.4283 | L4: =SUM(I4:K4) -> 59054.253 | M4: 59054.253 | N4: =+L4-M4 -> 0
A5: 17-09-2020 | B5: 2 au 29 août 2020 | C5: F3770 | D5: 141.25 | E5: 239.75 | F5: =4468.75+1162.5+8656.25+3562.5 -> 17850 | G5: =32873.6-F5 -> 15023.6 | I5: =SUM(F5:H5) -> 32873.6 | J5: =+I5*0.05 -> 1643.68 | K5: =+I5*0.09975 -> 3279.1416 | L5: =SUM(I5:K5) -> 37796.422 | M5: 37796.422 | N5: =+L5-M5 -> 0
A6: 08-10-2020 | B6: 30 août au 3 octobre 2020 | C6: F3800 | D6: 299.5 | E6: 619.5 | F6: 37762.5 | G6: =72312.05-H6-F6 -> 34256.1 | H6: 293.45 | I6: =SUM(F6:H6) -> 72312.05 | J6: =+I6*0.05 -> 3615.6025 | K6: =+I6*0.09975 -> 7213.127 | L6: =SUM(I6:K6) -> 83140.779 | M6: 83140.779 | N6: =+L6-M6 -> 0 | O6: 75000
A7: 31-10-2020 | B7: 4 au 31 octobre 2020 | C7: F3830 | D7: 304 | E7: =1015.75-D7 -> 711.75 | F7: 38250 | G7: =77024.44-F7 -> 38774.44 | I7: =SUM(F7:H7) -> 77024.44 | J7: =+I7*0.05 -> 3851.222 | K7: =+I7*0.09975 -> 7683.1879 | L7: =SUM(I7:K7) -> 88558.85 | M7: 88558.85 | N7: =+L7-M7 -> 0
A8: 44166 | B8: 1er au 28 novembre 2020 | C8: F3879 | D8: 283 | E8: =890.5-D8 -> 607.5 | F8: 35681.25 | G8: =70261.3-F8 -> 34580.05 | I8: =SUM(F8:H8) -> 70261.3 | J8: =+I8*0.05 -> 3513.065 | K8: =+I8*0.09975 -> 7008.5647 | L8: =SUM(I8:K8) -> 80782.93 | M8: 80782.93 | N8: =+L8-M8 -> 0
A9: 43843 | B9: 29 novembre au 2 janvier 2021 | C9: F3922 | D9: 227.75 | E9: =792.75-D9 -> 565 | F9: 28606.25 | G9: =60107.92-F9 -> 31501.67 | H9: 178.9 | I9: =SUM(F9:H9) -> 60286.82 | J9: =+I9*0.05 -> 3014.341 | K9: =+I9*0.09975 -> 6013.6103 | L9: =SUM(I9:K9) -> 69314.771 | M9: 69314.771 | N9: =+L9-M9 -> 0
A10: 43866 | B10: 3 au 30 janvier 2021 | C10: F3931 | D10: 254.25 | E10: =965.5-D10 -> 711.25 | F10: =7187.5+1575+12125+11156.25 -> 32043.75 | G10: =72235.05-F10 -> 40191.3 | I10: =SUM(F10:H10) -> 72235.05 | J10: =+I10*0.05 -> 3611.7525 | K10: =+I10*0.09975 -> 7205.4462 | L10: =SUM(I10:K10) -> 83052.249 | M10: 83052.249 | N10: =+L10-M10 -> 0
A11: 44263 | B11: 31 janvier au 27 février 2021 | C11: F3974 | D11: 243.75 | E11: =1279-D11 -> 1035.25 | F11: =4500+1950+14375+9968.75 -> 30793.75 | G11: =89493.04-F11-17.25 -> 58682.04 | H11: =17.25+2100 -> 2117.25 | I11: =SUM(F11:H11) -> 91593.04 | J11: =+I11*0.05 -> 4579.652 | K11: =+I11*0.09975 -> 9136.4057 | L11: =SUM(I11:K11)+48.29 -> 105357.39 | M11: 105357.39 | N11: =+L11-M11 -> 0 | O11: 325000
A12: 44307 | B12: 28 février au 3 avril 2021 | C12: F4006 | D12: 176 | E12: =1308-D12 -> 1132 | F12: =500+2100+15625+4125 -> 22350 | G12: =84358.7-F12-20.75-247.5 -> 61740.45 | H12: =20.75+247.5 -> 268.25 | I12: =SUM(F12:H12) -> 84358.7 | J12: =+I12*0.05 -> 4217.935 | K12: =+I12*0.09975 -> 8414.7803 | L12: =SUM(I12:K12) -> 96991.415 | M12: 96991.415 | N12: =+L12-M12 -> 0
A13: 44328 | B13: 4 avril au 1er mai 2021 | C13: F4031 | D13: 136.5 | E13: 934.25 | F13: =1575+12000+3750 -> 17325 | G13: =67770.28-F13-73.93 -> 50371.35 | H13: =38.18+35.75 -> 73.93 | I13: =SUM(F13:H13) -> 67770.28 | J13: =+I13*0.05 -> 3388.514 | K13: =+I13*0.09975 -> 6760.0854 | L13: =SUM(I13:K13) -> 77918.879 | M13: 77918.879 | N13: =+L13-M13 -> 0
A14: 44355 | B14: 2 au 29 mai 2021 | C14: F4056 | D14: 94.5 | E14: =590.25-D14 -> 495.75 | F14: =1350+10500+187.5 -> 12037.5 | G14: =34833.7-F14-H14 -> 22791.9 | H14: 4.3 | I14: =SUM(F14:H14) -> 34833.7 | J14: =+I14*0.05 -> 1741.685 | K14: =+I14*0.09975 -> 3474.6616 | L14: =SUM(I14:K14) -> 40050.047 | M14: 40050.047 | N14: =+L14-M14 -> 0
A15: 44391 | B15: 30 mai au 26 juin 2021 | C15: F4108 | D15: =7.5+67.5+4.75 -> 79.75 | E15: =3+58+0.5+10.5+22+38.25+78+6.25+2.5+46+1.5 -> 266.5 | F15: =1125+8437.5+593.75 -> 10156.25 | G15: =304.95+4683.5+26.6+578.55+898.7+1453.5+2779.14+356.25+106.88+2316.1+69.83 -> 13574 | I15: =SUM(F15:H15) -> 23730.25 | J15: =+I15*0.05 -> 1186.5125 | K15: =+I15*0.09975 -> 2367.0924 | L15: =SUM(I15:K15) -> 27283.855 | M15: 27283.855 | N15: =+L15-M15 -> 0
A16: 44417 | B16: 27 juin au 31 juillet 2021 | C16: F4120 | D16: =5.5+46 -> 51.5 | E16: =43+1+5.25+28.5+2 -> 79.75 | F16: =825+5750 -> 6575 | G16: =3472.25+55.1+199.5+1434.98+93.1 -> 5254.93 | I16: =SUM(F16:H16) -> 11829.93 | J16: =+I16*0.05 -> 591.4965 | K16: =+I16*0.09975 -> 1180.0355 | L16: =SUM(I16:K16)+0.01 -> 13601.472 | M16: 13601.472 | N16: =+L16-M16 -> 0
A17: 44441 | B17: 1er au 29 août 2021 | C17: F4142 | D17: =6+54.25+5 -> 65.25 | E17: =11.5+13.75+2+49+16.5+4.25+4+25.75+1 -> 127.75 | F17: =900+6781.25+625 -> 8306.25 | G17: =928.63+757.63+70.3+2001.65+627+177.65+142.52+1296.51+46.55 -> 6048.44 | H17: 12.78 | I17: =SUM(F17:H17) -> 14367.47 | J17: =+I17*0.05 -> 718.3735 | K17: =+I17*0.09975 -> 1433.1551 | L17: =SUM(I17:K17) -> 16518.999 | M17: 16518.999 | N17: =+L17-M17 -> 0 | O17: 375000
A18: 44484 | B18: 30 août au 2 octobre 2021 | C18: F4181 | D18: =2+20.25+27+11 -> 60.25 | E18: =8.75+3+0.7+8.25+0.5+33+1.25 -> 55.45 | F18: =300+2531.25+3375+1375 -> 7581.25 | G18: =706.56+165.3+30.64+313.5+21.38+1661.55+58.19 -> 2957.12 | H18: =70.52+276+20.75+8584.25 -> 8951.52 | I18: =SUM(F18:H18) -> 19489.89 | J18: =+I18*0.05 -> 974.4945 | K18: =+I18*0.09975 -> 1944.1165 | L18: =SUM(I18:K18) -> 22408.501 | M18: 22408.501 | N18: =+L18-M18 -> 0
A19: 44517 | B19: 3 au 30 octobre 2021 | C19: F4210 | D19: =2.5+21+32.5+18 -> 74 | E19: =3+3.75+6.75+12.5+5.75+53.75+56.75+13.5+0.5+24+1.5 -> 181.75 | F19: =375+2625+4062.5+2250 -> 9312.5 | G19: =17061.35-F19 -> 7748.85 | I19: =SUM(F19:H19) -> 17061.35 | J19: =+I19*0.05 -> 853.0675 | K19: =+I19*0.09975 -> 1701.8697 | L19: =SUM(I19:K19) -> 19616.287 | M19: 19616.287 | N19: =+L19-M19 -> 0
A20: 44536 | B20: 31 octobre au 27 novembre 2021 | C20: F4227 | D20: =1+6.5+35.5+7 -> 50 | E20: =75+1.5+51.25+26+3+24.25+1.25 -> 182.25 | F20: =150+812.5+4437.5+875 -> 6275 | G20: =5415+82.65+1947.5+926.38+119.7+1220.99+58.19 -> 9770.41 | H20: =31.82+178.7+6.5 -> 217.02 | I20: =SUM(F20:H20) -> 16262.43 | J20: =+I20*0.05 -> 813.1215 | K20: =+I20*0.09975 -> 1622.1774 | L20: =SUM(I20:K20) -> 18697.729 | M20: 18697.729 | N20: =+L20-M20 -> 0
A21: 44207 | B21: 28 nov 2021 au 1er jan 2022 | C21: F4259 | D21: =2.5+21+11+32 -> 66.5 | E21: =3+49.5+63.25+1+39+1+4.5+18.75+1 -> 181 | F21: =375+2625+1375+4000 -> 8375 | G21: =304.95+3573.9+2403.5+41.8+1389.57+57+192.38+944.06+46.55 -> 8953.71 | H21: =75.68+104.27+364.55 -> 544.5 | I21: =SUM(F21:H21) -> 17873.21 | J21: =+I21*0.05 -> 893.6605 | K21: =+I21*0.09975 -> 1782.8527 | L21: =SUM(I21:K21) -> 20549.723 | M21: 20549.723 | N21: =+L21-M21 -> 0
A22: 44610 | B22: 2 au 29 janvier 2022 | C22: F4301 | D22: =3.5+32.5+34.5+7.75 -> 78.25 | E22: =26+66+23.25+86.25+4.75+124+4.25+19+41+1.25 -> 395.75 | F22: =525+4062.5+4312.5+968.75 -> 9868.75 | G22: =30707.15-F22 -> 20838.4 | I22: =SUM(F22:H22) -> 30707.15 | J22: =+I22*0.05 -> 1535.3575 | K22: =+I22*0.09975 -> 3063.0382 | L22: =SUM(I22:K22) -> 35305.546 | M22: 35305.546 | N22: =+L22-M22 -> 0
A23: 44643 | B23: 30 janvier au 26 février 2022 | C23: F4329 | D23: =5.5+49+28.5+5.25 -> 88.25 | E23: =36+86.25+0.5+1.5+60.75+28+58.5+40.25+1.5 -> 313.25 | F23: =825+6125+3562.5+656.25 -> 11168.75 | G23: =30026.6-F23-H23 -> 18785.17 | H23: =32.68+40 -> 72.68 | I23: =SUM(F23:H23) -> 30026.6 | J23: =+I23*0.05 -> 1501.33 | K23: =+I23*0.09975 -> 2995.1534 | L23: =SUM(I23:K23) -> 34523.083 | M23: 34523.083 | N23: =+L23-M23 -> 0
A24: 44671 | B24: 27 février au 2 avril 2022 | C24: F4353 | D24: =5.5+48.5+56.5+11.75 -> 122.25 | E24: =9+1+99.75+23.5+88.25+42.5+67+2.5+56.5+1.5 -> 391.5 | F24: =825+6062.5+7062.5+1468.75 -> 15418.75 | G24: =37652.98-F24-H24 -> 21282.25 | H24: =83.42+683.1+58.17+127.29 -> 951.98 | I24: =SUM(F24:H24) -> 37652.98 | J24: =+I24*0.05 -> 1882.649 | K24: =+I24*0.09975 -> 3755.8848 | L24: =SUM(I24:K24) -> 43291.514 | M24: 43291.514 | N24: =+L24-M24 -> 0
A25: 44694 | B25: 3 au 30 avril 2022 | C25: F4390 | D25: =1.5+14.5+29.75+2 -> 47.75 | E25: =2+121+5+45+8.5+9.5+27+1.5 -> 219.5 | F25: =225+1812.5+3718.75+250 -> 6006.25 | G25: =19792.48-F25-H25 -> 13686.47 | H25: 99.76 | I25: =SUM(F25:H25) -> 19792.48 | J25: =+I25*0.05 -> 989.624 | K25: =+I25*0.09975 -> 1974.2999 | L25: =SUM(I25:K25) -> 22756.404 | M25: 22756.404 | N25: =+L25-M25 -> 0
A26: 44742 | B26: 1er au 28 mai 2022 | C26: F4444 | D26: =4+33+39.5+1.5 -> 78 | E26: =4.5+114.75+36+7.25+7.5+15.75+54+8.75+31.2 -> 279.7 | F26: =600+4125+4937.5+187.5 -> 9850 | G26: =27686.24-F26-H26 -> 17671.24 | H26: 165 | I26: =SUM(F26:H26) -> 27686.24 | J26: =+I26*0.05 -> 1384.312 | K26: =+I26*0.09975 -> 2761.7024 | L26: =SUM(I26:K26) -> 31832.254 | M26: 31832.254 | N26: =+L26-M26 -> 0
A27: 44749 | B27: 29 mai au 2 juillet 2022 | C27: F4445 | D27: =2+16.5+43.5 -> 62 | E27: =8.25+117.5+98+1.25+24.25+49.5+25+7.5+70.5+33.75+0.5+1 -> 437 | F27: =300+2062.5+5437.5 -> 7800 | G27: =33092.42-F27-H27 -> 23076.1 | H27: =229+746.45+40.87+1200 -> 2216.32 | I27: =SUM(F27:H27) -> 33092.42 | J27: 1594.62 | K27: 3181.27 | L27: =SUM(I27:K27) -> 37868.31 | M27: 37868.31 | N27: =+L27-M27 -> 0
A28: 44796 | B28: 3 au 30 juillet 2022 | C28: F4496 | D28: =2+19+20.5+2.5 -> 44 | E28: =345-D28 -> 301 | F28: =300+2375+2562.5+312.5 -> 5550 | G28: =22623.64-F28-H28 -> 16860.14 | H28: 213.5 | I28: =SUM(F28:H28) -> 22623.64 | J28: =+I28*0.05 -> 1131.182 | K28: =+I28*0.09975 -> 2256.7081 | L28: =SUM(I28:K28) -> 26011.53 | M28: 26011.53 | N28: =+L28-M28 -> 0
A29: 44818 | B29: 31 juillet au 3 septembre 2022 | C29: F4519 | D29: =2+19+42+2.5 -> 65.5 | E29: =10.5+139+83+85.5+63.5+7.5+36.5+1 -> 426.5 | F29: 8237.5 | G29: =33255.96-H29-F29 -> 23749.06 | H29: =309+952.4+8 -> 1269.4 | I29: =SUM(F29:H29) -> 33255.96 | J29: =+I29*0.05 -> 1662.798 | K29: =+I29*0.09975 -> 3317.282 | L29: =SUM(I29:K29) -> 38236.04 | M29: 38236.04 | N29: =+L29-M29 -> 0
A30: 44847 | B30: 4 septembre au 1er octobre 202 | C30: F4539 | D30: =2+17+59+1 -> 79 | E30: 406.5 | F30: =300+2125+7375+125 -> 9925 | G30: =33211.08-F30-H30 -> 22746.09 | H30: =405.5+50.5+65.04+18.95 -> 539.99 | I30: =SUM(F30:H30) -> 33211.08 | J30: 1657.3 | K30: 3306.32 | L30: =SUM(I30:K30) -> 38174.7 | M30: 38174.7 | N30: =+L30-M30 -> 0
A31: 44886 | B31: 2 au 29 octobre 2022 | C31: F4568 | D31: =1+6+50.5+54.25 -> 111.75 | E31: =534-D31 -> 422.25 | F31: =150+750+6312.5+6781.25 -> 13993.75 | G31: =37300.46-401-F31 -> 22905.71 | H31: 401 | I31: =SUM(F31:H31) -> 37300.46 | J31: =+I31*0.05 -> 1865.023 | K31: =+I31*0.09975 -> 3720.7209 | L31: =SUM(I31:K31) -> 42886.204 | M31: 42886.204 | N31: =+L31-M31 -> 0
A32: 44915 | B32: 30 octobre au 26 novembre 2022 | C32: F4603 | D32: =9.5+61+61.25 -> 131.75 | E32: =560.25-D32 -> 428.5 | F32: =150+1062.5+7625+7656.25 -> 16493.75 | G32: =40529.5-H32-F32 -> 23602.75 | H32: 433 | I32: =SUM(F32:H32) -> 40529.5 | J32: =+I32*0.05 -> 2026.475 | K32: 4042.82 | L32: =SUM(I32:K32) -> 46598.795 | M32: 46598.795 | N32: =+L32-M32 -> 0
A33: 44926 | B33: 27 novembre au 31 décembre 2022 | C33: F4631 | D33: =1+3.5+53.25+85 -> 142.75 | E33: =572.75-D33 -> 430 | F33: =150+437.5+6656.25+10625 -> 17868.75 | G33: =41650.79-H33-F33 -> 23507.04 | H33: 275 | I33: =SUM(F33:H33) -> 41650.79 | J33: =+I33*0.05 -> 2082.5395 | K33: =+I33*0.09975 -> 4154.6663 | L33: =SUM(I33:K33) -> 47887.996 | M33: 47887.996 | N33: =+L33-M33 -> 0
A34: 44957 | B34: 1er au 28 janvier 2023 | C34: F4643 | D34: =0.5+45.75+56.25 -> 102.5 | E34: =453-D34 -> 350.5 | F34: =75+5718.75+7031.25 -> 12825 | G34: =34076.49-F34-H34 -> 20976.49 | H34: 275 | I34: =SUM(F34:H34) -> 34076.49 | J34: =+I34*0.05 -> 1703.8245 | K34: =+I34*0.09975 -> 3399.1299 | L34: =SUM(I34:K34) -> 39179.444 | M34: 39179.444 | N34: =+L34-M34 -> 0
A35: 45019 | B35: 29 janvier au 25 février 2023 | C35: F4676 | D35: =1+7+40.5+77.5 -> 126 | E35: =671.25-D35 -> 545.25 | F35: =150+875+5062.5+9687.5 -> 15775 | G35: =47949.92-F35-H35 -> 31779.42 | H35: 395.5 | I35: =SUM(F35:H35) -> 47949.92 | J35: =+I35*0.05 -> 2397.496 | K35: =+I35*0.09975 -> 4783.0045 | L35: =SUM(I35:K35) -> 55130.421 | M35: 55130.421 | N35: =+L35-M35 -> 0
A36: 45034 | B36: 26 février au 1er avril 2023 | C36: F4696 | D36: =3.5+28+78+116.5 -> 226 | E36: =1094.25-D36 -> 868.25 | F36: =525+3500+9750+14562.5 -> 28337.5 | G36: =79288.96-H36-F36 -> 48812.44 | H36: =1693.5+17.97+427.55 -> 2139.02 | I36: =SUM(F36:H36) -> 79288.96 | J36: =+I36*0.05 -> 3964.448 | K36: =+I36*0.09975 -> 7909.0738 | L36: =SUM(I36:K36) -> 91162.482 | M36: 91162.482 | N36: =+L36-M36 -> 0
A37: 16-05-2023 | B37: 2 au 29 avril 2023 | C37: F4751 | D37: =3+25+56+105.5 -> 189.5 | E37: =753.25-D37 -> 563.75 | F37: =450+3125+7000+13187.5 -> 23762.5 | G37: =55945.39-F37-H37 -> 31759.47 | H37: =304+36+83.42 -> 423.42 | I37: =SUM(F37:H37) -> 55945.39 | J37: =+I37*0.05 -> 2797.2695 | K37: =+I37*0.09975 -> 5580.5527 | L37: =SUM(I37:K37) -> 64323.212 | M37: 64323.212 | N37: =+L37-M37 -> 0
A38: 14-06-2023 | B38: 30 avril au 3 juin 2023 | C38: F4779 | D38: =4+32+46+114+2.75 -> 198.75 | E38: =982.5-D38 -> 783.75 | F38: =600+4000+5750+14250+343.75 -> 24943.75 | G38: =71157.58-F38-H38 -> 44593.97 | H38: =1264+355.86 -> 1619.86 | I38: =SUM(F38:H38) -> 71157.58 | J38: =+I38*0.05 -> 3557.879 | K38: =+I38*0.09975 -> 7097.9686 | L38: =SUM(I38:K38) -> 81813.428 | M38: 81813.428 | N38: =+L38-M38 -> 0
A39: 12-07-2023 | B39: 4 juin au 1er juillet 2023 | C39: F4822 | D39: 171 | E39: =736.75-D39 -> 565.75 | F39: 21437.5 | G39: =55257.56-F39-H39 -> 33114.64 | H39: 705.42 | I39: =SUM(F39:H39) -> 55257.56 | J39: =+I39*0.05 -> 2762.878 | K39: =+I39*0.09975 -> 5511.9416 | L39: =SUM(I39:K39) -> 63532.38 | M39: 63532.38 | N39: =+L39-M39 -> 0
A40: 25-08-2023 | B40: 2 au 29 juillet 2023 | C40: F4902 | D40: =1.5+14+40+79.75 -> 135.25 | E40: =652.75-D40 -> 517.5 | F40: =225+1750+5000+9968.75 -> 16943.75 | G40: =47677.76-F40-H40 -> 30144.71 | H40: =540.4+48.9 -> 589.3 | I40: =SUM(F40:H40) -> 47677.76 | J40: =+I40*0.05 -> 2383.888 | K40: =+I40*0.09975+0.001 -> 4755.8576 | L40: =SUM(I40:K40) -> 54817.506 | M40: 54817.506 | N40: =+L40-M40 -> 0
A41: 21-09-2023 | B41: 30 juillet au 2 septembre 2023 | C41: F4941 | D41: =2.5+15+54.5+118.5+1.5 -> 192 | E41: =866.75-D41 -> 674.75 | F41: =375+1875+6812.5+14812.5+187.5 -> 24062.5 | G41: =64511.87-F41-H41 -> 39589.38 | H41: =767.2+90.83+1.96 -> 859.99 | I41: =SUM(F41:H41) -> 64511.87 | J41: =+I41*0.05 -> 3225.5935 | K41: =+I41*0.09975+0.001 -> 6435.06 | L41: =SUM(I41:K41) -> 74172.524 | M41: 74172.524 | N41: =+L41-M41 -> 0
A42: 18-10-2023 | B42: 3 au 30 septembre 2023 | C42: F4972 | D42: 163.5 | E42: =793.5-D42 -> 630 | F42: 20462.5 | G42: =57944.31-F42-H42 -> 36795.41 | H42: 686.4 | I42: =SUM(F42:H42) -> 57944.31 | J42: =+I42*0.05 -> 2897.2155 | K42: =+I42*0.09975 -> 5779.9449 | L42: =SUM(I42:K42) -> 66621.47 | M42: 66621.47 | N42: =+L42-M42 -> 0
A43: 30-11-2023 | B43: 1er au 28 octobre 2023 | C43: F5014 | D43: =1+8.5+41.5+75.5 -> 126.5 | E43: =734-D43 -> 607.5 | F43: =150+1062.5+5187.5+9437.5 -> 15837.5 | G43: =51608.88-H43-F43 -> 34187.2 | H43: =1235.33+321.22+27.63 -> 1584.18 | I43: =SUM(F43:H43) -> 51608.88 | J43: 2579.06 | K43: 5145.23 | L43: =SUM(I43:K43) -> 59333.17 | M43: 59333.17 | N43: =+L43-M43 -> 0
A44: 21-12-2023 | B44: 29 octobre au 2 décembre 2023 | C44: F5058 | D44: =1.5+10.5+68+132.5+0.5 -> 213 | E44: =898-D44 -> 685 | F44: =225+1312.5+8500+16562.5+62.5 -> 26662.5 | G44: =68578.05-H44-F44 -> 40468.07 | H44: =1226.84+197.29+23.35 -> 1447.48 | I44: =SUM(F44:H44) -> 68578.05 | J44: 3427.74 | K44: 6838.33 | L44: =SUM(I44:K44) -> 78844.12 | M44: 78844.12 | N44: =+L44-M44 -> 0
A45: 31-12-2023 | B45: 3 au 31 décembre 2023 | C45: F5087 | D45: =2+15.5+33+51+0.75 -> 102.25 | E45: =491.25-D45 -> 389 | F45: =300+1937.5+4125+6375+93.75 -> 12831.25 | G45: =36268.87-F45-H45 -> 22892.16 | H45: =528.83+14.19+2.44 -> 545.46 | I45: =SUM(F45:H45) -> 36268.87 | J45: 1813.32 | K45: 3617.58 | L45: =SUM(I45:K45) -> 41699.77 | M45: 41699.77 | N45: =+L45-M45 -> 0
A46: 45322 | B46: au 31 janvier 2024 | C46: F5103 | D46: 127 | E46: =554.75-D46 -> 427.75 | F46: =125.5*125+225 -> 15912.5 | G46: =44527.19-F46-H46 -> 27012.55 | H46: 1602.14 | I46: =SUM(F46:H46) -> 44527.19 | J46: 2222.84 | K46: 4434.57 | L46: =SUM(I46:K46) -> 51184.6 | M46: 51184.6 | N46: =+L46-M46 -> 0
A47: 45351 | B47: au 29 février 2024 | C47: F5134 | D47: =46.5+108.75 -> 155.25 | E47: =611.25-D47 -> 456 | F47: 19418.75 | G47: =48282.41-H47-F47 -> 28120.88 | H47: 742.78 | I47: =SUM(F47:H47) -> 48282.41 | J47: 2413.02 | K47: 4813.98 | L47: =SUM(I47:K47) -> 55509.41 | M47: 55509.41 | N47: =+L47-M47 -> 0
A48: 45382 | B48: au 31 mars 2024 | C48: F5162 | D48: 112.5 | E48: =454.25-D48 -> 341.75 | F48: 14087.5 | G48: =35439.43-F48-H48 -> 20716.74 | H48: 635.19 | I48: =SUM(F48:H48) -> 35439.43 | J48: 1771.74 | K48: 3534.61 | L48: =SUM(I48:K48) -> 40745.78 | M48: 40745.78 | N48: =+L48-M48 -> 0
A49: 45412 | B49: au 30 avril 2024 | C49: F5205 | D49: 144.75 | E49: =404.5-D49 -> 259.75 | F49: =75+125+6562.5+11343.75 -> 18106.25 | G49: =35813.43-F49-H49 -> 17224.22 | H49: =463.22+19.74 -> 482.96 | I49: =SUM(F49:H49) -> 35813.43 | J49: 1790.67 | K49: 3572.39 | L49: =SUM(I49:K49) -> 41176.49 | M49: 41176.49 | N49: =+L49-M49 -> 0
A50: 45443 | B50: au 31 mai 2024 | C50: F5250 | D50: 129 | E50: =490.5-D50 -> 361.5 | F50: =75+187.5+7437.5+8437.5 -> 16137.5 | G50: =38607.88-F50-H50 -> 21649.81 | H50: 820.57 | I50: =SUM(F50:H50) -> 38607.88 | J50: 1926.88 | K50: 3844.12 | L50: =SUM(I50:K50) -> 44378.88 | M50: 44378.88 | N50: =+L50-M50 -> 0
A51: 45473 | B51: au 30 juin 2024 | C51: F5306 | D51: 107.5 | E51: =404-D51 -> 296.5 | F51: 13450 | G51: =32452.36-F51-H51 -> 18035.29 | H51: 967.07 | I51: =SUM(F51:H51) -> 32452.36 | J51: 1621.62 | K51: 3235.14 | L51: =SUM(I51:K51) -> 37309.12 | M51: 37309.12 | N51: =+L51-M51 -> 0
A52: 45504 | B52: au 31 juillet 2024 | C52: F5372 | D52: 122.5 | E52: =511.5-D52 -> 389 | F52: 15325 | G52: =41045.09-H52-F52 -> 23860.93 | H52: =1319.66+488.84+50.66 -> 1859.16 | I52: =SUM(F52:H52) -> 41045.09 | J52: 2049.72 | K52: 4089.19 | L52: =SUM(I52:K52) -> 47184 | M52: 47184 | N52: =+L52-M52 -> 0
A53: 45535 | B53: au 31 aout 2024 | C53: F5388 | D53: =0.5+3.5+41.5+36.75 -> 82.25 | E53: =219.5-D53 -> 137.25 | F53: =75+437.5+5187.5+4593.75 -> 10293.75 | G53: =19422.87-H53-F53 -> 9006.49 | H53: 122.63 | I53: =SUM(F53:H53) -> 19422.87 | J53: 971.14 | K53: 1937.43 | L53: =SUM(I53:K53) -> 22331.44 | M53: 22331.44 | N53: =+L53-M53 -> 0
A54: 45565 | B54: au 30 septembre 2024 | C54: F5445 | D54: =1+17.5+29.25 -> 47.75 | E54: =223.75-D54 -> 176 | F54: =150+2187.5+3656.25 -> 5993.75 | G54: =19461.53-H54-F54 -> 12980.81 | H54: =410.93+71.13+4.91 -> 486.97 | I54: =SUM(F54:H54) -> 19461.53 | J54: 972.83 | K54: 1940.8 | L54: =SUM(I54:K54) -> 22375.16 | M54: 22375.16 | N54: =+L54-M54 -> 0 | O54: 100000
A55: 45596 | B55: au 31 octobre 2024 | C55: F5512 | D55: 53.25 | E55: =255-D55 -> 201.75 | F55: =52.75*125+0.5*150 -> 6668.75 | G55: =21753.4-F55-H55 -> 14009.19 | H55: =856.2+177.91+41.35 -> 1075.46 | I55: =SUM(F55:H55) -> 21753.4 | J55: 1085.6 | K55: 2165.78 | L55: =SUM(I55:K55) -> 25004.78 | M55: 25004.78 | N55: =+L55-M55 -> 0
A56: 45626 | B56: au 30 novembre 2024 | C56: F5555 | D56: 33.75 | E56: =118.75-D56 -> 85 | F56: =32.75*125+1*150 -> 4243.75 | G56: =9990.31-F56 -> 5746.56 | H56: 0 | I56: =SUM(F56:H56) -> 9990.31 | J56: =+I56*0.05 -> 499.5155 | K56: =+I56*0.09975 -> 996.53342 | L56: =SUM(I56:K56) -> 11486.359 | M56: 11486.359 | N56: =+L56-M56 -> 0
A57: 45657 | B57: au 31 décembre 2024 | C57: F5578 | D57: 7 | E57: =41.75-D57 -> 34.75 | F57: =+D57*125 -> 875 | G57: =3215.1-F57 -> 2340.1 | I57: =SUM(F57:H57) -> 3215.1 | J57: =+I57*0.05 -> 160.755 | K57: =+I57*0.09975 -> 320.70623 | L57: =SUM(I57:K57) -> 3696.5612 | M57: 3696.5612 | N57: =+L57-M57 -> 0
A58: 45688 | B58: au 31 janvier 2025 | C58: F5625 | D58: =5+9.5 -> 14.5 | E58: =80-D58 -> 65.5 | F58: =+D58*125 -> 1812.5 | G58: =5820.58-H58-F58 -> 3929.68 | H58: 78.4 | I58: =SUM(F58:H58) -> 5820.58 | J58: =+I58*0.05 -> 291.029 | K58: =+I58*0.09975 -> 580.60285 | L58: =SUM(I58:K58) -> 6692.2119 | M58: 6692.2119 | N58: =+L58-M58 -> 0
A59: 45716 | B59: au 28 février 2025 | C59: F5657 | D59: 20.5 | E59: =75.25-D59 -> 54.75 | F59: =+D59*125 -> 2562.5 | G59: =5857.26-F59 -> 3294.76 | I59: =SUM(F59:H59) -> 5857.26 | J59: =+I59*0.05 -> 292.863 | K59: =+I59*0.09975 -> 584.26169 | L59: =SUM(I59:K59) -> 6734.3847 | M59: 6734.3847 | N59: =+L59-M59 -> 0
A60: 45747 | B60: au 31 mars 2025 | C60: F5686 | D60: =15.5+8.75 -> 24.25 | E60: =62.25-D60 -> 38 | F60: =+D60*125 -> 3031.25 | G60: =5672.73-F60 -> 2641.48 | I60: =SUM(F60:H60) -> 5672.73 | J60: =+I60*0.05 -> 283.6365 | K60: =+I60*0.09975 -> 565.85482 | L60: =SUM(I60:K60) -> 6522.2213 | M60: 6522.2213 | N60: =+L60-M60 -> 0
A61: 45777 | B61: au 30 avril 2025 | C61: F5729 | D61: 29.5 | E61: =63.75-D61 -> 34.25 | F61: =375+125+3250 -> 3750 | G61: =6210.51-F61 -> 2460.51 | I61: =SUM(F61:H61) -> 6210.51 | J61: =+I61*0.05 -> 310.5255 | K61: =+I61*0.09975 -> 619.49837 | L61: =SUM(I61:K61) -> 7140.5339 | M61: 7140.5339 | N61: =+L61-M61 -> 0
A62: 45808 | B62: au 31 mai 2025 | C62: F5772 | D62: =4.25+17.75+2 -> 24 | E62: =66-D62 -> 42 | F62: =150+406.25+2218.75+250 -> 3025 | G62: =5835.82-F62 -> 2810.82 | I62: =SUM(F62:H62) -> 5835.82 | J62: =+I62*0.05 -> 291.791 | K62: =+I62*0.09975 -> 582.12305 | L62: =SUM(I62:K62) -> 6709.734 | N62: =+L62-M62 -> 6709.734
A63: 45838 | B63: au 30 juin 2025 | C63: F5824 | D63: =4.5+14.75 -> 19.25 | E63: =69.25-D63 -> 50 | F63: =562.5+1843.75 -> 2406.25 | G63: =5919.59-F63 -> 3513.34 | I63: =SUM(F63:H63) -> 5919.59 | J63: =+I63*0.05 -> 295.9795 | K63: =+I63*0.09975 -> 590.4791 | L63: =SUM(I63:K63) -> 6806.0486 | N63: =+L63-M63 -> 6806.0486
A64: 45869 | B64: au 31 juillet 2025 | C64: F5899 | D64: 4.75 | E64: =40-D64 -> 35.25 | F64: =+D64*125 -> 593.75 | G64: =3000.1-F64 -> 2406.35 | I64: =SUM(F64:H64) -> 3000.1 | J64: =+I64*0.05 -> 150.005 | K64: =+I64*0.09975 -> 299.25997 | L64: =SUM(I64:K64) -> 3449.365 | N64: =+L64-M64 -> 3449.365
A65: 45900 | B65: au 31 aout 2025 | C65: F5938 | D65: 7.75 | E65: =28-D65 -> 20.25 | F65: =+D65*125 -> 968.75 | G65: =2100.68-F65 -> 1131.93 | I65: =SUM(F65:H65) -> 2100.68 | J65: =+I65*0.05 -> 105.034 | K65: =+I65*0.09975 -> 209.54283 | L65: =SUM(I65:K65) -> 2415.2568 | N65: =+L65-M65 -> 2415.2568
A66: 45930 | B66: au 30 septembre 2025 | C66: F5974 | D66: 7.5 | E66: =26-D66 -> 18.5 | F66: =+D66*125 -> 937.5 | G66: =2068.48-F66 -> 1130.98 | I66: =SUM(F66:H66) -> 2068.48 | J66: =+I66*0.05 -> 103.424 | K66: =+I66*0.09975 -> 206.33088 | L66: =SUM(I66:K66) -> 2378.2349 | N66: =+L66-M66 -> 2378.2349
D68: =SUM(D4:D67) -> 7116.75 | E68: =SUM(E4:E67) -> 23535.4 | F68: =SUM(F4:F67) -> 894837.5 | G68: =SUM(G4:G67) -> 1345461.2 | H68: =SUM(H4:H67) -> 45519.14 | I68: =SUM(I4:I67) -> 2285817.9 | J68: =SUM(J4:J67) -> 114210.75 | K68: =SUM(K4:K67) -> 227850.48 | ... N68: =SUM(N4:N67) -> 21758.639 | O68: =SUM(O5:O67) -> 875000
E69: =+E68+D68 -> 30652.15

Sheet Consultants
A2: Date | B2: Consultant | C2: Facture | D2: Mandat : | E2: Montant (avant taxes) | F2: Payée
A4: 26-01-2021 | B4: Consultant 1 | C4: 2101004 | E4: 323.75 | F4: Oui
A5: 11-05-2021 | B5: Consultant 1 | C5: 2105005 | E5: 416.25 | F5: Oui
A6: 26-04-2021 | B6: Consultant 1 | C6: 2104007 | E6: 9750 | F6: Oui
A7: 14-02-2022 | B7: Consultant 1 | C7: 22011 | E7: 370 | F7: Oui
A8: 13-05-2022 | B8: Consultant 1 | C8: 22037 | E8: 185 | F8: Oui
A9: 13-09-2022 | B9: Consultant 1 | C9: 22076 | E9: 416.25 | F9: Oui
A10: 04-11-2022 | B10: Consultant 1 | C10: 22092 | E10: 231.25 | F10: Oui
A11: 18-11-2022 | B11: Consultant 1 | C11: 22104 | E11: 4970 | F11: Oui
A12: 05-12-2022 | B12: Consultant 1 | C12: 22106 | E12: 1341.25 | F12: Oui
A13: 16-01-2023 | B13: Consultant 1 | C13: 23004 | E13: 971.25 | F13: Oui
A14: 06-02-2023 | B14: Consultant 1 | C14: 23015 | E14: 370 | F14: Oui
A15: 14-03-2023 | B15: Consultant 1 | C15: 23030 | E15: 370 | F15: Oui
... A31: 13-06-2025 | B31: Consultant 1 | C31: 25072 | E31: 2008.75 | F31: Oui
D32: Total | E32: =SUM(E4:E31) -> 52158.75
A34: Date | B34: Consultant | C34: Facture | D34: Mandat : | E34: Montant (avant taxes) | F34: Payée
A36: 29-01-2021 | B36: Consultant 2 | C36: ING-MTL-21-120 | E36: 4430 | F36: Oui
D38: Total | E38: =SUM(E36:E37) -> 4430
A40: Date | B40: Consultant | C40: Facture | D40: Mandat : | E40: Montant (avant taxes) | F40: Payée
A42: 31-10-2021 | B42: Consultant 3 | C42: 49122 | E42: 811.25 | F42: Oui
A43: 07-10-2020 | B43: Consultant 3 | C43: 48723 | E43: 1540 | F43: Oui
A44: 30-10-2021 | B44: Consultant 3 | C44: 49121 | E44: 5850 | F44: Oui
A45: 14-09-2020 | B45: Consultant 3 | C45: 48401 | E45: 387.5 | F45: Oui
A46: 12-01-2021 | B46: Consultant 3 | C46: 49821 | E46: 1333 | F46: Oui
A47: 02-12-2020 | B47: Consultant 3 | C47: 49431 | E47: 745 | F47: Oui
A48: 14-09-2020 | B48: Consultant 3 | C48: 48400 | E48: 1950 | F48: Oui
A49: 23-02-2021 | B49: Consultant 3 | C49: 50267 | E49: 1138.75 | F49: Oui
A50: 22-04-2021 | B50: Consultant 3 | C50: 51021 | E50: 3337.5 | F50: Oui
A51: 30-11-2021 | B51: Consultant 3 | C51: 53333 | E51: 33.75 | F51: Oui
A52: 22-02-2022 | B52: Consultant 3 | C52: 54149 | E52: 165 | F52: Oui
A53: 21-04-2022 | B53: Consultant 3 | C53: 55012 | E53: 165 | F53: Oui
... A59: 31-03-2025 | B59: Consultant 3 | C59: 66809 | E59: 2986.25 | F59: Oui
D60: Total | E60: =SUM(E42:E59) -> 45335.5
A62: Date | B62: Consultant | C62: Facture | D62: Mandat : | E62: Montant (avant taxes) | F62: Payée
A64: 28-02-2021 | B64: Consultant 4 | C64: 82 | E64: 15100 | F64: Oui
A65: 30-01-2021 | B65: Consultant 4 | C65: 80 | E65: 23211.25 | F65: Oui
A66: 22-12-2020 | B66: Consultant 4 | C66: 75 | E66: 19315 | F66: Oui
A67: 30-11-2020 | B67: Consultant 4 | C67: 70 | E67: 16812.5 | F67: Oui
A68: 31-03-2021 | B68: Consultant 4 | C68: 89 | E68: 2282.5 | F68: Oui
D70: Total | E70: =SUM(E64:E69) -> 76721.25
A72: Date | B72: Consultant | C72: Facture | D72: Mandat : | E72: Montant (avant taxes) | F72: Payée
A74: 26-01-2021 | B74: Consultant 5 | C74: 598424 | E74: 6480 | F74: Oui
A75: 08-09-2021 | B75: Consultant 5 | C75: 636840 | E75: 2380 | F75: Oui
A76: 20-04-2021 | B76: Consultant 5 | C76: 612631 | E76: 6105 | F76: Oui
A77: 21-05-2021 | B77: Consultant 5 | C77: 618856 | E77: 885 | F77: Oui
A78: 23-03-2021 | B78: Consultant 5 | C78: 608406 | E78: 4230 | F78: Oui
D80: Total | E80: =SUM(E74:E79) -> 20080
A82: Date | B82: Consultant | C82: Facture | D82: Mandat : | E82: Montant (avant taxes) | F82: Payée
A84: 28-10-2020 | B84: Consultant 6 | C84: 956725 | E84: 1445 | F84: Oui
A85: 24-11-2020 | B85: Consultant 6 | C85: 962677 | E85: 7855 | F85: Oui
A86: 24-11-2020 | B86: Consultant 6 | C86: 962664 | E86: 14775 | F86: Oui
A87: 28-10-2020 | B87: Consultant 6 | C87: 956719 | E87: 1760 | F87: Oui
A88: 24-11-2020 | B88: Consultant 6 | C88: 962665 | E88: 8160 | F88: Oui
A89: 28-10-2020 | B89: Consultant 6 | C89: 956709 | E89: 5100 | F89: Oui
A90: 24-11-2020 | B90: Consultant 6 | C90: 962674 | E90: 8790 | F90: Oui
A91: 28-10-2020 | B91: Consultant 6 | C91: 956717 | E91: 2390 | F91: Oui
A92: 20-01-2021 | B92: Consultant 6 | C92: 974769 | E92: 5400 | F92: Oui
A93: 20-01-2021 | B93: Consultant 6 | C93: 974713 | E93: 6900 | F93: Oui
A94: 20-01-2021 | B94: Consultant 6 | C94: 974723 | E94: 7200 | F94: Oui
A95: 20-01-2021 | B95: Consultant 6 | C95: 974760 | E95: 3600 | F95: Oui
... A120: 26-05-2022 | B120: Consultant 6 | C120: 1109375 | E120: 3168.75 | F120: Oui
A121: 30-05-2022 | B121: Consultant 6 | C121: 1041072 | E121: 1800 | F121: Oui | G121: Facture datée du 20 septembre 2021, reçue en mai 2022
A122: 30-05-2022 | B122: Consultant 6 | C122: 1067093 | E122: 1056.25 | F122: Oui | G122: Facture datée du 15 décembre 2021, reçue en mai 2022
A123: 31-03-2022 | B123: Consultant 6 | C123: 1095364 | E123: 3963.75 | F123: Oui | G123: Reçue en mai 2022
A124: 29-04-2022 | B124: Consultant 6 | C124: 1102666 | E124: 1380 | F124: Oui
A125: 20-06-2022 | B125: Consultant 6 | C125: 1116716 | E125: 2907.5 | F125: Oui
A126: 28-07-2022 | B126: Consultant 6 | C126: 1127568 | E126: 1380 | F126: Oui
A127: 30-08-2022 | B127: Consultant 6 | C127: 1136180 | E127: 1056.25 | F127: Oui
A128: 30-08-2022 | B128: Consultant 6 | C128: 1136182 | E128: 1380 | F128: Oui
A129: 30-08-2022 | B129: Consultant 6 | C129: 1136183 | E129: 2070 | F129: Oui
A130: 30-09-2022 | B130: Consultant 6 | C130: 1146070 | E130: 3963.75 | F130: Oui
A131: 04-11-2022 | B131: Consultant 6 | C131: 1155978 | E131: 795 | F131: Oui
A132: 29-11-2022 | B132: Consultant 6 | C132: 1163439 | E132: 2171.25 | F132: Oui
A133: 29-11-2022 | B133: Consultant 6 | C133: 1163440 | E133: 1380 | F133: Oui
A134: 29-11-2022 | B134: Consultant 6 | C134: 1163442 | E134: 3555 | F134: Oui
A135: 21-12-2022 | B135: Consultant 6 | C135: 1173204 | E135: 690 | F135: Oui
... A156: 28-10-2024 | B156: Consultant 6 | C156: 20171863 | E156: 690 | F156: Oui
D157: Total | E157: =SUM(E84:E156) -> 225745.01
A160: Date | B160: Consultant | C160: Facture | D160: Mandat : | E160: Montant (avant taxes) | F160: Payée
A162: 18-05-2023 | B162: Consultant 7 | C162: 125124 | E162: 4250 | F162: Oui
A163: 18-05-2023 | B163: Consultant 7 | C163: 125126 | E163: 4250 | F163: Oui
A164: 04-12-2024 | B164: Consultant 7 | C164: 126862 | E164: 4250 | F164: Oui
A165: 28-01-2025 | B165: Consultant 7 | C165: 126990 | E165: 4250 | F165: Oui
D166: Total | E166: =SUM(E162:E165) -> 17000
A169: Date | B169: Consultant | C169: Facture | D169: Mandat : | E169: Montant (avant taxes) | F169: Payée
A171: 04-12-2023 | B171: Consultant 8 | C171: 1049 | D171: Magog | E171: 3605 | F171: Oui
A172: 23-10-2024 | B172: Consultant 8 | C172: 1097 | D172: Granby | E172: 1852.5 | F172: Oui
A173: 23-10-2024 | B173: Consultant 8 | C173: 1098 | D173: Coaticook | E173: 1995 | F173: Oui
A174: 23-10-2024 | B174: Consultant 8 | C174: 1099 | D174: Sherbrooke | E174: 1710 | F174: Oui
D176: Total | E176: =SUM(E171:E175) -> 9162.5
E179: =+E157+E70+E32+E80+E60+E38+E166+E176 -> 450633.01
E180: =+E179-consolidé!Q68 -> 0
